Workbook
Name DOCUMENTOS_DEL_CONVENIO: #REF!
Name DOCUMENTOS_DEL_CONVENIO: #REF!
Name DURACION_PRORROGA: #REF!
Name DURACION_PRORROGA: #REF!
Name FECHA_DE_FIN: #REF!
Name FECHA_DE_FIN: #REF!
Name FECHA_DE_INICIO: #REF!
Name FECHA_DE_INICIO: #REF!
Name FIN_PRORROGA: #REF!
Name FIN_PRORROGA: #REF!
Name INICIO_PRORROGA_1: #REF!
Name INICIO_PRORROGA_1: #REF!
Name INICIO_PRORROGA_2: #REF!
Name INICIO_PRORROGA_2: #REF!
Name PropuestasInv: Propuestas!$A$1:$AJ$162
Name SegmentaciónDeDatos_AÑO: #REF!
Name SegmentaciónDeDatos_ENTIDAD: #REF!
Name SegmentaciónDeDatos_ESTADO: #REF!
Name SegmentaciónDeDatos_ROL_UDFJC: #REF!
Name SegmentaciónDeDatos_TIPO: #REF!
Name UBICACIÓN: #REF!
Name UBICACIÓN: #REF!

Sheet Hoja3
A3: Etiquetas de fila
A4: Avalada
A5: No Avalada
A6: No continuo el trámite
A7: Sin aval del Comité de Investigaciones
A8: Contrato firmado
A9: Desistio
A10: Seleccionada
A11: En tramite
A12: Total general

Sheet Propuestas
A1: AÑO | B1: TIPO | C1: ESTADO | D1: No. CONVOCATORIA | E1: NOMBRE CONVOCATORIA | F1: ENTIDAD | G1: ROL UDFJC | H1: ALIADO | I1: PROGRAMA | J1: MESES | K1: GRUPOS DE INVESTIGACIÓN | L1: VALOR PROYECTO | M1: RECURSOS EN EFECTIVO FINANCIADO A UDFJC | N1: VALOR PROYECTO EFECTIVO | O1: VALOR PROYECTO ESPECIE | P1: SOLICITADO A ENTIDAD | Q1: UDFJC EFECTIVO | R1: UDFJC ESPECIE | S1: SOLICITADO ALIADO 1 EFECTIVO | T1: SOLICITADO ALIADO 1 ESPECIE | U1: SOLICITADO ALIADO 2 EFECTIVO | V1: SOLICITADO ALIADO 2 ESPECIE | W1: SOLICITADO ALIADO 3 EFECTIVO | X1: SOLICITADO ALIADO 3 ESPECIE | Y1: SOLICITADO ALIADO 4 EFECTIVO | Z1: SOLICITADO ALIADO 4 ESPECIE | AA1: RESULTADOS ESPERADOS | AB1: PRODUCTOS ESPERADOS | AC1: % Aportes Colciencias | AD1: % Aportes UDFJC | AE1: % Aportes UDFJC Efectivo | AF1: % Aportes UDFJC Especie | AG1: % Aportes Aliado 1 | AH1: % Aportes Aliado 2 | AI1: % Aportes Aliado 3 | AJ1: % Aportes Aliado 4
A2: 2021 | B2: Propuesta de Investigación Alianza Convenio | C2: Contrato firmado | D2: N/A | E2: Presentación propuesta al Proyecto de Inversión 1763 “Un nuevo contrato para mujeres cuidadoras en Fontibón”, 1782 "Un nuevo contrato para la participación ciudadana en Fontibón" y 1758 "Un nuevo contrato para la Cultura en Fontibón" | F2: Alcaldía de Fontibón | G2: Ejecutor | H2: Alcaldía de Fontibón | I2: N/A | J2: 6 | K2: UDFJC: - Vivencias | L2: =+SUM(P2:Z2) -> 440000000 | M2: 320000000 | N2: =+P2+Q2+S2+U2+W2+Y2 -> 384000000 | O2: =+R2+T2+V2+X2+Z2 -> 56000000 | P2: 320000000 | Q2: 64000000 | R2: 56000000 | S2: 0 | T2: 0 | U2: 0 | V2: 0 | W2: 0 | X2: 0 | Y2: 0 | Z2: 0 | AA2: TALLERES: 1. ¿Cómo renovar el sentido de la participación social comunitaria en torno a los conceptos de lo común y la comunidad? 2. La cuestión de los derechos humanos, económicos sociales y culturales en la construcción de territorios de la participación 3. Participación, convivencia y noviolencia 4. Gestión cultural y gestión política 5. Formas económicas en la gestión cultural 6. Tejiendo desarrollo 7. ¿Como pasar del sufrimiento y la enfermedad a la salud y la felicidad, a través del autocuidado? 8. Autocuidado y Desarrollo personal 9. Cuidado personal y autoconocimiento 10. El auto cuidado y el cuidado de otr@s: Una propuesta de plenitud 11. El auto cuidado y la sanación: Una mirada integral cuerpo, mente y espiritualidad. | AB2: - Documento para ser publicado que enfatiza en elementos de orden político, ético, existencial, estético de los diferentes componentes que integran el convenio, abordando los componentes de cuidado, participación y cultura - Se deberá diseñar, elaborar y entregar una cartilla por cada uno de los componentes del proyecto; la descripción técnica tendrá un formato abierto de 22x30 cm y cerrada de 22 X15 cm, con terminado caballete de 15 hojas tiro y retiro, impreso por las dos caras en dos tintas, con portada y contraportada en tres colores - Se creará un artículo académico para difundir en revista con ISBN, por cada uno de los componentes trabajados en el proceso de investigación-formación - Se desplegará un proceso de difusión y comunicación, a través del espacio radial, Voces y Devenires, el Doctorado en Estudios Sociales cuenta con un programa propio “Rizoma” en el cual se estarán transmitiendo noticias del proyecto “Fontibón como espacio cultural, democrático y del cuidado”, además de entrevistas a participantes del proceso investigativo-formativo. - El documento deberá contener los testimonios e insumos testimoniales recogidos a lo largo del proceso de investigación formación - Desarrollo de un proceso de formación orientado a hombres y mujeres de la localidad de Fontibón. Se busca la profundización en la configuración de imaginarios, prácticas y acciones sobre el cuidado, cultura y participación, estableciendo un proceso reflexivo entre las dinámicas institucionales y las vivencias de la ciudadanía de Cuidado y en la interacción cuidado-autocuidado en diversos contextos - Con el apoyo de un equipo de profesionales se trabajará con 30 cuidadores/as que estén participando en el proceso formativo e investigativo. Se impulsa una reflexión y un trabajo teórico y práctico que involucre una concepción crítica de Cuidado y Autocuidado que transite más allá de los sesgos de género o sexo y que muestre sus claras implicaciones éticas, políticas y existenciales. - Desarrollo de cinco tipos de talleres dirigidos a hombres y mujeres que asisten al proceso formativo/investigativo. Estos talleres que enfatizan en aspectos vivenciales, existenciales, éticos y políticos, configuran aspectos que deben ser centrales en un cuidador/a. Son procesos de corte afectivo que le apuntan a la desubjetivación y, además, a formas mutantes que permitan tránsitos más allá de significados y representaciones que circulan sobre el Cuidado en un plano de organización. - Cartografías sociales | AC2: =+IFERROR(P2/L2,0%) -> 0.72727273 | AD2: =+IFERROR((Q2+R2)/L2,0%) -> 0.27272727 | AE2: =IFERROR(Q2/(Q2+R2),0%) -> 0.53333333 | AF2: =IFERROR(R2/(Q2+R2),0%) -> 0.46666667 | AG2: =+IFERROR((S2+T2)/L2,0%) -> 0 | AH2: =+IFERROR((U2+V2)/L2,0%) -> 0 | AI2: =+IFERROR((W2+X2)/L2,0%) -> 0 | AJ2: =+IFERROR((Y2+Z2)/L2,0%) -> 0
A3: 2018 | B3: Propuesta de Investigación Convocatoria | C3: No Avalada | D3: 802 | E3: N/A | F3: MinCiencias | G3: Co-ejecutor | H3: 1- Universidad Minuto de Dios 2- Corporación Centauro Bacatá Alcaldía de Choachí - Alcaldía de Fómeque | I3: N/A | J3: 18 | K3: N/A | L3: =+SUM(P3:Z3) -> 547842614 | M3: 0 | N3: =+P3+Q3+S3+U3+W3+Y3 -> 442541614 | O3: =+R3+T3+V3+X3+Z3 -> 105301000 | P3: 349991614 | Q3: 52650000 | R3: 24301000 | S3: 39900000 | T3: 81000000 | U3: 0 | V3: 0 | W3: 0 | X3: 0 | Y3: 0 | Z3: 0 | AA3: * Participación ciudadana en productos CTel * Alianza con el municipio para promover la apropiación social del conocimiento por parte de la población. * Promover la creación de dos (2) comités de vigilancia, cuidado y recuperación de los acuíferos existentes en el área de influencia del estudio * Formación de 4 estudiantes de pregrado * Formación de 2 estudiantes de maestría | AB3: * Mapa geomorfológico que identifique los acuíferos presentes en el área de estudio y su interrelación. * Cartilla de cuidado y uso de los acuíferos * Un libro * Un artículo | AC3: =+IFERROR(P3/L3,0%) -> 0.63885431 | AD3: =+IFERROR((Q3+R3)/L3,0%) -> 0.14046187 | AE3: =IFERROR(Q3/(Q3+R3),0%) -> 0.68420163 | AF3: =IFERROR(R3/(Q3+R3),0%) -> 0.31579837 | AG3: =+IFERROR((S3+T3)/L3,0%) -> 0.22068382 | AH3: =+IFERROR((U3+V3)/L3,0%) -> 0 | AI3: =+IFERROR((W3+X3)/L3,0%) -> 0 | AJ3: =+IFERROR((Y3+Z3)/L3,0%) -> 0
A4: 2018 | B4: Propuesta de Investigación Convocatoria | C4: No Avalada | D4: 802 | E4: N/A | F4: MinCiencias | G4: Co-ejecutor | H4: 1- Universidad Minuto de Dios 2- Corporación Centauro Bacatá Beneficiarios: I.E.D IGNACIO PESCADOR DE CHOACHI I.E.D MONSEÑOR AGUSTIN GUTIERREZ DE FOMEQUE | I4: N/A | J4: 18 | K4: N/A | L4: =+SUM(P4:Z4) -> 507842614 | M4: 0 | N4: =+P4+Q4+S4+U4+W4+Y4 -> 402641614 | O4: =+R4+T4+V4+X4+Z4 -> 105201000 | P4: 349991614 | Q4: 52650000 | R4: 8101000 | S4: 0 | T4: 97100000 | U4: 0 | V4: 0 | W4: 0 | X4: 0 | Y4: 0 | Z4: 0 | AA4: * Participación ciudadana en productos Ctel * Alianza con centro dedicado a la apropiación social del conocimiento * Formación de 4 estudiantes de pregrado * Formación de dos estudiantes de maestría | AB4: * Mapa de cobertura vegetal * Un libro * Un articulo * Guía de cuidado, uso de especies vegetales | AC4: =+IFERROR(P4/L4,0%) -> 0.68917339 | AD4: =+IFERROR((Q4+R4)/L4,0%) -> 0.11962564 | AE4: =IFERROR(Q4/(Q4+R4),0%) -> 0.8666524 | AF4: =IFERROR(R4/(Q4+R4),0%) -> 0.1333476 | AG4: =+IFERROR((S4+T4)/L4,0%) -> 0.19120097 | AH4: =+IFERROR((U4+V4)/L4,0%) -> 0 | AI4: =+IFERROR((W4+X4)/L4,0%) -> 0 | AJ4: =+IFERROR((Y4+Z4)/L4,0%) -> 0
A5: 2018 | B5: Propuesta de Investigación Convocatoria | C5: No Avalada | D5: 806 | E5: N/A | F5: MinCiencias | G5: Ejecutor | H5: Programa ECOSNORD Francia | I5: N/A | J5: 36 | K5: N/A | L5: =+SUM(P5:Z5) -> 78000000 | M5: 0 | N5: =+P5+Q5+S5+U5+W5+Y5 -> 0 | O5: =+R5+T5+V5+X5+Z5 -> 78000000 | P5: 0 | Q5: 0 | R5: 78000000 | S5: 0 | T5: 0 | U5: 0 | V5: 0 | W5: 0 | X5: 0 | Y5: 0 | Z5: 0 | AA5: * Proyecto de documental UVED Parque Chingaza (equivalente del proyecto UVED Reerva de la Biosfera Mapimí) * Publicaciones (VIA revista sobre el ecosistema, Geocarrefour, …) * Coordinación de un Simposio en el 9º Congreso Internacional del Consejo Europeo de Investigaciones Sociales de América Latina (CEISAL) Alvaro Gutiérrez/Teresa Alarcón 2019 * Coordinación de un número de la revista ORDA 2021 | AB5: 0 | AC5: =+IFERROR(P5/L5,0%) -> 0 | AD5: =+IFERROR((Q5+R5)/L5,0%) -> 1 | AE5: =IFERROR(Q5/(Q5+R5),0%) -> 0 | AF5: =IFERROR(R5/(Q5+R5),0%) -> 1 | AG5: =+IFERROR((S5+T5)/L5,0%) -> 0 | AH5: =+IFERROR((U5+V5)/L5,0%) -> 0 | AI5: =+IFERROR((W5+X5)/L5,0%) -> 0 | AJ5: =+IFERROR((Y5+Z5)/L5,0%) -> 0
A6: 2018 | B6: Propuesta de Investigación Convocatoria | C6: No Avalada | D6: 806 | E6: N/A | F6: MinCiencias | G6: Ejecutor | H6: Programa ECOSNORD Alemania | I6: N/A | J6: 24 | K6: N/A | L6: =+SUM(P6:Z6) -> 108915069 | M6: 0 | N6: =+P6+Q6+S6+U6+W6+Y6 -> 69657534 | O6: =+R6+T6+V6+X6+Z6 -> 39257535 | P6: 69657534 | Q6: 0 | R6: 39257535 | S6: 0 | T6: 0 | U6: 0 | V6: 0 | W6: 0 | X6: 0 | Y6: 0 | Z6: 0 | AA6: 0 | AB6: 0 | AC6: =+IFERROR(P6/L6,0%) -> 0.63955828 | AD6: =+IFERROR((Q6+R6)/L6,0%) -> 0.36044172 | AE6: =IFERROR(Q6/(Q6+R6),0%) -> 0 | AF6: =IFERROR(R6/(Q6+R6),0%) -> 1 | AG6: =+IFERROR((S6+T6)/L6,0%) -> 0 | AH6: =+IFERROR((U6+V6)/L6,0%) -> 0 | AI6: =+IFERROR((W6+X6)/L6,0%) -> 0 | AJ6: =+IFERROR((Y6+Z6)/L6,0%) -> 0
A7: 2018 | B7: Propuesta de Investigación Convocatoria | C7: No Avalada | D7: 807 | E7: N/A | F7: MinCiencias | G7: Ejecutor | H7: HOME ROBOTIK SAS | I7: N/A | J7: 24 | K7: N/A | L7: =+SUM(P7:Z7) -> 774423518 | M7: 0 | N7: =+P7+Q7+S7+U7+W7+Y7 -> 599623518 | O7: =+R7+T7+V7+X7+Z7 -> 174800000 | P7: 528252518 | Q7: 51371000 | R7: 124400000 | S7: 20000000 | T7: 50400000 | U7: 0 | V7: 0 | W7: 0 | X7: 0 | Y7: 0 | Z7: 0 | AA7: * PROTOTIPO FUNCIONAL DE UN SISTEMA SUMERGIBLE DE _VISIÓN ARTIFICIAL PARA LA MEDICIÓN Y PROCESAMÍENTO BIOMECÁNICO DEL TREN INFERIOR HUMANO DURANTE LA REHABILITACIÓN EN PISCINA PARA ENFERMEDADES NEUROMUSCULARES * Sistema de Visión Artificial Sumergible * Sistema de Seguimiento Automático del Objetivo * Sistema de Procesamiento y Visualización de Datos. * Sistema de Telemedicina | AB7: * Artículo de investigación * Libro resultado de investigación * Ejemplar del libro resultado de la investigación o carta de aceptación de publicación del libro expedida por el comité editorial * Producto tecnológico patentado o en proceso de solicitud de patente * Prototipo de sistema * Registro de Software | AC7: =+IFERROR(P7/L7,0%) -> 0.68212355 | AD7: =+IFERROR((Q7+R7)/L7,0%) -> 0.22697012 | AE7: =IFERROR(Q7/(Q7+R7),0%) -> 0.29226095 | AF7: =IFERROR(R7/(Q7+R7),0%) -> 0.70773905 | AG7: =+IFERROR((S7+T7)/L7,0%) -> 0.09090633 | AH7: =+IFERROR((U7+V7)/L7,0%) -> 0 | AI7: =+IFERROR((W7+X7)/L7,0%) -> 0 | AJ7: =+IFERROR((Y7+Z7)/L7,0%) -> 0
A8: 2018 | B8: Propuesta de Investigación Convocatoria | C8: No Avalada | D8: 808 | E8: N/A | F8: MinCiencias | G8: Ejecutor | H8: N/A | I8: N/A | J8: 30 | K8: N/A | L8: =+SUM(P8:Z8) -> 439445398 | M8: 0 | N8: =+P8+Q8+S8+U8+W8+Y8 -> 259271998 | O8: =+R8+T8+V8+X8+Z8 -> 180173400 | P8: 241989411 | Q8: 17282587 | R8: 180173400 | S8: 0 | T8: 0 | U8: 0 | V8: 0 | W8: 0 | X8: 0 | Y8: 0 | Z8: 0 | AA8: * Formación culminada del estudiante de doctorado en el marco del proyecto. * Vinculación del joven investigador al proyecto * Formación culminada del estudiante de pregrado al proyecto * Tesis de maestría en ejecución, enmarcada en el proyecto financiado * Organización de eventos especializados * Presentación de los resultados ante las autoridades competentes * Documento sobre la patente y/o Registro de propiedad intelectual | AB8: * Dos (2) artículos publicados en revistas A de PUBLINDEX (Q1 o Q2). * Dos (2) artículos publicados en revistas B de PUBLINDEX (Q3) * Libro - documento final tesis Doctoral | AC8: =+IFERROR(P8/L8,0%) -> 0.55067003 | AD8: =+IFERROR((Q8+R8)/L8,0%) -> 0.44932997 | AE8: =IFERROR(Q8/(Q8+R8),0%) -> 0.087526275 | AF8: =IFERROR(R8/(Q8+R8),0%) -> 0.91247373 | AG8: =+IFERROR((S8+T8)/L8,0%) -> 0 | AH8: =+IFERROR((U8+V8)/L8,0%) -> 0 | AI8: =+IFERROR((W8+X8)/L8,0%) -> 0 | AJ8: =+IFERROR((Y8+Z8)/L8,0%) -> 0
A9: 2018 | B9: Propuesta de Investigación Convocatoria | C9: No Avalada | D9: 804 | E9: N/A | F9: MinCiencias | G9: Co-ejecutor | H9: 1- Konrad Lorenz - Ejecutor 2- Universidad Católica de Oriente - Coejecutor 3- Log On Colombia | I9: N/A | J9: 18 | K9: N/A | L9: =+SUM(P9:Z9) -> 8.6255883e+08 | M9: 0 | N9: =+P9+Q9+S9+U9+W9+Y9 -> 536553394 | O9: =+R9+T9+V9+X9+Z9 -> 3.2600543e+08 | P9: 536553394 | Q9: 0 | R9: 131800000 | S9: 0 | T9: 1.7440543e+08 | U9: 0 | V9: 0 | W9: 0 | X9: 19800000 | Y9: 0 | Z9: 0 | AA9: * Perfil sociodemográfico y psicográfico de los estudiantes de educación virtual de dos zonas de Antioquia, identificando su perfil tecnológico, su historia de interacción con entornos virtuales y sus competencias de autorregulación * Evidencia, a partir de las actividades de investigación y la metodología descrita, de los componentes pedagógicos necesarios para la implementación del programa. | AB9: * Dos artículos sometidos a revistas de impacto (Q1-Q2). * Informe final sobre el diseño, construcción y validación del programa de intervención pedagógica para la prevención de la deserción y aumento del éxito estudiantil. * Mundo virtual 3D para la implementación y uso del programa de intervención pedagógica para la prevención de la deserción y aumento del éxito estudiantil. * Informe final sobre las recomendaciones para el uso del programa de intervención pedagógica para la prevención de la deserción y aumento del éxito estudiantil. * Participación en dos eventos científicos. | AC9: =+IFERROR(P9/L9,0%) -> 0.62204846 | AD9: =+IFERROR((Q9+R9)/L9,0%) -> 0.15280117 | AE9: =IFERROR(Q9/(Q9+R9),0%) -> 0 | AF9: =IFERROR(R9/(Q9+R9),0%) -> 1 | AG9: =+IFERROR((S9+T9)/L9,0%) -> 0.20219541 | AH9: =+IFERROR((U9+V9)/L9,0%) -> 0 | AI9: =+IFERROR((W9+X9)/L9,0%) -> 0.022954956 | AJ9: =+IFERROR((Y9+Z9)/L9,0%) -> 0
A10: 2018 | B10: Propuesta de Investigación Convocatoria | C10: No Avalada | D10: 807 | E10: N/A | F10: MinCiencias | G10: Ejecutor | H10: 1- Empresa ING - Elkin Yamith Gualteros Vanegas 2- Hospital Central de la Policia Nacional HOCEN | I10: N/A | J10: 34 | K10: N/A | L10: =+SUM(P10:Z10) -> 355285227 | M10: 0 | N10: =+P10+Q10+S10+U10+W10+Y10 -> 288285227 | O10: =+R10+T10+V10+X10+Z10 -> 67000000 | P10: 229335227 | Q10: 23000000 | R10: 42000000 | S10: 26200000 | T10: 0 | U10: 0 | V10: 0 | W10: 9750000 | X10: 25000000 | Y10: 0 | Z10: 0 | AA10: * Tener un protocolo indicador de los pacientes con neumon a adquirida en comunidad que pueden acceder en el sistema hospitalizaci on domiciliaria. * Dispositivos biom etricos basados en el IoT que obtengan constantemente los signos vitales del paciente. * Un software que se encargue de registrar y administrar la evoluci on del paciente teniendo en cuenta la monitorizaci on constante de los dispositivos conectados a la red y que el centro asistencial pueda observar los datos recogidos. * Documento que gestione la parte administrativa de los instrumentos y sirva de guía para respuesta inmediata en caso de emergencia u otra eventualidad. * Evidencia de una prueba piloto en el que se especi que la evoluci on de los pacientes, los gastos y la viabilidad del proyecto a una escala mayor. | AB10: PONENCIAS: Participacion congresos internacionales para la divulgaci on de resultados. PONENCIAS: Participacion en congresos nacionales para la divulgaci on de resultados. ARTICULO ORIGINAL EN REVISTA INDEXADA:Articulo original publicado en cualquier revista clasi cadas como A1, A2, B, C. PRODUCTOS TECNOL OGICOS CERTIFICADOS O VALIDADOS: Plataforma virtual (software) de conexi on paciente-centro asistencial. PRODUCTOS TECNOL OGICOS CERTIFICADOS O VALIDADOS : Validaci on de los dispositivos de monitorizaci on de signos vitales a pacientes con neumonia adquirida en comunidad. CARTILLA: Elaboraci on y divulgaci on de una cartilla donde se evidencie la propuesta de un nuevo modelo de hospitalizaci on domiciliaria con sus respectivos protocolos y normas. REALIZACI ON DE CURSOS DE CAPACITACI ON, SEMINARIOS Y TALLERES : Realizar una capacitaci on al personal de la salud de acuerdo a la investigaci on y procedimientos de nuestro proyecto. PRESENTACI ON DE LOS RESULTADOS A LAS AUTORIDADES LOCALES, NACIONALES Y SECTORIALES: Presentar resultados del estudio acerca de la viabilidad de un modelo de | AC10: =+IFERROR(P10/L10,0%) -> 0.6454961 | AD10: =+IFERROR((Q10+R10)/L10,0%) -> 0.1829516 | AE10: =IFERROR(Q10/(Q10+R10),0%) -> 0.35384615 | AF10: =IFERROR(R10/(Q10+R10),0%) -> 0.64615385 | AG10: =+IFERROR((S10+T10)/L10,0%) -> 0.073743567 | AH10: =+IFERROR((U10+V10)/L10,0%) -> 0 | AI10: =+IFERROR((W10+X10)/L10,0%) -> 0.097808739 | AJ10: =+IFERROR((Y10+Z10)/L10,0%) -> 0
A11: 2018 | B11: Propuesta de Investigación Convocatoria | C11: No Avalada | D11: 808 | E11: N/A | F11: MinCiencias | G11: Ejecutor | H11: Grupos de investigación UDFJC: 1- GCEM 2- LIFAE 3- GITUD | I11: N/A | J11: 24 | K11: N/A | L11: =+SUM(P11:Z11) -> 3.8771405e+08 | M11: 0 | N11: =+P11+Q11+S11+U11+W11+Y11 -> 239984850 | O11: =+R11+T11+V11+X11+Z11 -> 1.477292e+08 | P11: 239984850 | Q11: 0 | R11: 1.477292e+08 | S11: 0 | T11: 0 | U11: 0 | V11: 0 | W11: 0 | X11: 0 | Y11: 0 | Z11: 0 | AA11: * Profundo conocimiento de las funciones de diseño, construcción e implementación de sistemas de registro inteligentes, al igual que un procedimiento técnico ara la selección del hardware y software requerido en el proyecto * Validación y mejora de los sistemas de apantallamiento y aislamiento gracias a las pruebas en laboratorio, simulación a través de herramientas computacionales. Identificación de los sistemas de conexión y la metodología de montaje óptima. * El estudio preliminar de mercado permitirá realizar la búsqueda de principales actores de mercado, fortalezas, debilidades y diferencias con los competidores. Se realizará un análisis de la distribución geográfica, temporal y tipología del mercado. Por último, se realizará la búsqueda de competidores * Se conseguirá identificar los procesos y requisitos necesarios para realizar la protección intelectual del conocimiento generado | AB11: * Formación culminada del estudiante de maestría (2) * Participación en eventos especializados, presentando los resultados de la investigación (2) * Se dictará un curso de diseño de PCBs de veinte (20) horas * Artículos de investigación A2 (2) * SOFTWARE: Código fuente o manual de instalación. Registro de software ante entidades competentes * PROTOTIPO: Planos de diseño o sus fotografías o demás soportes de existencia | AC11: =+IFERROR(P11/L11,0%) -> 0.61897383 | AD11: =+IFERROR((Q11+R11)/L11,0%) -> 0.38102617 | AE11: =IFERROR(Q11/(Q11+R11),0%) -> 0 | AF11: =IFERROR(R11/(Q11+R11),0%) -> 1 | AG11: =+IFERROR((S11+T11)/L11,0%) -> 0 | AH11: =+IFERROR((U11+V11)/L11,0%) -> 0 | AI11: =+IFERROR((W11+X11)/L11,0%) -> 0 | AJ11: =+IFERROR((Y11+Z11)/L11,0%) -> 0
A12: 2018 | B12: Propuesta de Investigación Convocatoria | C12: No Avalada | D12: 807 | E12: N/A | F12: MinCiencias | G12: Ejecutor | H12: 1- Grupo GITEM++ 2- Laboratorio de Investigación en Fuentes Alternativas de Energía (LIFAE) | I12: N/A | J12: 36 | K12: N/A | L12: =+SUM(P12:Z12) -> 386200000 | M12: 0 | N12: =+P12+Q12+S12+U12+W12+Y12 -> 285400000 | O12: =+R12+T12+V12+X12+Z12 -> 100800000 | P12: 257400000 | Q12: 28000000 | R12: 100800000 | S12: 0 | T12: 0 | U12: 0 | V12: 0 | W12: 0 | X12: 0 | Y12: 0 | Z12: 0 | AA12: 1- Criterios de diagnóstico que propendan por disminución de la probabilidad de falsos negativos. 2- Nueva técnica matemática que permita extraer la información relevante para el diagnóstico desde la imagen medica de la retina. 3- Software que permita modelar un vaso sanguíneo desde el modelo matemático producto del segundo objetivo y a su vez permita verificar dicho modelo matemático como herramienta de diagnóstico de la retinopatía diabética. 4- Modelo matemático del comportamiento dinámico de la irrigación sanguínea en cercanías de la retina, que permita determinar el estadio patológico actual de la retinopatía diabética y que permita predecir la evolución de la patología en un paciente particular. 5- Software que permita verificar el modelo obtenido. | AB12: 1- Formación de estudiante de doctorado: Formación culminada de estudiante de doctorado en el marco del proyecto. 2- Ponencias: Se realizará dos ponencias de presentación de resultados de la investigación en sendos eventos académicos internacionales. 3- Participación en eventos científicos: Se participará en por lo menos un evento científicos internacional del área de la salud ocular, donde se presentarán resultados de la investigación. 4- Articulo original en revista indexada: Se presentará artículo en categoría A2 y articulo en categoría Al. 5- Capítulo en libro resultado de investigación: Se entregará capítulo de libro o borrador sometido a evaluación. | AC12: =+IFERROR(P12/L12,0%) -> 0.66649404 | AD12: =+IFERROR((Q12+R12)/L12,0%) -> 0.33350596 | AE12: =IFERROR(Q12/(Q12+R12),0%) -> 0.2173913 | AF12: =IFERROR(R12/(Q12+R12),0%) -> 0.7826087 | AG12: =+IFERROR((S12+T12)/L12,0%) -> 0 | AH12: =+IFERROR((U12+V12)/L12,0%) -> 0 | AI12: =+IFERROR((W12+X12)/L12,0%) -> 0 | AJ12: =+IFERROR((Y12+Z12)/L12,0%) -> 0
A13: 2018 | B13: Propuesta de Investigación Convocatoria | C13: No Avalada | D13: 807 | E13: N/A | F13: MinCiencias | G13: Ejecutor | H13: 1- Universidad del Valle 2- Hospital Universitario del Valle Evaristo García ESE 3- Universidad de la Rioja | I13: N/A | J13: 36 | K13: N/A | L13: =+SUM(P13:Z13) -> 1694823566 | M13: 0 | N13: =+P13+Q13+S13+U13+W13+Y13 -> 555364566 | O13: =+R13+T13+V13+X13+Z13 -> 1139459000 | P13: 539364566 | Q13: 0 | R13: 494102000 | S13: 0 | T13: 339597000 | U13: 0 | V13: 193440000 | W13: 16000000 | X13: 112320000 | Y13: 0 | Z13: 0 | AA13: 1. Vinculación 2 Jóvenes Investigadores (UDISTRITAL Y UNIVALLE) 2.Vinculación Estudiante de Maestría 3. Formación Culminada Estudiante de Pregrado 4. Participación en eventos científicos, presentando los resultados de la investigación CUATRO (4) 5. Dos cursos de capacitación, seminarios o talleres realizados. 6. Artículo Original en Revista Indexada A1 7. Artículo Original en Revista Indexada A2 8. DOS Artículos Original en Revista Indexada B 9.Registro de Software 10. Empresas de base tecnológica (spin-off), | AB13: 1. Contrato de vinculación del joven investigador e informe de las actividades desarrolladas en el marco del proyecto. 2.Documento que certifique que el trabajo de grado se realiza en el marco del proyecto, emitido por la autoridad en investigación de la institución educativa e informe de actividades realizadas. 3. Documento que certifique el trabajo de grado realizado por el estudiante de pregrado en el marco del proyecto y el acta de grado. 4. Producto: Certificado como de participación como ponente y soporte del trabajo presentado (memorias, programa de los eventos). 5. Programa del curso, capacitación, seminario o taller; intensidad horaria, duración y lista de asistencia. 6. Copia del artículo original aceptado en revista categorizada o la carta de aceptación del artículo. 7. Copia del artículo original aceptado en revista categorizada o la carta de aceptación del artículo. 8.Copia del artículo original aceptado en revista categorizada o la carta de aceptación del artículo. 9.Certificación de registro aprobado por la institución otorgante. 10. Registro del producto o de la empresa ante la entidad competente, certificación institucional firmada por el representante legal que declare la implementación de la innovación en pequeñas, medianas y grandes empresas. | AC13: =+IFERROR(P13/L13,0%) -> 0.31824231 | AD13: =+IFERROR((Q13+R13)/L13,0%) -> 0.29153595 | AE13: =IFERROR(Q13/(Q13+R13),0%) -> 0 | AF13: =IFERROR(R13/(Q13+R13),0%) -> 1 | AG13: =+IFERROR((S13+T13)/L13,0%) -> 0.20037307 | AH13: =+IFERROR((U13+V13)/L13,0%) -> 0.11413577 | AI13: =+IFERROR((W13+X13)/L13,0%) -> 0.075712896 | AJ13: =+IFERROR((Y13+Z13)/L13,0%) -> 0
A14: 2018 | B14: Propuesta de Investigación Convocatoria | C14: No Avalada | D14: 808 | E14: N/A | F14: MinCiencias | G14: Ejecutor | H14: 1- Grupo GIIRA 2- Grupo GITUD | I14: N/A | J14: 36 | K14: N/A | L14: =+SUM(P14:Z14) -> 477567000 | M14: 0 | N14: =+P14+Q14+S14+U14+W14+Y14 -> 241535000 | O14: =+R14+T14+V14+X14+Z14 -> 236032000 | P14: 241535000 | Q14: 0 | R14: 236032000 | S14: 0 | T14: 0 | U14: 0 | V14: 0 | W14: 0 | X14: 0 | Y14: 0 | Z14: 0 | AA14: 1- Modelo conceptual de representación del información espacial y espectral basado en una adecuada captura de datos considerando las propiedades físicas y temporales de la vegetación a evaluar. 2- Modelos digitales de elevación y ortofotomosaicos con un muestreo hiper-temporal para su análisis, 3- Identificación de los índices espectrales con una relación influyente para una estimación cuantitativa en la condición de la vegetación. 4- Metodología adecuada para el procesamiento de la información, que generen índices de calidad y permitan realizar detecciones de cambio en la condición de la vegetación. 5- Documento que contenga los lineamientos metodológicos para la captura, análisis y evaluación de la condición vegetal en sistemas agroecológicos mediante imágenes obtenidas con vehículos aéreos no tripulados. | AB14: 1- Formación de estudiantes de Maestría (2) 2- Vinculación de estudiante de doctorado 3- Ponencias (2): Participación en eventos científicos 4- Seminarios (2) 5- ARTICULO ORIGINAL EN REVISTA INDEXADA tipo top (A1 o A2) 6- ARTICULO ORIGINAL EN REVISTA INDEXADA tipo A (B o C) 7- Libro o borrador de libro sometido a evaluación. | AC14: =+IFERROR(P14/L14,0%) -> 0.5057615 | AD14: =+IFERROR((Q14+R14)/L14,0%) -> 0.4942385 | AE14: =IFERROR(Q14/(Q14+R14),0%) -> 0 | AF14: =IFERROR(R14/(Q14+R14),0%) -> 1 | AG14: =+IFERROR((S14+T14)/L14,0%) -> 0 | AH14: =+IFERROR((U14+V14)/L14,0%) -> 0 | AI14: =+IFERROR((W14+X14)/L14,0%) -> 0 | AJ14: =+IFERROR((Y14+Z14)/L14,0%) -> 0
A15: 2018 | B15: Propuesta de Investigación Convocatoria | C15: No Avalada | D15: 808 | E15: N/A | F15: MinCiencias | G15: Co-ejecutor | H15: 1- TECSOL | I15: N/A | J15: 24 | K15: N/A | L15: =+SUM(P15:Z15) -> 416335317 | M15: 0 | N15: =+P15+Q15+S15+U15+W15+Y15 -> 313585317 | O15: =+R15+T15+V15+X15+Z15 -> 102750000 | P15: 313585317 | Q15: 0 | R15: 60750000 | S15: 0 | T15: 42000000 | U15: 0 | V15: 0 | W15: 0 | X15: 0 | Y15: 0 | Z15: 0 | AA15: 1- Tesis de doctorado 2- Trabajo de grado de pregrado | AB15: 1- Artículo en revista indexada (2) 2- Ponencia en evento científico (2) 3- Informe técnico Final 4- Taller de divulgación con industriales (a los 10 meses de inicio) 5- Taller de socialización con industriales y búsqueda de financiación (a los 22meses de inicio) | AC15: =+IFERROR(P15/L15,0%) -> 0.75320374 | AD15: =+IFERROR((Q15+R15)/L15,0%) -> 0.14591604 | AE15: =IFERROR(Q15/(Q15+R15),0%) -> 0 | AF15: =IFERROR(R15/(Q15+R15),0%) -> 1 | AG15: =+IFERROR((S15+T15)/L15,0%) -> 0.10088022 | AH15: =+IFERROR((U15+V15)/L15,0%) -> 0 | AI15: =+IFERROR((W15+X15)/L15,0%) -> 0 | AJ15: =+IFERROR((Y15+Z15)/L15,0%) -> 0
A16: 2018 | B16: Propuesta de Investigación Convocatoria | C16: No Avalada | D16: 808 | E16: N/A | F16: MinCiencias | G16: Ejecutor | H16: 1- Grupo LIDER 2- Grupo LASER | I16: N/A | J16: 36 | K16: N/A | L16: =+SUM(P16:Z16) -> 376834000 | M16: 0 | N16: =+P16+Q16+S16+U16+W16+Y16 -> 241834000 | O16: =+R16+T16+V16+X16+Z16 -> 135000000 | P16: 241834000 | Q16: 0 | R16: 135000000 | S16: 0 | T16: 0 | U16: 0 | V16: 0 | W16: 0 | X16: 0 | Y16: 0 | Z16: 0 | AA16: 1- Vinculación de un (1) estudiante de doctorado 2- Formación de dos (2) Magister 3- Formación de dos (2) profesionales 4- Dos (2) ponencias internacionales 5- Participación en tres (3) eventos científicos 6- Organización de un (1) evento científico | AB16: 1- Dos (2) artículos categoría A1, A2, B y C. 2- Publicación de un libro o borrador sometido a evaluación | AC16: =+IFERROR(P16/L16,0%) -> 0.64175207 | AD16: =+IFERROR((Q16+R16)/L16,0%) -> 0.35824793 | AE16: =IFERROR(Q16/(Q16+R16),0%) -> 0 | AF16: =IFERROR(R16/(Q16+R16),0%) -> 1 | AG16: =+IFERROR((S16+T16)/L16,0%) -> 0 | AH16: =+IFERROR((U16+V16)/L16,0%) -> 0 | AI16: =+IFERROR((W16+X16)/L16,0%) -> 0 | AJ16: =+IFERROR((Y16+Z16)/L16,0%) -> 0
A17: 2018 | B17: Propuesta de Investigación Alianza Convenio | C17: Contrato firmado | D17: N/A | E17: N/A | F17: Fuerza Aérea Colombiana FAC | G17: Ejecutor | H17: Fuerza Aérea Colombiana FAC | I17: N/A | J17: 17 | K17: N/A | L17: =+SUM(P17:Z17) -> 948000000 | M17: 0 | N17: =+P17+Q17+S17+U17+W17+Y17 -> 0 | O17: =+R17+T17+V17+X17+Z17 -> 948000000 | P17: 0 | Q17: 0 | R17: 298000000 | S17: 0 | T17: 650000000 | U17: 0 | V17: 0 | W17: 0 | X17: 0 | Y17: 0 | Z17: 0 | AA17: Dominio Institucional • Tanto la Universidad como la Fuerza Aérea Colombiana desarrollan su misionalidad generando y difundiendo saberes con vocación hacia el desarrollo sociocultural en defensa de la soberanía e integridad del territorio desde una perspectiva de sostenibilidad ambiental. • Se consolidan procesos de investigación interinstitucionales que fortalecen los ámbitos académicos y tecnológicos en la búsqueda mancomunada del desarrollo social como fin primordial del Estado. • Se afianza el compromiso de la Fuerza Aérea Colombiana en el despliegue de proyectos de protección ambiental que procuran una mayor producción de oxígeno, no sólo para la nación de la que hace parte de su defensa, sino para beneficio global. Dominio lnvestigativo • Fomento del cambio de perspectiva en el abordaje de problemáticas complejas que requieren la articulación de equipos de trabajo multidisciplinarios. • Integración de la óptica civil a los proyectos de defensa de la soberanía e integridad del territorio, a partir de núcleos comunes de trabajo. • Generación de nuevas narrativas de interpretación de la problemática del deterioro ambiental causado por estrategias mineras no planificadas. • Explotación inteligente de bancos de datos del territorio nacional para garantizar el derecho y obligación del Estado y de las personas de proteger las riquezas y naturales de la Nación • Divulgación de resultados y experiencias en eventos nacionales e internacionales. Dominio Tecnológico • Se dota a la nación de una federación de herramientas para el análisis de datos multifuente, multi-formato; con capacidad de ser utilizada en los estudios de afectación ambiental con una perspectiva multimedia!. • Se fomenta la estandarización de datos y procesos (ambiente común de datos) para su visualización multitemporal y multidimensional en entornos Web (4D y SD). • Se propicia el enriquecimiento semántico de la metadata a partir de la definición de una ontología específica que permita la representación del conocimiento del dominio de afectación ambiental de lechos fluviales. • Al estar centrado en la arquitectura, se obtiene el beneficio de establecer un modelo base sobre el cual se integrarán los componentes en un ecosistema orientado a servicios. | AB17: * Generación de conocimiento: Un artículo indexado, Una ponencia, un registro de software. *Nuevos desarrollos tecnológicos: Un modelo y sistema de predicción * Fortalecimiento de la capacidad científica: Formación de Un Magíster, Formación de un Ingeniero * Fortalecimiento de la capacidad institucional: Futuros trabajos en alianza y colaboración, reconocimientos por parte del estado. * Apropiación social del conocimiento: Informes manuales, y transferencia al sector productivo. | AC17: =+IFERROR(P17/L17,0%) -> 0 | AD17: =+IFERROR((Q17+R17)/L17,0%) -> 0.31434599 | AE17: =IFERROR(Q17/(Q17+R17),0%) -> 0 | AF17: =IFERROR(R17/(Q17+R17),0%) -> 1 | AG17: =+IFERROR((S17+T17)/L17,0%) -> 0.68565401 | AH17: =+IFERROR((U17+V17)/L17,0%) -> 0 | AI17: =+IFERROR((W17+X17)/L17,0%) -> 0 | AJ17: =+IFERROR((Y17+Z17)/L17,0%) -> 0
A18: 2018 | B18: Propuesta de Investigación Convocatoria | C18: No Avalada | D18: 816 | E18: N/A | F18: MinCiencias | G18: Co-ejecutor | H18: GIM Ingeniería Eléctrica LTDA | I18: N/A | J18: 12 | K18: N/A | L18: =+SUM(P18:Z18) -> 770564675 | M18: 0 | N18: =+P18+Q18+S18+U18+W18+Y18 -> 599046915 | O18: =+R18+T18+V18+X18+Z18 -> 171517760 | P18: 599046915 | Q18: 0 | R18: 44843496 | S18: 0 | T18: 126674264 | U18: 0 | V18: 0 | W18: 0 | X18: 0 | Y18: 0 | Z18: 0 | AA18: 1- Levantamiento de Requerimientos: Informe con necesidades, Diagrama de Procesos, Documento de análisis de funcionamiento de la línea de producción, Fichas de equipos documentados, Fichas de puestos de trabajo. 2- Diseño global del sistema de seguimiento y los requerimientos monitoreo inteligente: Documento con el levantamiento de los requerimientos, URL con acceso a las funciones de la arquitectura de software 3- Adquisición de equipos software y servicios tecnológicos: Informe con las especificaciones de los requerimientos para el diseño de software, Manual de procesos de adquisiciones 4- Instalación de elementos adquiridos: Documentos con las especificaciones técnicas de los sensores, Informe con los detalles de la implementación y el estado del sistema 5- Evaluación: Tablas de evaluación del nivel de satisfacción de las adquisiciones, Informe técnico con las variables implementadas en la base de datos, Interfaz gráfica del sistema. | AB18: Sistema de seguimiento y monitoreo inteligente implementado correctamente, Documento con linea de producción caracterizada Sistema con módulo de verificación de cada variable indicando en comportamiento individual y registro de mediciones que registre tiempo. Protocolo de validación del sistema de seguimiento y monitoreo propuesto desarrollado y probado | AC18: =+IFERROR(P18/L18,0%) -> 0.7774129 | AD18: =+IFERROR((Q18+R18)/L18,0%) -> 0.058195629 | AE18: =IFERROR(Q18/(Q18+R18),0%) -> 0 | AF18: =IFERROR(R18/(Q18+R18),0%) -> 1 | AG18: =+IFERROR((S18+T18)/L18,0%) -> 0.16439148 | AH18: =+IFERROR((U18+V18)/L18,0%) -> 0 | AI18: =+IFERROR((W18+X18)/L18,0%) -> 0 | AJ18: =+IFERROR((Y18+Z18)/L18,0%) -> 0
A19: 2018 | B19: Propuesta de Investigación Convocatoria | C19: No Avalada | D19: 816 | E19: N/A | F19: MinCiencias | G19: Co-ejecutor | H19: 1- FIREFLY ENERGY SAS 2- Universidad de Cundinamarca | I19: N/A | J19: 12 | K19: N/A | L19: =+SUM(P19:Z19) -> 339886600 | M19: 0 | N19: =+P19+Q19+S19+U19+W19+Y19 -> 251886600 | O19: =+R19+T19+V19+X19+Z19 -> 88000000 | P19: 191886600 | Q19: 0 | R19: 48000000 | S19: 60000000 | T19: 0 | U19: 0 | V19: 40000000 | W19: 0 | X19: 0 | Y19: 0 | Z19: 0 | AA19: 1- Análisis de patrones y correlaciones en los reportes de emergencias. 2- Uso de Modelo de inteligencia de máquina y BigData en la predicción de emergencias, y que permita asistir en la coordinación y optimización de equipos de respuesta a emergencias 3- Informe técnico del resultado de análisis de BigData sobre los datos recibidos de reportes de emergencias. 4- Sistema que permita recepción análisis y predicciones por medio de aprendizaje de máquina, encaminado a mejorar la respuesta de equipos de emergencia. 5- Datos estadísticos y anóminos de libre consulta acerca de la geolocalización, frecuencia, clasificación y ocurrencia de reporte de emergencias en la ciudad de Facatativa 6- Diseño de estaciones de monitoreo climático y de otros tipos que se conecten con sistemas de IOT basados en protocolo MQTT | AB19: 1- Publicación Revista Internacional Machine Learning y Big data 2- Ponencia Internacional Machine Learning y Big data aplicado a ciudades inteligentes | AC19: =+IFERROR(P19/L19,0%) -> 0.56456065 | AD19: =+IFERROR((Q19+R19)/L19,0%) -> 0.14122357 | AE19: =IFERROR(Q19/(Q19+R19),0%) -> 0 | AF19: =IFERROR(R19/(Q19+R19),0%) -> 1 | AG19: =+IFERROR((S19+T19)/L19,0%) -> 0.17652947 | AH19: =+IFERROR((U19+V19)/L19,0%) -> 0.11768631 | AI19: =+IFERROR((W19+X19)/L19,0%) -> 0 | AJ19: =+IFERROR((Y19+Z19)/L19,0%) -> 0
A20: 2020 | B20: Propuesta de Investigación Alianza Convenio | C20: Contrato firmado | D20: N/A | E20: N/A | F20: N/A | G20: Aliado | H20: 1- Corporación Universitaria Iberoamericana 2- Fundación Zemillah 3- Saber Colombia Languages Research and Development | I20: N/A | J20: 12 | K20: UDFJC: -Grupo de Investigación Interdisciplinaria en Pedagogía del Lenguaje y las Matemáticas-GIIPLyM. -Grupo de Investigación - Literatura, Educación y Comunicación (LEC) IBERO: - Grupo en Investigación y Escenarios de Educación Pedagógica - GIEEP. | L20: =+SUM(P20:Z20) -> 101651661 | M20: 0 | N20: =+P20+Q20+S20+U20+W20+Y20 -> 7000000 | O20: =+R20+T20+V20+X20+Z20 -> 94651661 | P20: 0 | Q20: 0 | R20: 51500000 | S20: 7000000 | T20: 25783661 | U20: 0 | V20: 8354000 | W20: 0 | X20: 9014000 | Y20: 0 | Z20: 0 | AA20: - Identificación de presencia o no de tópicos de formación relacionados y en lo posible de metodologías y orientaciones metodológicas. - Base conceptual de las categorías. - Formulación de primera versión tipo Artículo con categorías - Talleres para la formación de profesores en experiencia estética en artes y en lenguaje y acogimiento a la diversidad. | AB20: - Un artículo postulado a revista indexada A1, A, B, C y D - Tres prototipos de talleres para formación de estudiantes para profesor. - Un informe de análisis de potencialidades de recursos tecnológicos - Estudiantes vinculados al proyecto como población en formación: - Nueve estudiantes en formación: - Cuatro pasantes de la UDFJC, Facultad de Ciencias y Educación: mediante convocatoria, de los proyectos curriculares Licenciatura Artística (danza), LEBEHLC (literatura y lenguaje), y NEES para diseño, población diversa. - Tres estudiantes asistentes de investigación de la IBERO, convocados por el GIEEP: Ma. de Jesús Blanco: Ibero de los programas de Educación infantil y de Educación especial (uno para población sordas y uno para población ciega y 2 de educación infantil). - Estudiantes de la Facultad Tecnológica, UDFJC vinculados al Módulo innova del CADEP Acacia. - Tres trabajos de grado de estudiantes de pregrado de programas Licenciatura Artística (danza), LEBEHLC (literatura y lenguaje), y NEES de la FCE-UDFJC y estudiantes para profesor en general. | AC20: =+IFERROR(P20/L20,0%) -> 0 | AD20: =+IFERROR((Q20+R20)/L20,0%) -> 0.50663215 | AE20: =IFERROR(Q20/(Q20+R20),0%) -> 0 | AF20: =IFERROR(R20/(Q20+R20),0%) -> 1 | AG20: =+IFERROR((S20+T20)/L20,0%) -> 0.32250984 | AH20: =+IFERROR((U20+V20)/L20,0%) -> 0.082182622 | AI20: =+IFERROR((W20+X20)/L20,0%) -> 0.088675383 | AJ20: =+IFERROR((Y20+Z20)/L20,0%) -> 0
A21: 2018 | B21: Propuesta de Investigación Convocatoria | C21: No Avalada | D21: 816 | E21: N/A | F21: MinCiencias | G21: Co-ejecutor | H21: 1- Praxis IT Colombia LTDA | I21: N/A | J21: 12 | K21: N/A | L21: =+SUM(P21:Z21) -> 599696552 | M21: 0 | N21: =+P21+Q21+S21+U21+W21+Y21 -> 560629662 | O21: =+R21+T21+V21+X21+Z21 -> 39066890 | P21: 400280763 | Q21: 5200000 | R21: 0 | S21: 155148899 | T21: 39066890 | U21: 0 | V21: 0 | W21: 0 | X21: 0 | Y21: 0 | Z21: 0 | AA21: 0 | AB21: Documento o informe de la consultoría en: - Diseño de la Arquitectura - Aseguramiento de la calidad para la implantación - Diseño e implementación de modelos analíticos en la plataforma - Generación de modelos analíticos - Protección de Datos | AC21: =+IFERROR(P21/L21,0%) -> 0.66747218 | AD21: =+IFERROR((Q21+R21)/L21,0%) -> 0.008671052 | AE21: =IFERROR(Q21/(Q21+R21),0%) -> 1 | AF21: =IFERROR(R21/(Q21+R21),0%) -> 0 | AG21: =+IFERROR((S21+T21)/L21,0%) -> 0.32385677 | AH21: =+IFERROR((U21+V21)/L21,0%) -> 0 | AI21: =+IFERROR((W21+X21)/L21,0%) -> 0 | AJ21: =+IFERROR((Y21+Z21)/L21,0%) -> 0
A22: 2021 | B22: Propuesta de Investigación Alianza Convenio | C22: Contrato firmado | D22: N/A | E22: N/A | F22: Universidad Pedagógica Nacional - UPN | G22: Aliado | H22: 1- Universidad Pedagógica Nacional (Colombia) 2- Universidad Alberto Hurtado (Chile) 3- Centro de Investigación y Estudios Avanzados del IPN (CINVESTAV, México 4- Universidade Federal de Santa Catarina (Brasil) | I22: N/A | J22: 42 | K22: UDFJC: - Biología, Enseñanza y Realidades UPN: - Biología, Enseñanza y Realidades CINVESTAV: - Educación en Biología UFSC: - Discursos da Ciência e da Tecnologia na Educação | L22: =+SUM(P22:Z22) -> 698127195 | M22: 0 | N22: =+P22+Q22+S22+U22+W22+Y22 -> 156069919 | O22: =+R22+T22+V22+X22+Z22 -> 542057276 | P22: 0 | Q22: 135004531 | R22: 81038638 | S22: 14065388 | T22: 209570394 | U22: 7000000 | V22: 67994644 | W22: 0 | X22: 91928000 | Y22: 0 | Z22: 91525600 | AA22: FASE I: - De dos a cuatro artículos que presenten los resultados del análisis bibliométrico y del discurso (contenido) - Dos ponencias, presentadas en congresos en enseñanza De las ciencias, formación De profesores y educación en general. - Tres trabajos De grado De pregrado FASE II: - Un artículo de comparación de los resultados obtenidos de los países participantes en relación con las políticas públicas en educación en ciencias y su articulación con la construcción de ciudadanías. - Dos ponencias sobre la relación planteada en esta fase - Simposio FASE III: - Diseño colectivo de ocho propuestas de educación en biología en clave de construcción de ciudadanías - Edición de un libro que sistematice la implementación de las ocho propuestas - Dos trabajos de grado de pregrado - Dos ponencias para la presentación de los resultados de investigación - 5 trabajos de grado de posgrado - Un artículo de investigación | AB22: - De dos a cuatro Artículos de investigación A1, A2, B y C - Un Libro resultado de investigación - Creación de la red Latinoamérica de enseñanza de la biología y construcción de ciudadanías - Organización de dos simposios que permitan reflexionar sobre la relación del proyecto - Participación como ponentes en seis eventos especializados - Dirección de cinco trabajo de grado de maestría en asociación directa al proyecto de investigación de las fases II y III - Dirección de cinco trabajo de grado de pregrado en asociación directa al proyecto de investigación de las fases I y II | AC22: =+IFERROR(P22/L22,0%) -> 0 | AD22: =+IFERROR((Q22+R22)/L22,0%) -> 0.30946104 | AE22: =IFERROR(Q22/(Q22+R22),0%) -> 0.62489609 | AF22: =IFERROR(R22/(Q22+R22),0%) -> 0.37510391 | AG22: =+IFERROR((S22+T22)/L22,0%) -> 0.32033673 | AH22: =+IFERROR((U22+V22)/L22,0%) -> 0.10742261 | AI22: =+IFERROR((W22+X22)/L22,0%) -> 0.13167801 | AJ22: =+IFERROR((Y22+Z22)/L22,0%) -> 0.13110161
A23: 2018 | B23: Propuesta de Investigación Convocatoria | C23: No Avalada | D23: 825 | E23: N/A | F23: MinCiencias | G23: Co-ejecutor | H23: Entidad Ejecutora: 1- Konrad Lorenz Entidad Co-ejecutora: 2- Universidad Católica de Oriente Entidad Sector TIC: 3- Log On Colombia | I23: N/A | J23: 15 | K23: N/A | L23: =+SUM(P23:Z23) -> 1.0101434e+09 | M23: 0 | N23: =+P23+Q23+S23+U23+W23+Y23 -> 698408645 | O23: =+R23+T23+V23+X23+Z23 -> 3.1173471e+08 | P23: 698408645 | Q23: 0 | R23: 131800000 | S23: 0 | T23: 1.3252229e+08 | U23: 0 | V23: 39600000 | W23: 0 | X23: 7812420 | Y23: 0 | Z23: 0 | AA23: * Perfil sociodemográfico y psicográfico de los estudiantes de educación virtual de dos zonas de Antioquia, identificando su perfil tecnológico, su historia de interacción con entornos virtuales y sus competencias de autorregulación * Evidencia, a partir de las actividades de investigación y la metodología descrita, de los componentes pedagógicos necesarios para la implementación del programa. | AB23: * Dos artículos sometidos a revistas de impacto (Q1-Q2). * Informe final sobre el diseño, construcción y validación del programa de intervención pedagógica para la prevención de la deserción y aumento del éxito estudiantil. * Plataforma para la implementación y uso del programa de intervención pedagógica para la prevención de la deserción y aumento del éxito estudiantil. * Informe final sobre las recomendaciones para el uso del programa de intervención pedagógica para la prevención de la deserción y aumento del éxito estudiantil. * Participación en dos eventos científicos. | AC23: =+IFERROR(P23/L23,0%) -> 0.69139557 | AD23: =+IFERROR((Q23+R23)/L23,0%) -> 0.13047653 | AE23: =IFERROR(Q23/(Q23+R23),0%) -> 0 | AF23: =IFERROR(R23/(Q23+R23),0%) -> 1 | AG23: =+IFERROR((S23+T23)/L23,0%) -> 0.13119157 | AH23: =+IFERROR((U23+V23)/L23,0%) -> 0.039202357 | AI23: =+IFERROR((W23+X23)/L23,0%) -> 0.0077339716 | AJ23: =+IFERROR((Y23+Z23)/L23,0%) -> 0
A24: 2021 | B24: Propuesta de Investigación Alianza Convenio | C24: Contrato firmado | D24: N/A | E24: N/A | F24: EAN - ICC | G24: Aliado | H24: 1- Universidad EAN 2- Instituto Caro y Cuervo | I24: N/A | J24: 15 | K24: UDFJC: - ESTUPOLI EAN: - Lingüística aplicada y comunicación organizacional ICC: - Linguistica | L24: =+SUM(P24:Z24) -> 49779000 | M24: 0 | N24: =+P24+Q24+S24+U24+W24+Y24 -> 0 | O24: =+R24+T24+V24+X24+Z24 -> 49779000 | P24: 0 | Q24: 0 | R24: 18456000 | S24: 0 | T24: 7640000 | U24: 0 | V24: 23683000 | W24: 0 | X24: 0 | Y24: 0 | Z24: 0 | AA24: - 10 participantes, profesores entre los que están 5 de inglés y 5 de español - El protocolo de las entrevistas - Grabaciones de las entrevistas - Transcripción y codificación de transcripción de las entrevistas - Una recolección de propuestas metodológicas sistematizadas por temáticas, objetivos y metodologías - Instrumento en forma de matriz para análisis de propuestas - Propuestas insertadas en las matrices diseñadas - Informe de análisis | AB24: 0 | AC24: =+IFERROR(P24/L24,0%) -> 0 | AD24: =+IFERROR((Q24+R24)/L24,0%) -> 0.37075875 | AE24: =IFERROR(Q24/(Q24+R24),0%) -> 0 | AF24: =IFERROR(R24/(Q24+R24),0%) -> 1 | AG24: =+IFERROR((S24+T24)/L24,0%) -> 0.15347837 | AH24: =+IFERROR((U24+V24)/L24,0%) -> 0.47576287 | AI24: =+IFERROR((W24+X24)/L24,0%) -> 0 | AJ24: =+IFERROR((Y24+Z24)/L24,0%) -> 0
A25: 2018 | B25: Propuesta de Investigación Convocatoria | C25: No Avalada | D25: Convocatoria de investigaciones 2018 para presentar proyectos de CT+I en temáticas relacionadas con la planeación, gestión eficiente, atribución, vigilancia y control del espectro radioeléctrico en Colombia | E25: N/A | F25: Agencia Nacional del Espectro - ANE | G25: Ejecutor | H25: N/A | I25: N/A | J25: 11 | K25: N/A | L25: =+SUM(P25:Z25) -> 363820662 | M25: 0 | N25: =+P25+Q25+S25+U25+W25+Y25 -> 248389600 | O25: =+R25+T25+V25+X25+Z25 -> 115431062 | P25: 248389600 | Q25: 0 | R25: 115431062 | S25: 0 | T25: 0 | U25: 0 | V25: 0 | W25: 0 | X25: 0 | Y25: 0 | Z25: 0 | AA25: 0 | AB25: 1- El resultado esperado de esta fase del proyecto es un informe de los métodos de planificación utilizados actualmente por los diferentes operadores de televisión, así mismo una clasificación de dichos modelos eleccionando los índices de gestión de recursos en el espectro radioeléctrico, para así buscar una comparación pertinente para realizar de forma adecuada y eficiente la puesta en funcionamiento de la metodología que es el objetivo de este proyecto. 2- El resultado esperado de esta fase del proyecto se compone de un informe que unifique los criterios y procedimientos necesarios en la planificación de redes de televisión digital terrestre, incluyendo una sección de pruebas de campo y/o laboratorio, se seleccionaran los lugares más representativos de la región rural de Cundinamarca para realizar las mediciones. Aquí se busca tener un componente comparativo de los comportamientos de los modelos en entornos rurales. La redacción de un documento de socialización para estudiantes de la Facultad de Ingeniería de la Universidad Distrital permitirá mostrar los avances logrados en esta fase, de igual forma la presentación de los mismos en un evento nacional/internacional en el formato ponencia o poster. 3- El resultado esperado de esta fase del proyecto se compone de un documento de análisis de todo lo relacionado con la gestión del modelo para la parametrización de coberturas y asignación eficiente del espectro radioeléctrico, a través de análisis pertinentes y verificación de campo para generar la metodología propuesta. Así mismo de los análisis de coberturas, interferencias, eficiencia de frecuencias en entornos rurales y su respectiva validación de campo. En esta fase se preparará un documento tipo artículo para presentar en revista internacional indexada. 4- En esta etapa se recopilará la información obtenida con las fases anteriores. Esta documentación tiene el objeto de describir claramente la metodología para la planificación de redes de televisión digital terrestre en el entorno rural de Cundinamarca, así mismo la integración de los procesos que se seleccionaron para posteriores trabajos y/o desarrollos. Se postulará el artículo redactado en la fase anterior en una revista internacional indexada. | AC25: =+IFERROR(P25/L25,0%) -> 0.68272538 | AD25: =+IFERROR((Q25+R25)/L25,0%) -> 0.31727462 | AE25: =IFERROR(Q25/(Q25+R25),0%) -> 0 | AF25: =IFERROR(R25/(Q25+R25),0%) -> 1 | AG25: =+IFERROR((S25+T25)/L25,0%) -> 0 | AH25: =+IFERROR((U25+V25)/L25,0%) -> 0 | AI25: =+IFERROR((W25+X25)/L25,0%) -> 0 | AJ25: =+IFERROR((Y25+Z25)/L25,0%) -> 0
A26: 2018 | B26: Propuesta de Investigación Convocatoria | C26: No Avalada | D26: 828 | E26: N/A | F26: MinCiencias | G26: Co-ejecutor | H26: 1- Ejecutor:TECSOL 2- Aliado Institucional: Alcaldía de Guacheta | I26: N/A | J26: 18 | K26: N/A | L26: =+SUM(P26:Z26) -> 417331506 | M26: 0 | N26: =+P26+Q26+S26+U26+W26+Y26 -> 287770013 | O26: =+R26+T26+V26+X26+Z26 -> 129561493 | P26: 287770013 | Q26: 0 | R26: 40162098 | S26: 0 | T26: 89399395 | U26: 0 | V26: 0 | W26: 0 | X26: 0 | Y26: 0 | Z26: 0 | AA26: * Implementar cuatro sistemas generadores de biogás y bioabono cuyo funcionamiento permite dar uso a los residuos orgánicos resultantes de los procesos productivos agropecuarios y domiciliarios con el fin de generar biogás y bioabono para su reutilización en el proceso productivo, como acercamiento a un ciclo de economía circular. * Agremiar inicialmente a veinte hogares de siete veredas del municipio de Guachetá para capacitarlos acerca de diversos aspectos que rodean la valorización energética de sus residuos orgánicos. * Desarrollar una aplicación móvil para la recolección de datos obtenidos durante los procesos de digestión anaerobia, entre otras experiencias y resultados que se puedan dar de este proyecto, con el fin de garantizar la construcción colectiva del conocimiento. * Generar una caracterización de la zona geográfica que sirva para futuras investigaciones en el área de los biodigestores. * Estimar la reducción de uso de recursos energéticos en los procesos productivos al usar el producto de los biodigestores, además de materia orgánica que deja de ser arrojada a los vertederos. | AB26: 1. Productos resultados de actividades de generación de nuevo conocimiento. - 1 Artículo de investigación 2. Productos resultados de actividades de desarrollo tecnológico e innovación. - 1 Producto tecnológico certificado o validado: c.Software (aplicación móvil). 3. Productos resultados de actividades de apropiación social del conocimiento. - Participación ciudadana en CTeI: b. Espacios de participación ciudadana en CTeI. - Circulación de conocimiento especializado: a. Participaciones u organizaciones de eventos científicos, tecnológicos y de innovación (congresos, seminarios, foros, conversatorios, talleres, entre otros). 4. Productos de actividades relacionadas con la formación de recurso humano para CTeI. - Estudiante de 1 pregrado y 1 maestría: b. Vinculación de estudiantes de pregrado y maestría. | AC26: =+IFERROR(P26/L26,0%) -> 0.68954778 | AD26: =+IFERROR((Q26+R26)/L26,0%) -> 0.09623548 | AE26: =IFERROR(Q26/(Q26+R26),0%) -> 0 | AF26: =IFERROR(R26/(Q26+R26),0%) -> 1 | AG26: =+IFERROR((S26+T26)/L26,0%) -> 0.21421674 | AH26: =+IFERROR((U26+V26)/L26,0%) -> 0 | AI26: =+IFERROR((W26+X26)/L26,0%) -> 0 | AJ26: =+IFERROR((Y26+Z26)/L26,0%) -> 0
A27: 2018 | B27: Propuesta de Investigación Convocatoria | C27: No Avalada | D27: 829 | E27: N/A | F27: MinCiencias | G27: Co-ejecutor | H27: 1- Ejecutor:TECSOL 2- Aliado Institucional: Alcaldía de Guacheta | I27: N/A | J27: 18 | K27: N/A | L27: =+SUM(P27:Z27) -> 417331506 | M27: 0 | N27: =+P27+Q27+S27+U27+W27+Y27 -> 287770013 | O27: =+R27+T27+V27+X27+Z27 -> 129561493 | P27: 287770013 | Q27: 0 | R27: 40162098 | S27: 0 | T27: 89399395 | U27: 0 | V27: 0 | W27: 0 | X27: 0 | Y27: 0 | Z27: 0 | AA27: * Implementar cuatro sistemas generadores de biogás y bioabono cuyo funcionamiento permite dar uso a los residuos orgánicos resultantes de los procesos productivos agropecuarios y domiciliarios con el fin de generar biogás y bioabono para su reutilización en el proceso productivo, como acercamiento a un ciclo de economía circular. * Agremiar inicialmente a veinte hogares de siete veredas del municipio de Guachetá para capacitarlos acerca de diversos aspectos que rodean la valorización energética de sus residuos orgánicos. * Desarrollar una aplicación móvil para la recolección de datos obtenidos durante los procesos de digestión anaerobia, entre otras experiencias y resultados que se puedan dar de este proyecto, con el fin de garantizar la construcción colectiva del conocimiento. * Generar una caracterización de la zona geográfica que sirva para futuras investigaciones en el área de los biodigestores. * Estimar la reducción de uso de recursos energéticos en los procesos productivos al usar el producto de los biodigestores, además de materia orgánica que deja de ser arrojada a los vertederos. | AB27: 1. Productos resultados de actividades de generación de nuevo conocimiento. - 1 Artículo de investigación 2. Productos resultados de actividades de desarrollo tecnológico e innovación. - 1 Producto tecnológico certificado o validado: c.Software (aplicación móvil). 3. Productos resultados de actividades de apropiación social del conocimiento. - Participación ciudadana en CTeI: b. Espacios de participación ciudadana en CTeI. - Circulación de conocimiento especializado: a. Participaciones u organizaciones de eventos científicos, tecnológicos y de innovación (congresos, seminarios, foros, conversatorios, talleres, entre otros). 4. Productos de actividades relacionadas con la formación de recurso humano para CTeI. - Estudiante de 1 pregrado y 1 maestría: b. Vinculación de estudiantes de pregrado y maestría. | AC27: =+IFERROR(P27/L27,0%) -> 0.68954778 | AD27: =+IFERROR((Q27+R27)/L27,0%) -> 0.09623548 | AE27: =IFERROR(Q27/(Q27+R27),0%) -> 0 | AF27: =IFERROR(R27/(Q27+R27),0%) -> 1 | AG27: =+IFERROR((S27+T27)/L27,0%) -> 0.21421674 | AH27: =+IFERROR((U27+V27)/L27,0%) -> 0 | AI27: =+IFERROR((W27+X27)/L27,0%) -> 0 | AJ27: =+IFERROR((Y27+Z27)/L27,0%) -> 0
A28: 2018 | B28: Propuesta de Investigación Convocatoria | C28: No Avalada | D28: 829 | E28: N/A | F28: MinCiencias | G28: Co-ejecutor | H28: 1- Ejecutor: Corporación Universitaria Minuto de Dios 2- Aliado: Corporación Centauro Bacata | I28: N/A | J28: 18 | K28: N/A | L28: =+SUM(P28:Z28) -> 509627362 | M28: 0 | N28: =+P28+Q28+S28+U28+W28+Y28 -> 381426362 | O28: =+R28+T28+V28+X28+Z28 -> 128201000 | P28: 349676362 | Q28: 31750000 | R28: 45100000 | S28: 0 | T28: 83101000 | U28: 0 | V28: 0 | W28: 0 | X28: 0 | Y28: 0 | Z28: 0 | AA28: Se espera obtener los siguientes resultados: 1- Actividades de Nuevo conocimiento: Libro, Un articulo. 2- Actividades Desarrollo tecnológico e innovación: Mapa de la cobertera vegetal, Guía de cuidado y uso de especies vegetales. 3- Actividades de Apropiación social del conocimiento: Participación ciudadana en productos CTel, Alianza con centro dedicado a la apropiación social del conocimiento. 4- Actividades de formación del recurso humano: Formación de 4 estudiantes de pregrado, Formación de dos estudiantes de maestría. | AB28: * Cartilla guia para identificar, cuidadar y aprovechar las especies vegetales presentes en la zona. * Libro Publicación con los resultados obtenidos y la metodología desarrollada * Mapa de la cobertera vegetal del área investigada * Alianza con los centros educativos de los municipios de Choachí, Ubaque y Fómeque * Tesis de grado de maestría, trabajo de campo e instruirán a los estudiantes. * Vinculación estudiantes de pregrado Apoyarán todo el proceso de la investigación y trabajarán en campo e instruirán a los estudiantes * Formación estudiantes de pregrado | AC28: =+IFERROR(P28/L28,0%) -> 0.68614126 | AD28: =+IFERROR((Q28+R28)/L28,0%) -> 0.15079646 | AE28: =IFERROR(Q28/(Q28+R28),0%) -> 0.41314249 | AF28: =IFERROR(R28/(Q28+R28),0%) -> 0.58685751 | AG28: =+IFERROR((S28+T28)/L28,0%) -> 0.16306228 | AH28: =+IFERROR((U28+V28)/L28,0%) -> 0 | AI28: =+IFERROR((W28+X28)/L28,0%) -> 0 | AJ28: =+IFERROR((Y28+Z28)/L28,0%) -> 0
A29: 2018 | B29: Propuesta de Investigación Convocatoria | C29: No Avalada | D29: 829 | E29: N/A | F29: MinCiencias | G29: Co-ejecutor | H29: 1- Ejecutor: Corporación Universitaria Minuto de Dios 2- Aliado: Corporación Centauro Bacata | I29: N/A | J29: 18 | K29: N/A | L29: =+SUM(P29:Z29) -> 509627362 | M29: 0 | N29: =+P29+Q29+S29+U29+W29+Y29 -> 381426362 | O29: =+R29+T29+V29+X29+Z29 -> 128201000 | P29: 349676362 | Q29: 31750000 | R29: 45100000 | S29: 0 | T29: 83101000 | U29: 0 | V29: 0 | W29: 0 | X29: 0 | Y29: 0 | Z29: 0 | AA29: Se espera obtener los siguientes resultados: 1- Actividades de desarrollo tecnológico: Mapa geomorfológico: Información obtenida como resultado de la transformación de imágenes pares estereoscópicas paralelas, en un modelo digital del relieve y su deriva con clasificación de la superficie sobre la base de indicadores dinámicos y parámetro hidrogeológicos, con los cuales se ajusta el algoritmo de interpretación de la imagen. Permite el conocimiento de estructuras regionales, el lineamiento de las áreas que presentan las fallas tectónicas, las cuales no se observan con otros algoritmos. Las estructuras definidas en este mapa permiten observar la presencia de acuíferos. Incrementar el conocimiento de los acuíferos existentes en el área de estudio y socializarlo entre la comunidad. 2- Actividades de apropiación del conocimiento: Metas: Capacitar al 10% de la pob]ación del área de estudio en el proyecto, en el nuevo conocimiento. Promover la creación de dos (2) comités de vigilancia, cuidado y recuperación de Jos acuíferos existentes en el área de influencia del estudio. 3- Actividades de Nuevo conocimiento: Un libro, un articulo 4- Actividades Desarrollo tecnológico e innovación: Guía de cuidado, uso y recuperación de acuíferos 5- Actividades de formación del recurso humano: Formación de 6 estudiantes de pregrado Formación de dos estudiantes de maestría. | AB29: * Libro con resultado de la investigación, metodología y propuestas * Guia de cuidado, uso y recuperación de acuíferos * Mapa.geomorfológico del corredor Choachi - Fómeque 25 km2 * Alianza con las alcaldías de los municipios de Choachi y Fómeque * Vinculación de estudiantes de pregrado, para apoyo de la investigación en campo y oficina * Vinculación estudiantes de Maestría que trabajarán en todo el proyecto, incluido el trabajo de campo e instruirán a los estudiantes. | AC29: =+IFERROR(P29/L29,0%) -> 0.68614126 | AD29: =+IFERROR((Q29+R29)/L29,0%) -> 0.15079646 | AE29: =IFERROR(Q29/(Q29+R29),0%) -> 0.41314249 | AF29: =IFERROR(R29/(Q29+R29),0%) -> 0.58685751 | AG29: =+IFERROR((S29+T29)/L29,0%) -> 0.16306228 | AH29: =+IFERROR((U29+V29)/L29,0%) -> 0 | AI29: =+IFERROR((W29+X29)/L29,0%) -> 0 | AJ29: =+IFERROR((Y29+Z29)/L29,0%) -> 0
A30: 2021 | B30: Propuesta de Investigación Alianza Convenio | C30: Contrato firmado | D30: N/A | E30: N/A | F30: Secretaria de Educación Distrital - Dirección de formación de docentes e Innovaciones Pedagógicas | G30: Aliado | H30: Secretaria de Educación Distrital - Dirección de formación de docentes e Innovaciones Pedagógicas | I30: N/A | J30: 4 ó hasta el 28 de diciembre de 2021 | K30: UDFJC: - Vivencias | L30: =+SUM(P30:Z30) -> 508000000 | M30: =+S30 -> 350000000 | N30: =+P30+Q30+S30+U30+W30+Y30 -> 440000000 | O30: =+R30+T30+V30+X30+Z30 -> 68000000 | P30: 0 | Q30: 90000000 | R30: 68000000 | S30: 350000000 | T30: 0 | U30: 0 | V30: 0 | W30: 0 | X30: 0 | Y30: 0 | Z30: 0 | AA30: Documento que incluya propuesta conceptual, metodológica y plan de trabajo detallado de los cuatro componentes: 1. Formación de maestras y maestros. 2. Investigación y configuración de nuevo conocimiento. 3. Comunicación: Circulación, apropiación y divulgación pública del conocimiento. 4.Configuración de comunidad de saber pedagógico - Informe que presente el avance por cada uno de los cuatro componentes: 1. Formación de maestras y maestros. 2. Investigación y configuración de nuevo conocimiento. 3. Comunicación: Circulación, apropiación y divulgación pública del conocimiento. 4.Configuración de comunidad de saber pedagógico - Informe final que incluya: 1. Documento que dé cuenta de los resultados del proceso de formación e investigación con 140 maestras y maestros de Bogotá y su aporte en la comprensión crítica del acontecimiento pandémico en el contexto educativo y cultural del Distrito Capital. 2. Documento editado con el archivo sobre testimonios de vida de maestras y maestros de Bogotá, a partir de veinte (20) entrevistas realizadas. 3. Carpeta con las versiones finales del siguiente material digital editado: a. Diez (10) entrevistas radiales. b. Treinta (30) podcast. c.Diez (10) materiales en videoclip. d. Un (1) libro álbum de póster e ilustraciones de recorrido por 12 experiencias seleccionadas. e. Un (1) video de 10 minutos de duración que recoja el proceso realizado. 4. Documento que dé cuenta del proceso realizado en la configuración de comunidad de saber pedagógico (redes y colectivos): a. Caracterización de redes y colectivos. b. Sistematización del proceso realizado con redes y colectivos. 5. Informe final publicable de las actividades desarrolladas durante el proceso de formación/investigación sobre el tema Afro (Componente 5 - Acciones afirmativas y escuela). Este documento estará organizado en cuatro partes: a. Introducción que presente los componentes centrales del diplomado. b. Referentes conceptuales establecidos en la serie interculturalidad-intraculturalidad-arte-cultura-escuela-pamdemia que recojan los aportes de los maestros y maestras. c. Testimonios, crónicas, entrevistas de los docentes. d.Conclusiones | AB30: El macroproyecto de investigación maestros y maestras de Bogotá: Tránsitos por el acontecimiento pandémico y configuración de redes y comunidades de saber pedagógico plantea un conjunto de impactos esperados encabezados por aspectos de orden socio-económico que se complementan con las dimensiones tecnológica, técnica y ambiental que surgen a partir de los procesos de formación docente, investigación, configuración de comunidades de saber, comunicación y acciones pedagógicas en el marco de la reflexión crítica frente a las condiciones generadas por el COVID 19 en maestros, maestras y docentes directivos de Bogotá. Se trata, en consecuencia, de una serie de efectos que redundan tanto en la construcción de diversos conocimientos en conjunto con los grupos de trabajo participantes en el macropoyecto como también en posibilidades de generación de condiciones para el desarrollo de procesos investigativos y críticos en los campos de lo social y lo pedagógico a nivel del Distrito Capital. En primera instancia, el impacto socio-económico que se espera obtener como resultado del desarrollo del marcoproyecto tiene que ver con la consolidación de acciones de empoderamiento de grupos docentes, comunidades de saber y colectivos sociales en comunidades afrodescendientes, de manera que, en conjunto con el proceso de reflexión acerca de la práctica educativa, también se construyan los elementos para el manejo de elementos de producción comunicativa, técnicas de investigación y procesos formativos en relación con la reflexión del acontecimiento pandémico. El trabajo en estas dimensiones permitirá que los sujetos participantes en el macroproyecto refuercen sus saberes y manejo de elementos investigativos, lo que redunda en la cualificación de sus labores diarias y con ello permiten un desarrollo humano, pero también la creación de condiciones para aportar a un crecimiento económico en términos de la producción de posibles recursos intangibles asociados al conocimiento adquirido. En otras palabras, el macroproyecto permite posicionar el proceso investigativo y formativo como el punto de partida para el crecimiento económico y social teniéndose el conocimiento como elemento fundamental para la producción de recursos a futuro. De igual modo, a nivel de lo propiamente social, la construcción de comunidad de saber, permite el posicionamiento de procesos de trabajo en red, lo que permite establecer como impacto la transformación significativa de los modos en los que se configuran procesos de reflexión educativa y social que, adicionalmente, al ubicar sus reflexiones en el acontecimiento pandémico, posibilitan la creación de condiciones para asumir los retos que plantean los escenarios de la postpandemia, la inclusión de las diferencias y la recomposición de tejidos sociales. De esta manera, el impacto del macroproyecto radica en la posibilidad de generar interacciones significativas al interior de los grupos de docentes a nivel nacional, lo que redunda en la creación de asociaciones y, al mismo tiempo el reconocimiento y posicionamiento de diferentes grupos sociales en términos de convergencia e integración entre distintos, dando cabida así a la inclusión y la apertura a un escenario reflexivo desde la multiplicidad. Ahora bien, estos impactos se complementan con los que son producidos en el ámbito técnico y tecnológico y que se refieren a las posibilidades de apropiación y uso significativo de diferentes recursos tanto teóricos como metodológicos para la realización de reflexiones sobre el acontecimiento pandémico, la cuestión de la diferencia y la posibilidad de construcción de procesos comunicativos significativos a nivel audiovisual. Es así como se cuenta con la consolidación de una comunidad de saber que maneja de forma adecuada técnicas de investigación y reflexión critica susceptibles de ser aplicadas en sus entornos pedagógicos en la transformación de sus prácticas educativas y, al mismo tiempo, cuenta con la formación para poder hacer uso de recursos digitales a nivel comunicativo. Así, el proceso formativo y de comunicación no solamente arroja como impacto la interiorización de técnicas investigativas, sino también el acercamiento a herramientas tecnológicas para la producción de contenidos, lo que redunda en un impacto mediado por el conocimiento de dispositivos, elementos y posibilidades de uso de recursos tanto para investigar como para crear tanto en aspectos de orden estético como la pintura y el relato, como en elementos comunicativos tales como el podcast y el video. A nivel ambiental, el macroproyecto genera un impacto positivo en términos del uso principalmente de recursos digitales para su desarrollo, de manera que se reduzcan al máximo las afectaciones en términos de medioambiente que podría tener, por ejemplo, el uso de papel u otros recursos en el proceso investigativo. En esta medida, en el macroproyecto, si bien aparecen diferentes actividades que implican la participación de grupos, la elaboración de productos audiovisuales y la interacción permanente al interior de la comunidad de saber, definitivamente se propenderá por el uso de mecanismos virtuales y digitales preferiblemente, velándose así por un uso moderado de los recursos disponibles. Finalmente, y en adición a los impactos expresados anteriormente, es preciso señalar los modos en los que el macroproyecto impacta directamente a nivel de la formación de maestros a nivel del Distrito Capital y la reflexión que emerge sobre el acontecimiento pandémico como un elemento fundamental para pensar incluso en procesos de política pública ante contingencias semejantes a la vivida con el COVID 19. Este impacto se da tanto por el proceso formativo como por los espacios de divulgación y producción comunicativa en tanto que posibilita una reflexión desde la educación a nivel distrital sobre las transformaciones sociales y pedagógicas fruto de la coyuntura dada por la emergencia sanitaria y, al mismo tiempo permite que las experiencias y reflexiones resultado del macroproyecto puedan constituirse como referente en términos incluso de política pública en el sector educativo. | AC30: =+IFERROR(P30/L30,0%) -> 0 | AD30: =+IFERROR((Q30+R30)/L30,0%) -> 0.31102362 | AE30: =IFERROR(Q30/(Q30+R30),0%) -> 0.56962025 | AF30: =IFERROR(R30/(Q30+R30),0%) -> 0.43037975 | AG30: =+IFERROR((S30+T30)/L30,0%) -> 0.68897638 | AH30: =+IFERROR((U30+V30)/L30,0%) -> 0 | AI30: =+IFERROR((W30+X30)/L30,0%) -> 0 | AJ30: =+IFERROR((Y30+Z30)/L30,0%) -> 0
A31: 2018 | B31: Propuesta de Investigación Convocatoria | C31: No Avalada | D31: 829 | E31: N/A | F31: MinCiencias | G31: Co-ejecutor | H31: 1- Ejecutor: Corporación Universidad Piloto de Colombia - Seccional Girardot 2- Aliada: Alcaldía de Guachetá | I31: N/A | J31: 18 | K31: N/A | L31: =+SUM(P31:Z31) -> 504658699 | M31: 0 | N31: =+P31+Q31+S31+U31+W31+Y31 -> 349229442 | O31: =+R31+T31+V31+X31+Z31 -> 155429257 | P31: 349229442 | Q31: 0 | R31: 58608566 | S31: 0 | T31: 96820691 | U31: 0 | V31: 0 | W31: 0 | X31: 0 | Y31: 0 | Z31: 0 | AA31: * Estudio del potencial energético y aprovechamiento del residuo orgánico para la generación de biogás y biofertilizantes. * Creación de una base de datos de la caracterización y potencial de biomasa residual disponible y un inventario de las capacidades técnicas actuales de la OMATAA. * Sistematización del proceso de diseño, construcción e implementación de biodigestores en condiciones climáticas del municipio de Guachetá Cundinamarca * Implementar una estrategia de clasificación de residuos y plan de sostenibilidad del CERBÍO que cuente con la participación activa de la población de Guachetá. * Implementar estrategias para la apropiación social del conocimiento que beneficien a la población de Guachetá, la OMATAA y la comunidad académica y científica de las Universidades Piloto de Colombia y Distrital Francisco José de Caldas. * Desarrollar un aplicativo móvil para el fortalecimiento de capacidades en la producción y comercialización del biogás y biofertilizante. * Implementación de un Centro de Experiencia Rural Bioambiental –CERBÍO-, para la biodigestión de residuos orgánicos y el fortalecimiento de capacidades en la producción agrícola del municipio de Guachetá. * A partir de las lecciones aprendidas del proyecto, ser un referente para replicar el Centro de Experiencia Rural Bioambiental –CERBÍO- en otras poblaciones del departamento de Cundinamarca y del resto del país. * Generar productos de nuevo conocimiento que sean publicados en revistas indexadas internacionales y/o nacionales. | AB31: * Artículo Categoría "B" Optimización de biodigestores según condiciones climáticas en municipios de Cundinamarca, a partir de los resultados alcanzados en el objetivo 2: Diseñar e implementar un biodigestor piloto para generar biogás y biofertilizante a partir de los residuos orgánicos acopiados por Oficina Municipal de Asistencia Técnica Agropecuaria y Ambiental -OMATAA- del municipio de Guachetá. * Artículo Categpría "A2" Un artículo en revista indexada de categoría A2 de acuerdo al objetivo 5 Documentar la experiencia y las lecciones aprendidas del proyecto para la posible replicabilidad del - CERBÍO- en otras poblaciones del departamento de Cundinamarca. * Informe técnico que describa los avances y logros alcanzados en el proyecto, así como las técnicas y estrategias implementadas por el Centro de Experiencia Rural Bioambiental -CERBÍO-, para la biodigestión de residuos orgánicos y el fortalecimiento de capacidades en la producción agrícola del municipio de Guachetá. * Software Aplicativo móvil para el fortalecimiento de capacidades en la producción y comercialización del biogás y biofertilizante, de acuerdo al objetivo 4 Desarrollar una estrategia para la apropiación social del conocimiento del Centro de Experiencia Rural Bioambiental -CERBÍO-. * Trabajo conjunto con comunidades del municipio en el desarrollo de actividades orientadas al mejoramiento de las condiciones del territorio, buscando una construcción colectiva de saberes. * Diseño y ejecución de una estrategia pedagógica y didáctica que facilite el aprendizaje y uso de los potenciales de biomasa, clasificación de residuos municipales e industriales * Organización del Seminario de Bioenergía * Ponencia 1: Participación con ponencia o póster Seminario de Bioenergía Ponencia 2: Participación con ponencia en evento internacional * Divulgación de las experiencias y las lecciones aprendidas del proyecto para la posible replicabilidad del -CERBÍO- en otros territorios de Cundinamarca a través de emisiones radiales y/o videos * Modelo y estrategias para la creación de Centros de Experiencia Rural Bioambiental -CERBÍO-, para la biodigestión de residuos orgánicos y el fortalecimiento de capacidades en producción agrícola. * Vinculación de estudiante de maestría | AC31: =+IFERROR(P31/L31,0%) -> 0.69201114 | AD31: =+IFERROR((Q31+R31)/L31,0%) -> 0.11613506 | AE31: =IFERROR(Q31/(Q31+R31),0%) -> 0 | AF31: =IFERROR(R31/(Q31+R31),0%) -> 1 | AG31: =+IFERROR((S31+T31)/L31,0%) -> 0.1918538 | AH31: =+IFERROR((U31+V31)/L31,0%) -> 0 | AI31: =+IFERROR((W31+X31)/L31,0%) -> 0 | AJ31: =+IFERROR((Y31+Z31)/L31,0%) -> 0
A32: 2018 | B32: Propuesta de Investigación Convocatoria | C32: No Avalada | D32: Convocatoria de estímulos 2018 | E32: N/A | F32: MinCultura | G32: Ejecutor | H32: N/A | I32: N/A | J32: 6.5 | K32: N/A | L32: =+SUM(P32:Z32) -> 180000000 | M32: 0 | N32: =+P32+Q32+S32+U32+W32+Y32 -> 180000000 | O32: =+R32+T32+V32+X32+Z32 -> 0 | P32: 180000000 | Q32: 0 | R32: 0 | S32: 0 | T32: 0 | U32: 0 | V32: 0 | W32: 0 | X32: 0 | Y32: 0 | Z32: 0 | AA32: 0 | AB32: * Cinco capítulos de siete minutos cada uno en las temáticas: - Ambiente, basuras, mitigación y Control. - Energías alternas en la cotidianidad - Dispositivos para tratamientos DIY del agua - Prácticas ancestrales y sonido - Alimentación huertas urbanas y rurales sistematizadas | AC32: =+IFERROR(P32/L32,0%) -> 1 | AD32: =+IFERROR((Q32+R32)/L32,0%) -> 0 | AE32: =IFERROR(Q32/(Q32+R32),0%) -> 0 | AF32: =IFERROR(R32/(Q32+R32),0%) -> 0 | AG32: =+IFERROR((S32+T32)/L32,0%) -> 0 | AH32: =+IFERROR((U32+V32)/L32,0%) -> 0 | AI32: =+IFERROR((W32+X32)/L32,0%) -> 0 | AJ32: =+IFERROR((Y32+Z32)/L32,0%) -> 0
A33: 2018 | B33: Propuesta de Investigación Alianza Convenio | C33: Desistio | D33: N/A | E33: N/A | F33: Universidad de Sucre | G33: Ejecutor | H33: Universidad de Sucre | I33: N/A | J33: 18 | K33: N/A | L33: =+SUM(P33:Z33) -> 194254513 | M33: 0 | N33: =+P33+Q33+S33+U33+W33+Y33 -> 111000913 | O33: =+R33+T33+V33+X33+Z33 -> 83253600 | P33: 0 | Q33: 83222913 | R33: 67500000 | S33: 27778000 | T33: 15753600 | U33: 0 | V33: 0 | W33: 0 | X33: 0 | Y33: 0 | Z33: 0 | AA33: * Generación de conocimiento para entender el potencial hidrico (calidad y cantidad) de un cuerpo de aqua lentico * Mejoramiento en las condiciones de tratabilidad del agua para consumo humano * Participación de un evento científico * Establecer el índice de calidad del agua del cuerpo del agua lentico * Socialización de resultados ante la Autoridad Ambiental en la Jurisdicción | AB33: * Cuatro (4) artículos científicos Número de artículos resultados de la investigación en publicados en revista indexadas por Colciencias * Dos libros resultados de investigación * Formación de cuatro (4) estudiantes de pregrado en investigación formativa: 2 estudiantes de la Tecnología en Saneamiento Ambiental y/o Ingeniería Sanitaria de la Universidad Distrital y 2 estudiantes de Ingeniería Civil de la Universidad de Sucre * Ocho (8) ponencias en Congresos y/o Seminarios especializados | AC33: =+IFERROR(P33/L33,0%) -> 0 | AD33: =+IFERROR((Q33+R33)/L33,0%) -> 0.77590431 | AE33: =IFERROR(Q33/(Q33+R33),0%) -> 0.55215834 | AF33: =IFERROR(R33/(Q33+R33),0%) -> 0.44784166 | AG33: =+IFERROR((S33+T33)/L33,0%) -> 0.22409569 | AH33: =+IFERROR((U33+V33)/L33,0%) -> 0 | AI33: =+IFERROR((W33+X33)/L33,0%) -> 0 | AJ33: =+IFERROR((Y33+Z33)/L33,0%) -> 0
A34: 2022 | B34: Propuesta de Investigación Alianza Convenio | C34: Contrato firmado | D34: N/A | E34: N/A | F34: N/A | G34: Aliado | H34: UPN | I34: N/A | J34: 18 | K34: UDFJC Representación, Discurso y Poder UPN Filosofía y enseñanza de la filosofía | L34: =+SUM(P34:Z34) -> 367001920 | M34: 0 | N34: =+P34+Q34+S34+U34+W34+Y34 -> 10000000 | O34: =+R34+T34+V34+X34+Z34 -> 357001920 | P34: 0 | Q34: 10000000 | R34: 166651200 | S34: 0 | T34: 190350720 | U34: 0 | V34: 0 | W34: 0 | X34: 0 | Y34: 0 | Z34: 0 | AA34: 1. Elaborar dos Informes de avance del proyecto (mes 6 y 12) y un informe final de la Investigación. 2. Capítulo de libro resultados de investigación o artículo de revista. 3. Diseño , aprobación y desarrollo (transferencia) de un seminario dirigido a estudiantes de posgrado. 4. Organización de un evento de carácter académico. 5. Adjuntar Certificación de participación en espacios de socialización en eventos internos institucionales | AB34: 1. Un documento en revista indexada o un capítulo de libro que recoja los hallazgos de la investigación. 2. Diseño y aprobación de un curso dirigido a estudiantes de posgrado. 3. Organización de un evento de carácter académico. 4. Vinculación de un estudiante de Maestría en Educación, que organice su trabajo de grado en el marco de la discusión que el proyecto propone. | AC34: =+IFERROR(P34/L34,0%) -> 0 | AD34: =+IFERROR((Q34+R34)/L34,0%) -> 0.4813359 | AE34: =IFERROR(Q34/(Q34+R34),0%) -> 0.05660873 | AF34: =IFERROR(R34/(Q34+R34),0%) -> 0.94339127 | AG34: =+IFERROR((S34+T34)/L34,0%) -> 0.5186641 | AH34: =+IFERROR((U34+V34)/L34,0%) -> 0 | AI34: =+IFERROR((W34+X34)/L34,0%) -> 0 | AJ34: =+IFERROR((Y34+Z34)/L34,0%) -> 0
A35: 2018 | B35: Propuesta de Investigación Alianza Convenio | C35: Desistio | D35: N/A | E35: N/A | F35: Secretaria de Gobierno Bogotá | G35: Ejecutor | H35: Secretaria de Gobierno Bogotá | I35: N/A | J35: 3 | K35: N/A | L35: =+SUM(P35:Z35) -> 529900000 | M35: 0 | N35: =+P35+Q35+S35+U35+W35+Y35 -> 508900000 | O35: =+R35+T35+V35+X35+Z35 -> 21000000 | P35: 0 | Q35: 82000000 | R35: 21000000 | S35: 426900000 | T35: 0 | U35: 0 | V35: 0 | W35: 0 | X35: 0 | Y35: 0 | Z35: 0 | AA35: La Secretaría Distrital de Gobierno a través de la Subsecretaría de Gestión Local liderará una campaña de investigación, formación, sensibilización y socialización dirigida a las Juntas de Acción Comunal (JAC) que sean priorizadas con el fin de fortalecer la apropiación del Código Nacional de Policía y Convivencia en las comunidades que sirva a su vez como mecanismo de prevención de contravenciones, mejoramiento de la convivencia, desarrollo activo del control social informal, apropiación de valores, entre otros. | AB35: * Documento sobre análisis de percepción con los actores del proceso de formación sobre el estado de la convivencia y la seguridad ciudadana en los territorios de Bogotá. * Un documento de análisis sobre algunas alternativas a la seguridad, basado en las opiniones y propuestas de los actores del proceso de formación | AC35: =+IFERROR(P35/L35,0%) -> 0 | AD35: =+IFERROR((Q35+R35)/L35,0%) -> 0.1943763 | AE35: =IFERROR(Q35/(Q35+R35),0%) -> 0.7961165 | AF35: =IFERROR(R35/(Q35+R35),0%) -> 0.2038835 | AG35: =+IFERROR((S35+T35)/L35,0%) -> 0.8056237 | AH35: =+IFERROR((U35+V35)/L35,0%) -> 0 | AI35: =+IFERROR((W35+X35)/L35,0%) -> 0 | AJ35: =+IFERROR((Y35+Z35)/L35,0%) -> 0
A36: 2019 | B36: Propuesta de Investigación Convocatoria | C36: No Avalada | D36: VIII UNIMINUTO | E36: N/A | F36: UNIMINUTO | G36: Co-ejecutor | H36: N/A | I36: N/A | J36: 12 | K36: N/A | L36: =+SUM(P36:Z36) -> 29000000 | M36: 0 | N36: =+P36+Q36+S36+U36+W36+Y36 -> 29000000 | O36: =+R36+T36+V36+X36+Z36 -> 0 | P36: 29000000 | Q36: 0 | R36: 0 | S36: 0 | T36: 0 | U36: 0 | V36: 0 | W36: 0 | X36: 0 | Y36: 0 | Z36: 0 | AA36: * Memorias de participación en eventos de investigación institucionales internos y externos a nivel nacional donde se presenten las conclusiones del ejercicio de investigación realizada. * Ponencia en evento internacional con memorias indexables en WOS, Scimago o Scopus donde se presenten las conclusiones del ejercicio de investigación realizada, tales como: 1. EUROSCICON LTD, Ocupational Health and Safety 2019, London, UK 2. V Congreso Internacional de Seguridad y Salud en el Trabajo – Osalan 2019 http://www.osalan.euskadi.eus/evento/-/evento/iv-congreso-internacional-de-seguridad-y-salud-en-el-trabajo-osalan-y-la-prevencion-de-riesgos-una-trayectoria-de-25-anos/ | AB36: * Artículo de investigación sometido en revista indexada internacional, en el cual se plasme el proceso investigativo desarrollado y los resultados obtenidos. 1. AIHA journal : a journal for the science of occupational and environmental health and safety UK 2. Safety and Health at Work, South Korea * Libro resultado de investigación, donde desde la seguridad y salud en el trabajo se plasmen condiciones y estrategias para el mejoramiento d ela calidad d evida y la formalizaciones de quienes trabajan en la informalidad | AC36: =+IFERROR(P36/L36,0%) -> 1 | AD36: =+IFERROR((Q36+R36)/L36,0%) -> 0 | AE36: =IFERROR(Q36/(Q36+R36),0%) -> 0 | AF36: =IFERROR(R36/(Q36+R36),0%) -> 0 | AG36: =+IFERROR((S36+T36)/L36,0%) -> 0 | AH36: =+IFERROR((U36+V36)/L36,0%) -> 0 | AI36: =+IFERROR((W36+X36)/L36,0%) -> 0 | AJ36: =+IFERROR((Y36+Z36)/L36,0%) -> 0
A37: 2019 | B37: Propuesta de Investigación Convocatoria | C37: No Avalada | D37: No es una convocatoria | E37: N/A | F37: Fundación para la Promoción de la Investigación y la Tecnología del Banco de la República | G37: Ejecutor | H37: N/A | I37: N/A | J37: 12 | K37: N/A | L37: =+SUM(P37:Z37) -> 20408000 | M37: 0 | N37: =+P37+Q37+S37+U37+W37+Y37 -> 17629000 | O37: =+R37+T37+V37+X37+Z37 -> 2779000 | P37: 17629000 | Q37: 0 | R37: 2779000 | S37: 0 | T37: 0 | U37: 0 | V37: 0 | W37: 0 | X37: 0 | Y37: 0 | Z37: 0 | AA37: 0 | AB37: 0 | AC37: =+IFERROR(P37/L37,0%) -> 0.86382791 | AD37: =+IFERROR((Q37+R37)/L37,0%) -> 0.13617209 | AE37: =IFERROR(Q37/(Q37+R37),0%) -> 0 | AF37: =IFERROR(R37/(Q37+R37),0%) -> 1 | AG37: =+IFERROR((S37+T37)/L37,0%) -> 0 | AH37: =+IFERROR((U37+V37)/L37,0%) -> 0 | AI37: =+IFERROR((W37+X37)/L37,0%) -> 0 | AJ37: =+IFERROR((Y37+Z37)/L37,0%) -> 0
A38: 2019 | B38: Propuesta de Investigación Convocatoria | C38: No Avalada | D38: 844 | E38: CONVOCATORIA PACTO PARA LA GENERACIÓN DE NUEVO CONOCIMIENTO A TRAVÉS DE PROYECTOS DE INVESTIGACIÓN CIENTÍFICA EN CIENCIAS MÉDICAS Y DE LA SALUD. | F38: MinCiencias | G38: Co-ejecutor | H38: 1- Universidad Manuela Beltrán 2- Universidad Pedagógica y Tecnológica de Colombia UPTC | I38: N/A | J38: 36 | K38: UDFJC: - DIGITI - SISTEMAS DIGITALES INTELIGENTES UPTC: - GENTE - DITMAV- Diseño, Innovación y Asistencia Técnica para Materiales Avanzados UMB: - Ingeniería Biomédica - GIIB_UMB | L38: =+SUM(P38:Z38) -> 714242718 | M38: 0 | N38: =+P38+Q38+S38+U38+W38+Y38 -> 365376204 | O38: =+R38+T38+V38+X38+Z38 -> 348866514 | P38: 349776204 | Q38: 8200000 | R38: 97906724 | S38: 4200000 | T38: 142308752 | U38: 3200000 | V38: 108651038 | W38: 0 | X38: 0 | Y38: 0 | Z38: 0 | AA38: • Identificación de variables biomecánicas determinantes en la alineación en condiciones estáticas y dinámicas de una persona que utiliza prótesis transtibial. • Protocolo de medición para la obtención de las variables biomecánicas de los sujetos amputados transtibiales. • Identificación de los factores y/o parámetros que utilizan los médicos o técnicos protesistas para realizar la alineación de las prótesis transtibiales. • Identificación de las características y parámetros que los usuarios de prótesis transtibiales tienen sobre las prótesis. • Caracterización de la población que usan prótesis transtibiales. • Caracterización de las variables biomecánicas obtenidas durante las pruebas de estabilidad estática y dinámica. • Análisis estadístico de las variables biomecánicas obtenidas durante las pruebas de estabilidad estática y dinámica. • Identificación por significancia estadística, de las variables biomecánicas determinantes en la alineación en condiciones estáticas y dinámicas de una persona que utiliza prótesis transtibial • Diseño de un prototipo para obtener las variables biomecánicas determinantes en la alineación de prótesis transtibiales en condiciones estáticas y dinámicas. • Conocimiento en las diferentes técnicas que se deben realizar para la validación del prototipo. • Desarrollo de un software que indique las características con la óptima alineación de la prótesis transtibial de acuerdo a unos parámetros de entrada. • Conocimiento sobre las diversas teorías de información para el desarrollo del sistema para la alineación. • Desarrollo de un protocolo para la validación del sistema contrastando la información obtenida sobre las técnicas y parámetros que usan los médicos y técnicos protesistas para la alineación de las prótesis transtibiales, así como los registrados por los usuarios. • Conocimiento en el desarrollo del protocolo final para realizar la alineación de la prótesis transtibial usando el sistema diseñado en la presente investigación. • Conocimiento en el desarrollo de manuales de usuario para el buen uso y funcionamiento del sistema de alineación para prótesis transtibiale | AB38: - Dos (2) artículos categoría A1 - Un (1) artículo categoría B - Un (1) libro de investigación - Informes técnicos - Software - Protótipo Industrial - Protocolo para realizar la alineación de las prótesis transtibiales - Asistencia a dos (2) ponencias - Asistencia a dos (2) eventos científicos - Vinculación de cuatro (4) estudiantes de pregrado (UD-UMB-UPTC) - Vinculación un (1) estudiante de maestría (UD) | AC38: =+IFERROR(P38/L38,0%) -> 0.48971616 | AD38: =+IFERROR((Q38+R38)/L38,0%) -> 0.14855836 | AE38: =IFERROR(Q38/(Q38+R38),0%) -> 0.077280682 | AF38: =IFERROR(R38/(Q38+R38),0%) -> 0.92271932 | AG38: =+IFERROR((S38+T38)/L38,0%) -> 0.2051246 | AH38: =+IFERROR((U38+V38)/L38,0%) -> 0.15660088 | AI38: =+IFERROR((W38+X38)/L38,0%) -> 0 | AJ38: =+IFERROR((Y38+Z38)/L38,0%) -> 0
A39: 2019 | B39: Propuesta de Investigación Convocatoria | C39: No Avalada | D39: 849 | E39: CONVOCATORIA DE PROYECTOS DE I+D+i PARA EL FORTALECIMIENTO DEL PLANEAMIENTO MINERO ENERGÉTICO | F39: MinCiencias | G39: Ejecutor | H39: 1- Universidad de Sevilla 2- Universidad de Cádiz 3- Universidad Nacional de Manizales | I39: N/A | J39: 10 | K39: UDFJC: - GIEAUD - GRINSAUD Universidad de Sevilla: - Termotecnia Universidad de Cádiz: - Ingeniería Térmica | L39: =+SUM(P39:Z39) -> 482142000 | M39: 0 | N39: =+P39+Q39+S39+U39+W39+Y39 -> 399324000 | O39: =+R39+T39+V39+X39+Z39 -> 82818000 | P39: 399324000 | Q39: 0 | R39: 82818000 | S39: 0 | T39: 0 | U39: 0 | V39: 0 | W39: 0 | X39: 0 | Y39: 0 | Z39: 0 | AA39: Se espera crear una referencia que hasta el momento no se puede encontrará de manera gratuita ni formal por parte del estado, esta referencia se compondrá de archivos climáticos representativitos de varios municipios del país. Adicionalmente al adquirir el Meteonorm, el Grupo de investigación y Así la universidad misma, tendrán una herramienta para generar archivos climáticos particulares para evaluación, fomentando la generación de convenios de cooperación con otras instituciones o entidades. Se podrá sustentar que los archivos climáticos anteriores son correspondientes a los datos entregados por el IDEAM, no en valor sino en tendencia. Se generará un producto de fácil visualización de la extensa información que presentan estos archivos climáticos. Se concluye un modelo de severidad climática en Colombia para el análisis de la demanda energética en la edificación que también soporta el consumo de los equipos, así como la determinación de la eficiencia energética en la edificación, una de las razones por las cuales Colombia aún no presenta dichos parámetros. Se establecen ciudades representativas para la severidad climática las cuales pueden ser usadas para conclusiones en comportamientos de sistemas La tipología de la construcción en Colombia establece la forma como se construye, pero no su relación en cuanto al impacto energético de la construcción, esto debería sustentar los beneficios de la edificación “Vernácula” Se pretende concluir con datos de propiedades térmicas y de transporte de los materiales que se usan en la construcción, información fundamental para el análisis del comportamiento energético del edifico en función de la demanda Se espera comprobar el comportamiento energético del edificio mediante pruebas de termografía Obtendrá una referencia específica que hasta el momento no existe específicamente para el país, por lo que no se sabe la relación entre archivos climáticos oficiales, comportamiento energético de la edificación en función de la demanda y su relación con el confort adaptativo. Este rango es primordial para la definición de la eficiencia energética en la edificación, si este no se obtiene no es posible definirla de manera concreta. | AB39: Vinculación de estudiante de maestría en el marco del proyecto Vinculación de estudiante de ingeniería en el marco del proyecto Vinculación de estudiante de tecnología en el marco del proyecto Formación de estudiante de maestría en el marco del proyecto Participación en 2 ponencias Dos (2) Red creada o articulación en una red a nivel nacional o internacional Presentación de los resultados ante las autoridades competentesIDEAM, constructores, proveedores de materiales de construcción y Academia Publicación de dos (2) Artículos de investigación A1, A2, B y C | AC39: =+IFERROR(P39/L39,0%) -> 0.82822903 | AD39: =+IFERROR((Q39+R39)/L39,0%) -> 0.17177097 | AE39: =IFERROR(Q39/(Q39+R39),0%) -> 0 | AF39: =IFERROR(R39/(Q39+R39),0%) -> 1 | AG39: =+IFERROR((S39+T39)/L39,0%) -> 0 | AH39: =+IFERROR((U39+V39)/L39,0%) -> 0 | AI39: =+IFERROR((W39+X39)/L39,0%) -> 0 | AJ39: =+IFERROR((Y39+Z39)/L39,0%) -> 0
A40: 2019 | B40: Propuesta de Investigación Convocatoria | C40: No Avalada | D40: 849 | E40: CONVOCATORIA DE PROYECTOS DE I+D+i PARA EL FORTALECIMIENTO DEL PLANEAMIENTO MINERO ENERGÉTICO | F40: MinCiencias | G40: Ejecutor | H40: N/A | I40: N/A | J40: 10 | K40: UDFJC: - GESETIC - Grupo de Compatibilidad e Interferencia Electromagnética GCEM - Grupo de Investigación Internacional en Informática, Comunicación y Gestión del Conocimiento "GICOGE" | L40: =+SUM(P40:Z40) -> 249600005 | M40: 0 | N40: =+P40+Q40+S40+U40+W40+Y40 -> 172700000 | O40: =+R40+T40+V40+X40+Z40 -> 76900005 | P40: 172700000 | Q40: 0 | R40: 76900005 | S40: 0 | T40: 0 | U40: 0 | V40: 0 | W40: 0 | X40: 0 | Y40: 0 | Z40: 0 | AA40: - Vinculación 2 estudiantes de pregrado - Vinculación 1 estudiante de doctorado - Dos trabajos de pregrado de estudiantes del programa de Ingeniería Eléctrica | AB40: - Dos Artículos de categoría A2 - Informe parcial y final del proyecto de investigación - Una ponencia nacional y una ponencia internacional en Congresos de alto impacto - Curso corto de modelamiento de aplicaciones de software para la integración de recursos energéticos distribuidos de energía y gestión de redes eléctricas de distribución (duración de 20 horas) - Desarrollo de tesis de alumno de pregrado en el marco del desarrollo del proyecto de investigación - Elaboración de propuesta de investigación doctoral dentro del marco de desarrollo del proyecto - Un trabajo de pregrado de estudiantes del programa de Ingeniería Eléctrica | AC40: =+IFERROR(P40/L40,0%) -> 0.69190704 | AD40: =+IFERROR((Q40+R40)/L40,0%) -> 0.30809296 | AE40: =IFERROR(Q40/(Q40+R40),0%) -> 0 | AF40: =IFERROR(R40/(Q40+R40),0%) -> 1 | AG40: =+IFERROR((S40+T40)/L40,0%) -> 0 | AH40: =+IFERROR((U40+V40)/L40,0%) -> 0 | AI40: =+IFERROR((W40+X40)/L40,0%) -> 0 | AJ40: =+IFERROR((Y40+Z40)/L40,0%) -> 0
A41: 2019 | B41: Propuesta de Investigación Convocatoria | C41: No Avalada | D41: 852 | E41: CONVOCATORIA CONECTANDO CONOCIMIENTO 2019 | F41: MinCiencias | G41: Co-ejecutor | H41: 1- Universidad Cooperativa de Colombia (ejecutora) 2- Institución universitaria Politécnico Grancolombiano (co-ejecutora) | I41: N/A | J41: 24 | K41: UDFJC: - GIIRA UCC: - INGENIO INDUSPYMES IUPG: - FICB-PG | L41: =+SUM(P41:Z41) -> 897805227 | M41: 0 | N41: =+P41+Q41+S41+U41+W41+Y41 -> 359570757 | O41: =+R41+T41+V41+X41+Z41 -> 538234470 | P41: 335721015 | Q41: 0 | R41: 184320000 | S41: 11924871 | T41: 236429670 | U41: 11924871 | V41: 117484800 | W41: 0 | X41: 0 | Y41: 0 | Z41: 0 | AA41: - Evaluar la producción de ácidos grasos volátiles AGV’s, bajo distintos valores de carga orgánica, tiempo de retención hidráulica y temperatura mediante pruebas a escala de laboratorio. - Desarrollar una metodología a escala de laboratorio para el enriquecimiento de biomasa con el propósito de producir polihidroxialcanoatos PHA’s a partir de cultivos mixtos. - Establecer las condiciones de operación a escala de laboratorio y pruebas piloto que permitan la producción de polihidroxialcanoatos PHA’s, con los mejores rendimientos. - Evaluar las variables y parámetros del proceso de producción de polihidroxialcanoatos PHA’s a partir de cultivos mixtos y fuentes de carbono renovables mediante una técnica de análisis visual. - Calcular el potencial económico y los impactos ambientales del proceso de producción de polihidroxialcanoatos PHA´s propuesto a escala industrial, empleando software de simulación. | AB41: - Artículos de investigación: Dos (2) categoría A2 y uno (1) categoría B - Dos (2) ponencias internacionales - Vinculación de un (1) estudiante de doctorado - Vinculación de un (1) estudiante de maestría - Formación de cuatro (4) estudiantes de pregrado | AC41: =+IFERROR(P41/L41,0%) -> 0.37393524 | AD41: =+IFERROR((Q41+R41)/L41,0%) -> 0.20530065 | AE41: =IFERROR(Q41/(Q41+R41),0%) -> 0 | AF41: =IFERROR(R41/(Q41+R41),0%) -> 1 | AG41: =+IFERROR((S41+T41)/L41,0%) -> 0.27662408 | AH41: =+IFERROR((U41+V41)/L41,0%) -> 0.14414003 | AI41: =+IFERROR((W41+X41)/L41,0%) -> 0 | AJ41: =+IFERROR((Y41+Z41)/L41,0%) -> 0
A42: 2023 | B42: Propuesta de Investigación Alianza Convenio | C42: Contrato firmado | D42: N/A | E42: N/A | F42: IDEP | G42: Aliado | H42: 1- INSTITUTO PARA LA INVESTIGACIÓN EDUCATIVA Y EL DESARROLLO PEDAGÓGICO - IDEP | I42: N/A | J42: 8 | K42: UDFJC: - Vivencias | L42: =+SUM(P42:Z42) -> 180000000 | M42: 100000000 | N42: =+P42+Q42+S42+U42+W42+Y42 -> 130000000 | O42: =+R42+T42+V42+X42+Z42 -> 50000000 | P42: 100000000 | Q42: 30000000 | R42: 50000000 | S42: 0 | T42: 0 | U42: 0 | V42: 0 | W42: 0 | X42: 0 | Y42: 0 | Z42: 0 | AA42: 0 | AB42: - Informe de investigación - Artículos Académicos en revistas con ISSN o Indexadas - Dos Cartillas - Evento académico - Micrositio - Proceso formativo/investigativo | AC42: =+IFERROR(P42/L42,0%) -> 0.55555556 | AD42: =+IFERROR((Q42+R42)/L42,0%) -> 0.44444444 | AE42: =IFERROR(Q42/(Q42+R42),0%) -> 0.375 | AF42: =IFERROR(R42/(Q42+R42),0%) -> 0.625 | AG42: =+IFERROR((S42+T42)/L42,0%) -> 0 | AH42: =+IFERROR((U42+V42)/L42,0%) -> 0 | AI42: =+IFERROR((W42+X42)/L42,0%) -> 0 | AJ42: =+IFERROR((Y42+Z42)/L42,0%) -> 0
A43: 2019 | B43: Propuesta de Investigación Convocatoria | C43: Contrato firmado | D43: Invitación InvestigARTE | E43: Invitación a presentar proyectos de investigación + Creación en Artes InvestigARTE | F43: MinCiencias | G43: Co-ejecutor | H43: 1- Universidad de Antioquia 2- Corporación Artística ImaginEros 3- Casa Benet Domingo (Brasil) | I43: N/A | J43: 24 | K43: UDFJC: - Investigación para la creación artística UdeA: Teoría e Historia del Arte en Colombia | L43: =+SUM(P43:Z43) -> 305161000 | M43: 0 | N43: =+P43+Q43+S43+U43+W43+Y43 -> 212000000 | O43: =+R43+T43+V43+X43+Z43 -> 93161000 | P43: 210000000 | Q43: 0 | R43: 27720000 | S43: 2000000 | T43: 40551000 | U43: 0 | V43: 13640000 | W43: 0 | X43: 11250000 | Y43: 0 | Z43: 0 | AA43: El proyecto presentado no configura un objeto de investigación cerrado, por el contrario se expande hacia diferentes escenarios, y se espera generar impactos que conciernen a la incitación del pensamiento crítico en la comunidad, estudiantes, profesores y creadores; despertar en ellos una inquietud por construir saberes en consonancia con sus contextos de vida, la detonación de afectos y perceptos en sus prácticas cotidianas, laborales, académicas y de creación, que permitan expandir sus referentes y apuestas estéticas, éticas y políticas en el arte.Por ello se trabajará desde la investigación-creación para generar una reflexión en torno a la importancia de esta práctica y cómo ello repercute en espacios sociales y políticos. Se espera entonces que haya un despliegue en este campo que permita a grupos artísticos, entidades culturales e instituciones educativas tener un panorama expandido de sus alcances y significación para que se convierta en un material de consulta para la sociedad. Se ampliará el estado del arte de la investigación-creación dentro del marco de la investigación en Colombia y cómo desde este lugar se proporcionan maneras y estrategias que pueden alimentar los procesos científicos, sociales y humanos. Se espera realizar un marco teórico amplio que dé elementos de discusión en torno al arte contemporáneo, a las prácticas pedagógicas y sociales y muy especialmente a la performance, lo cual lleve a nuevas preguntas, ampliar los debates, generar posibilidades para estudiantes de arte o de otras disciplinas, integrar saberes y producir espacios de discusión y creación como seminarios, talleres, nuevas asignaturas, intercambios, asesorías en pregrados, posgrados e inferir en las políticas culturales locales, nacionales e internacionales. Para ello se desplegarán conceptos que hasta ahora no han sido trabajados de manera muy profunda en el ámbito artístico como la fabulación, el acontecimiento artístico, la performance, la cartografía, la construcción de subjetividades, la resistencia. La escritura como práctica permite una apropiación del conocimiento y el ejercicio argumental para la publicación en revistas, periódicos, libros, en fin, una posibilidad de creación y ampliación de conceptos y términos desde diversas áreas: filosofía, antropología, sociología, arte, incluso otros saberes más exactos. Se espera crear, revisar y publicar artículos en revistas indexadas, en otras revistas, en periódicos y sistematizar la investigación en un libro que pueda ser material de consulta y de referencia, para ello es preciso actualizar los referentes artísticos y conceptuales, indagar, hacer analogías, cruzar saberes y experiencias con otras ciudades y otros actores. Se intenta así mismo crear una puesta en escena performática que tenga un impacto social dentro de las ciudades en las cuales se hará esta investigación, en la que se recoja la experiencia de todo el proceso en una acción fabuladora para la configuración de nuevos mundos, la cual pueda itinerar por diferentes escenarios del país y el mundo y se convierta en una propuesta innovadora enmarcada en un acto comunitario, producto de una convocatoria amplia que genere puntos de fuga como resistencia frente a la muerte y la violencia que vive nuestro país. Una acción de grandes alcances para no olvidar el horror. Ello implica un entrenamiento constante tanto físico como intelectual, encuentros para diseñar, experimentar, debatir y crear; un reconocimiento del cuerpo y de las capacidades ante el reto de la creación, un trabajo interdisciplinario y un diálogo de saberes, así como la posibilidad de estar juntos en un pacto por la vida. Un proceso de largo aliento también presenta momentos difíciles y sea esta la oportunidad para diseñar estrategias que nos ayuden a permanecer y resistir, entender que el malestar y el disensoson partes fundamentales de un trabajo colectivo y es necesario atender a estos momentos para crecer en colectividad y ver cómo la resolución de los diferentes conflictos que se presenten, puede resonar en los ámbitos educativos, sociales y artísticos en que nos movemos. Los viajes e intercambios tanto virtuales (redes sociales) como presenciales, abren posibilidades de entender otras maneras de apropiación del conocimiento, la variedad de prácticas culturales, formas de vestir, hablar, comer, bailar, en fin, todo un universo que abre oportunidades y genera acciones que repercuten en las dinámicas vitales de cada uno y de todo el equipo, lo que tiene consecuencias en la construcción de propuestas artísticas, pedagógicas y políticas que posibiliten el acercamiento a la invitación de Foucault de hacer de la vida una obra de arte. | AB43: 1. Generación de nuevo conocimiento ● Un artículo de nuevo conocimiento para publicar en revista indexada A1. ● 3 Publicaciones en otras revistas de circulación nacional o internacional. ● Realización de una propuesta artística (performance) con la comunidad que evidencie los hallazgos de la investigación que hará una itinerancia por las ciudades beneficiarias del proyecto. ● Un libro resultado de la investigación. ● Implementación de una estrategia de investigación cartográfica que permita expandir los hallazgos en relación con la vida. ● La apertura de nuevos conceptos que sirvan para la ampliación de referentes artísticos, pedagógicos, éticos, estéticos y políticos. 2. Apropiación social del conocimiento ● Creación de un seminario en el cual participen los investigadores, estudiantes en formación de pregrado y posgrado e invitados académicos que dialoguen con las búsquedas de la investigación. ● Ponencia y socialización del proceso de investigación y los hallazgos encontrados en las diferentes ciudades en que se realice el proyecto. ● Presentación de un registro audiovisual que condense las propuestas artísticas, talleres, seminarios e intervenciones con la comunidad. ● Afianzamiento de la participación en Redes de conocimiento nacionales e internacionales, que permitan una constante retroalimentación e intercambio de saberes sobre la investigación creación. ● Resignificación de las redes sociales como un espacio para el intercambio de información, generación de conocimiento, invitación a la participación, retroalimentación y contacto con la comunidad. ● Se espera la participación de 100 artistas en el diseño, realización y presentación de la performance y más de 2.000 personas que sean los intercesores (espectadores) delproceso en las diferentes ciudades. ● Devolución del proceso a las comunidades que permita el diálogo de saberes, la retroalimentación con las diferentes entidades culturales, educativas y pedagógicas en que nos movemos. ● Realización de encuentros entre comunidades que permita emplazar a la comunidad como protagonista del proceso. 3. Formación de Recurso Humano en el CTel ● Formación estudiante de Doctorado. Doctorado en Artes. ● Formación estudiante de Maestría. Maestría en Estética. ● Formación estudiante de Maestría. Maestría en Educación y Derechos Humanos. ● Formación de estudiantes de pregrado en diferentes áreas del conocimiento. ● Fortalecimiento en las estrategias de trabajo entre los grupos de Investigación participantes, la Corporación Artística ImaginEros y su semillero de creación y la Casa Benet Domingo. ● Apertura de una nueva asignatura en forma de seminario en Medellín y Cartagena dividido en módulos para generar un intercambio de experiencias y saberes. ● Asesoría de tesis de pregrado y posgrado que se formulen dentro de la investigación-creación o escenarios afines. | AC43: =+IFERROR(P43/L43,0%) -> 0.68816133 | AD43: =+IFERROR((Q43+R43)/L43,0%) -> 0.090837296 | AE43: =IFERROR(Q43/(Q43+R43),0%) -> 0 | AF43: =IFERROR(R43/(Q43+R43),0%) -> 1 | AG43: =+IFERROR((S43+T43)/L43,0%) -> 0.13943787 | AH43: =+IFERROR((U43+V43)/L43,0%) -> 0.044697717 | AI43: =+IFERROR((W43+X43)/L43,0%) -> 0.036865786 | AJ43: =+IFERROR((Y43+Z43)/L43,0%) -> 0
A44: 2019 | B44: Propuesta de Investigación Convocatoria | C44: No Avalada | D44: 852 | E44: CONVOCATORIA CONECTANDO CONOCIMIENTO 2019 | F44: MinCiencias | G44: Ejecutor | H44: N/A | I44: N/A | J44: 24 | K44: N/A | L44: =+SUM(P44:Z44) -> 441624352 | M44: 0 | N44: =+P44+Q44+S44+U44+W44+Y44 -> 322624352 | O44: =+R44+T44+V44+X44+Z44 -> 119000000 | P44: 294774610 | Q44: 27849742 | R44: 119000000 | S44: 0 | T44: 0 | U44: 0 | V44: 0 | W44: 0 | X44: 0 | Y44: 0 | Z44: 0 | AA44: Esta propuesta de investigación puede arrojar como resultados: - La generación de nuevo conocimiento en el ámbito de los estudios sociales contemporáneos disciplinares y transdiciplinares que pueden impactar a las comunidades académicas y a las poblaciones beneficiarias, protagonistas en la producción de los lenguajes culturales. - Agenciamiento de centros de pensamiento propio desde las acciones y prácticas de las comunidades a manera de capacidad instalada con los territorios. De manera que se fortalezcan los territorios de impacto. | AB44: - Galería itinerante del proceso de investigación realizado en el territorio - Un artículo categoría A1 - Dos artículos categoría C - Un libro categoría A - Un libro categoría A1 - Un capítulo de libro categoría B - Informe de línea de base que sirva como insumo para el desarrollo de futuros proyectos de investigación - Tres ponencias en Eventos Internacionales - Realización de tres programas de radio sobre el proceso de investigación - Tres Ponencias en Eventos Nacionales - Vinculación de dos Jóvenes Investigadores - Formación tres estudiantes de maestria | AC44: =+IFERROR(P44/L44,0%) -> 0.66747816 | AD44: =+IFERROR((Q44+R44)/L44,0%) -> 0.33252184 | AE44: =IFERROR(Q44/(Q44+R44),0%) -> 0.18964788 | AF44: =IFERROR(R44/(Q44+R44),0%) -> 0.81035212 | AG44: =+IFERROR((S44+T44)/L44,0%) -> 0 | AH44: =+IFERROR((U44+V44)/L44,0%) -> 0 | AI44: =+IFERROR((W44+X44)/L44,0%) -> 0 | AJ44: =+IFERROR((Y44+Z44)/L44,0%) -> 0
A45: 2019 | B45: Propuesta de Investigación Convocatoria | C45: No Avalada | D45: 852 | E45: CONVOCATORIA CONECTANDO CONOCIMIENTO 2019 | F45: MinCiencias | G45: Ejecutor | H45: 1- Universidad de los Llanos (Ull) 2- Universidad Surcolombiana (USC) 3- Universidad de la Amazonía (UA) 4- Universidad Santo Tomás (UST) | I45: CAPACIDADES COMUNITARIAS EN ZONAS RURALES DE POSACUERDO: OPORTUNIDADES PARA DISMINUIR DESIGUALDADES | J45: 24 | K45: UDFJC: - MORALIA UII: - GRITOX USC: - CRECER UA: - ANAKEKO UST: - ABA | L45: =+SUM(P45:Z45) -> 2116363764 | M45: 0 | N45: =+P45+Q45+S45+U45+W45+Y45 -> 1476363764 | O45: =+R45+T45+V45+X45+Z45 -> 640000000 | P45: 1294814538 | Q45: 63849742 | R45: 340000000 | S45: 11924871 | T45: 160000000 | U45: 46924871 | V45: 60000000 | W45: 21924871 | X45: 80000000 | Y45: 36924871 | Z45: 0 | AA45: - Vinculación de seis (6) jóvenes investigadores al programa de investigación - Vinculación de seis (6) estudiantes del pregrado en temas relacionados con el programa. - Formación de cinco (5)estudiantes del pregrado en temas relacionados con el programa. - Formación de seis (6) estudiantes de maestría en el marco del programa de investigación. - Formación de un (1) estudiante de doctorado en el marco del programa de investigación - Participación en veinte (20) eventos socializando los resultados de investigación del programa. - Participación o realización de veinte (20) eventos académicos orientados a la presentación de los resultados de investigación del programa - Presentación de cinco (5) resultados de investigación a través de diferentes estrategias (piezas comunicativas) - Desarrollo de diez (10) talleres, o seminarios, o cursos, entre otros espacios para la retroalimentación y divulgación de los resultados de investigación del programa a la comunidad civil - Desarrollo de diez (10) talleres, o seminarios, o cursos, entre otros espacios para la retroalimentación y divulgación de los resultados de investigación del programa a la comunidad científica - Creación o participación en cinco (5) redes de conocimiento, nacional o internacional, que trabaje temas relacionados con los proyectos que involucra el programa de investigación. | AB45: - Cuatro (4) artículos publicados en revistas indexadas. - Dos (2) libros publicados con los resultados de la investigación. - Cinco (5) capítulos de libro publicados | AC45: =+IFERROR(P45/L45,0%) -> 0.61181096 | AD45: =+IFERROR((Q45+R45)/L45,0%) -> 0.19082246 | AE45: =IFERROR(Q45/(Q45+R45),0%) -> 0.15810272 | AF45: =IFERROR(R45/(Q45+R45),0%) -> 0.84189728 | AG45: =+IFERROR((S45+T45)/L45,0%) -> 0.081235974 | AH45: =+IFERROR((U45+V45)/L45,0%) -> 0.050522917 | AI45: =+IFERROR((W45+X45)/L45,0%) -> 0.048160374 | AJ45: =+IFERROR((Y45+Z45)/L45,0%) -> 0.017447318
A46: 2019 | B46: Propuesta de Investigación Convocatoria | C46: No Avalada | D46: 852 | E46: CONVOCATORIA CONECTANDO CONOCIMIENTO 2019 | F46: MinCiencias | G46: Ejecutor | H46: N/A | I46: Pertenence a un programa | J46: 24 | K46: N/A | L46: =+SUM(P46:Z46) -> 444812175 | M46: 0 | N46: =+P46+Q46+S46+U46+W46+Y46 -> 274812175 | O46: =+R46+T46+V46+X46+Z46 -> 170000000 | P46: 237887305 | Q46: 36924870 | R46: 170000000 | S46: 0 | T46: 0 | U46: 0 | V46: 0 | W46: 0 | X46: 0 | Y46: 0 | Z46: 0 | AA46: - Vinculación de un (1) joven investigador al programa de investigación - Formación de dos (2) estudiantes de maestría en el marco del programa de investigación. - Formación de un (1) estudiante de doctorado en el marco del programa de investigación - Participación en cuatro (4) eventos socializando los resultados de investigación del programa. - Participación o realización de cuatro (4) eventos académicos orientados a la presentación de los resultados de investigación del programa - Presentación de un (1) resultados de investigación a través de diferentes estrategias (piezas comunicativas) - Desarrollo de dos (2) talleres, o seminarios, o cursos, entre otros espacios para la retroalimentación y divulgación de los resultados de investigación del programa a la comunidad civil - Desarrollo de dos (2) talleres, o seminarios, o cursos, entre otros espacios para la retroalimentación y divulgación de los resultados de investigación del programa a la comunidad científica - Creación o participación en una (1) red de conocimiento, nacional o internacional, que trabaje temas relacionados con los proyectos que involucra el programa de investigación. | AB46: - Un (1) artículo publicado en revistas indexadas. - Un (1) libro publicado con los resultados de la investigación. - Un (1) capítulo de libro publicado | AC46: =+IFERROR(P46/L46,0%) -> 0.53480394 | AD46: =+IFERROR((Q46+R46)/L46,0%) -> 0.46519606 | AE46: =IFERROR(Q46/(Q46+R46),0%) -> 0.17844578 | AF46: =IFERROR(R46/(Q46+R46),0%) -> 0.82155422 | AG46: =+IFERROR((S46+T46)/L46,0%) -> 0 | AH46: =+IFERROR((U46+V46)/L46,0%) -> 0 | AI46: =+IFERROR((W46+X46)/L46,0%) -> 0 | AJ46: =+IFERROR((Y46+Z46)/L46,0%) -> 0
A47: 2020 | B47: Propuesta de Investigación Convocatoria | C47: Contrato firmado | D47: 872 | E47: Hacia una mayor comprensión del conflicto armado, las víctimas y la historia reciente de Colombia | F47: MinCiencias | G47: Ejecutor | H47: 1- Universidad SurColombiana USC 2- Universidad de la Amazonía UA 3- Fundación para el desarrollo de la educación en la Orinoquía | I47: N/A | J47: 18 | K47: UDFJC - Moralia UA - Ananeko USTV - humanidades digitales, formación y coonstrucción de paz territorial - ABA | L47: =+SUM(P47:Z47) -> 962086576 | M47: 325727305 | N47: =+P47+Q47+S47+U47+W47+Y47 -> 409812176 | O47: =+R47+T47+V47+X47+Z47 -> 552274400 | P47: 357887305 | Q47: 11924871 | R47: 260000000 | S47: 35000000 | T47: 93000000 | U47: 0 | V47: 84274400 | W47: 5000000 | X47: 115000000 | Y47: 0 | Z47: 0 | AA47: - Producción de narrativas (expresiones ilocutivas) acerca de los procesos de subordinación en los territorios rurales, la presencia de hechos bélicos y su impacto en los ambientes escolares. (Instrumentos aplicados: entrevistas narrativas) - Producción de narrativas presentes en memorias del pasado reciente acerca de emociones asociadas a modos de menosprecio y agravios, pero también a formas de resistencia. (Instrumentos aplicados: Foto-biografías territoriales) - Producción de narrativas relacionadas con prácticas en educación para la paz realizadas por los maestros rurales para promover la reconciliación y la reparación simbólica. (Instrumentos aplicados: Estético- analógico, multimodal, digital) - Sistematización de la información. Recolección y organización de la información recogida en los instrumentos de recolección de información (entrevistas narrativas, foto-biografías territoriales y estético –analógico) - Elaboración de piezas comunicativas para dar a conocer la información recolectada en los instrumentos. - Registros audiovisuales para la elaboración de piezas comunicativas. - Documento comprensivo interpretativo con perspectiva interseccional que da cuenta de las aristas de interpretación (subordinación, humillación y comprensión) de la investigación en su componente cualitativo. - Rutas territoriales que visibilicen las prácticas y saberes de los docentes que contribuyen a la construcción del pasado reciente en el territorio. - Material didáctico para la enseñanza del pasado reciente en los territorios. - Dinámicas de vulneración de derechos en clave territorial . Dan cuenta de las condiciones geográficas, características culturales e históricas del territorio, condiciones estatales de abandono, presencia y acciones de organizaciones sociales, entre otros factores. - Identificación de aspectos relacionados con género . Reconociendo las dimensiones plurales y diferenciales del impacto del conflicto armado, en relación con patrones de violencia basados en género: mujeres, jóvenes, adultos, niños, niñas, comunidades LGTBIQ+. - Reconocimiento de aspectos étnicos presentes en cada territorio. Atendiendo a las dimensiones plurales y diferenciadas de patrones de violencia, atendiendo a una perspectiva étnica y cultural para determinar: formas diferenciadas de violencias contra pueblos indígenas, comunidades campesinas, maestros y maestras, poblaciones afrocolombianas, entre otros. - Matriz de subordinación. En tramas narrativas de memorias del pasado, que aportan a la identificación de categorías analíticas para reconocer los atributos estables y recoger información de las características específicas y relativas al fenómeno o realidad. - Matriz de modos de resistencia . En tramas narrativas de memorias del pasado reciente que permiten la identificación de categorías analíticas para develar los fenómenos comunes y discrepantes en el territorio con perspectiva interseccional. - Informe descriptivo analítico. - Categorías (matrices de subordinación y modos de resistencia) Subcategorías, Propiedades, Dimensiones, Indicadores. | AB47: - Un libro de investigación publicado categoría B - Un capítulo de libro publicado categoría B - Un artículo de investigación categoría A1 - Evento de participación ciudadana o de comunidades relacionado con la CTeI - Una cartilla o folleto de divulgación de resultados - Tres cursos de capacitación, seminarios o talleres - Presentación de resultados ante las autoridades competentes. - Una red creada o articulación en una red a nivel nacional o internacional - Generación de contenidos - Vinculación de un joven investigador | AC47: =+IFERROR(P47/L47,0%) -> 0.37199075 | AD47: =+IFERROR((Q47+R47)/L47,0%) -> 0.28264075 | AE47: =IFERROR(Q47/(Q47+R47),0%) -> 0.04385355 | AF47: =IFERROR(R47/(Q47+R47),0%) -> 0.95614645 | AG47: =+IFERROR((S47+T47)/L47,0%) -> 0.13304416 | AH47: =+IFERROR((U47+V47)/L47,0%) -> 0.087595443 | AI47: =+IFERROR((W47+X47)/L47,0%) -> 0.1247289 | AJ47: =+IFERROR((Y47+Z47)/L47,0%) -> 0
A48: 2021 | B48: Propuesta de Investigación Convocatoria | C48: Contrato firmado | D48: N/A | E48: Development of Integrated Techniques for Induced Genetic Diversity and Improvement of Vegetatively Propagated and Horticultural Tree Crops | F48: International Atomic Energy Agency - IAEA | G48: Ejecutor | H48: AGROSAVIA | I48: N/A | J48: 60 | K48: Grupo de investigación biología molecular | L48: =+SUM(P48:Z48) -> 423000 | M48: 50000 | N48: =+P48+Q48+S48+U48+W48+Y48 -> 50000 | O48: =+R48+T48+V48+X48+Z48 -> 373000 | P48: 50000 | Q48: 0 | R48: 373000 | S48: 0 | T48: 0 | U48: 0 | V48: 0 | W48: 0 | X48: 0 | Y48: 0 | Z48: 0 | AA48: Harmonize protocols for in vitro regenerants. Determination of mutated characters as an effect of irradiation Agromorphological, physicochemical and nutritional characterization of the tuber of the genetic variants obtained. Agronomic evaluation tests of mutants obtained Mass production of high quality microtubers / tubers Training in potato genetic improvement processes | AB48: 0 | AC48: =+IFERROR(P48/L48,0%) -> 0.11820331 | AD48: =+IFERROR((Q48+R48)/L48,0%) -> 0.88179669 | AE48: =IFERROR(Q48/(Q48+R48),0%) -> 0 | AF48: =IFERROR(R48/(Q48+R48),0%) -> 1 | AG48: =+IFERROR((S48+T48)/L48,0%) -> 0 | AH48: =+IFERROR((U48+V48)/L48,0%) -> 0 | AI48: =+IFERROR((W48+X48)/L48,0%) -> 0 | AJ48: =+IFERROR((Y48+Z48)/L48,0%) -> 0
A49: 2019 | B49: Propuesta de Investigación Convocatoria | C49: No Avalada | D49: 852 | E49: CONVOCATORIA CONECTANDO CONOCIMIENTO 2019 | F49: MinCiencias | G49: N/A | H49: 1- Universidad Pontificia Javeriana | I49: N/A | J49: 12 | K49: N/A | L49: =+SUM(P49:Z49) -> 0 | M49: 0 | N49: =+P49+Q49+S49+U49+W49+Y49 -> 0 | O49: =+R49+T49+V49+X49+Z49 -> 0 | P49: 0 | Q49: 0 | R49: 0 | S49: 0 | T49: 0 | U49: 0 | V49: 0 | W49: 0 | X49: 0 | Y49: 0 | Z49: 0 | AA49: - Fabricación de una celda solar basada en materiales orgánicos con microestructura y eficiencia de conversión. - 1 Articulo revista internacional - Participación en Congresos/Ponencias/Conferencias/Workshops/Conversatorios Internacionales - Participación de dos jóvenes investigadores en la elaboración de la investigación | AB49: - Artículo original aceptado o publicado en revista categorizada o la carta de aceptación del artículo. - Certificado como de participación como ponente y soporte del trabajo presentado (memorias, programa de los eventos). - Certificado como de participación en calidad de póster y soporte del trabajo presentado (memorias, programa de los eventos). - Contrato de vinculación del joven investigador e informe de las actividades desarrolladas en el marco de proyecto | AC49: =+IFERROR(P49/L49,0%) -> 0 | AD49: =+IFERROR((Q49+R49)/L49,0%) -> 0 | AE49: =IFERROR(Q49/(Q49+R49),0%) -> 0 | AF49: =IFERROR(R49/(Q49+R49),0%) -> 0 | AG49: =+IFERROR((S49+T49)/L49,0%) -> 0 | AH49: =+IFERROR((U49+V49)/L49,0%) -> 0 | AI49: =+IFERROR((W49+X49)/L49,0%) -> 0 | AJ49: =+IFERROR((Y49+Z49)/L49,0%) -> 0
A50: 2019 | B50: Propuesta de Investigación Convocatoria | C50: No Avalada | D50: 852 | E50: CONVOCATORIA CONECTANDO CONOCIMIENTO 2019 | F50: MinCiencias | G50: Co-ejecutor | H50: 1- Universidad Nacional de Colombia UNAL (Ejecutor) | I50: N/A | J50: 24 | K50: UDFJC: - Grupo de Instrumentación Cientifica & Didáctica UNAL: - Grupo de Óptica e Información Cuántica | L50: =+SUM(P50:Z50) -> 557030051 | M50: 0 | N50: =+P50+Q50+S50+U50+W50+Y50 -> 327673411 | O50: =+R50+T50+V50+X50+Z50 -> 229356640 | P50: 303823669 | Q50: 11924871 | R50: 65500000 | S50: 11924871 | T50: 163856640 | U50: 0 | V50: 0 | W50: 0 | X50: 0 | Y50: 0 | Z50: 0 | AA50: - Evaluación, comprensión y síntesis de las propiedades ópticas, estructurales y composicionales de los biomateriales analizados. - Modelo de los biomateriales como cristales fotónicos 1D que permita evaluar y predecir respuestas ópticas pasivas como la iridiscencia. - Modelo de los biomateriales fotónicos con características de sistemas 1D como filtros ópticos angulares. - Comprensión de los procesos de transporte y localización de la luz en sistemas no ideales y que presenten desorden en sus parámetros estructurales. | AB50: - Un Artículo categoría A1 - Un Artículo categoría A2 - Un Artículo categoría B - Un Artículo categoría C - Dos ponencias en eventos científicos nacionales o internacionales - Dos presentaciones de trabajos en modalidad poster en eventos científicos nacionales o internacionales - Coorganización de un evento especializado en el área - Vinculación de dos jovenes investigadores - Vinculacion y formacion de cuatro estudiantes de pregrado - Vinculacion de un estudiante de maestria | AC50: =+IFERROR(P50/L50,0%) -> 0.54543497 | AD50: =+IFERROR((Q50+R50)/L50,0%) -> 0.13899586 | AE50: =IFERROR(Q50/(Q50+R50),0%) -> 0.15401861 | AF50: =IFERROR(R50/(Q50+R50),0%) -> 0.84598139 | AG50: =+IFERROR((S50+T50)/L50,0%) -> 0.31556917 | AH50: =+IFERROR((U50+V50)/L50,0%) -> 0 | AI50: =+IFERROR((W50+X50)/L50,0%) -> 0 | AJ50: =+IFERROR((Y50+Z50)/L50,0%) -> 0
A51: 2019 | B51: Propuesta de Investigación Convocatoria | C51: No Avalada | D51: 852 | E51: CONVOCATORIA CONECTANDO CONOCIMIENTO 2019 | F51: MinCiencias | G51: Co-ejecutor | H51: 1- Universidad Católica de Colombia UCC (ejecutor) 2- Fundación Universitaria Konrad Lorenz FUKL (co-ejecutor) 3- Lifesense SAS (co-ejecutor) | I51: PROGRAMA DE ENTRENAMIENTO COGNITIVO BASADO EN LA PRÁCTICA DEL AJEDREZ PARA ESTIMULAR LAS FUNCIONES EJECUTIVAS IMPLICADAS EN EL PENSAMIENTO LÓGICO MATEMÁTICO. DIRIGIDO A ESTUDIANTES DEL PRIMER CICLO DE EDUCACIÓN BÁSICA | J51: 24 | K51: UDFJC: - GIIRA UCC: - ENLACE - Grupo de Investigación en Aplicaciones de Estadística Multivariantes GAEM - Grupo de Investigación en Software Inteligente y Convergencia Tecnológica - GISIC FUKL: - PROMENTE-KONRAD | L51: =+SUM(P51:Z51) -> 1128785882 | M51: 0 | N51: =+P51+Q51+S51+U51+W51+Y51 -> 746152450 | O51: =+R51+T51+V51+X51+Z51 -> 382633432 | P51: 636587224 | Q51: 23849742 | R51: 161016280 | S51: 47699484 | T51: 191617152 | U51: 38016000 | V51: 0 | W51: 0 | X51: 30000000 | Y51: 0 | Z51: 0 | AA51: - Una batería de pruebas neuropsicológicas informatizadas. - Evidencia objetiva sobre los efectos de la práctica de ajedrez como una actividad curricular en el desarrollo de las funciones ejecutivas - Evidencia objetiva sobre los efectos de la práctica de ajedrez como una actividad curricular en el desarrollo del pensamiento lógico matemático. - Evidencia objetiva sobre las relaciones existentes entre las funciones ejecutivas y el pensamiento lógico matemático a fin de impactar el diseño curricular | AB51: - Seis Artículos categoría C - Dos Artículos categoría A2 - Un Artículo categoría A1 - Un libro de investigación categoría A1 - Un software - Seis Ponencias en Congreso Internacional - Formación de un estudiante de maestria (Tesis) - Vinculación de un estudiante de doctorado - Vinculación seis jóvenes investigadores - Formación de cuatro estudiantes de pregrado | AC51: =+IFERROR(P51/L51,0%) -> 0.56395746 | AD51: =+IFERROR((Q51+R51)/L51,0%) -> 0.16377422 | AE51: =IFERROR(Q51/(Q51+R51),0%) -> 0.12901095 | AF51: =IFERROR(R51/(Q51+R51),0%) -> 0.87098905 | AG51: =+IFERROR((S51+T51)/L51,0%) -> 0.21201243 | AH51: =+IFERROR((U51+V51)/L51,0%) -> 0.033678664 | AI51: =+IFERROR((W51+X51)/L51,0%) -> 0.026577228 | AJ51: =+IFERROR((Y51+Z51)/L51,0%) -> 0
A52: 2019 | B52: Propuesta de Investigación Convocatoria | C52: No Avalada | D52: 852 | E52: CONVOCATORIA CONECTANDO CONOCIMIENTO 2019 | F52: MinCiencias | G52: Co-ejecutor | H52: 1- Universidad de los Andes UniAndes (ejecutor) 2- Universidad Nacional de Colombia UNAL (co-ejecutor) | I52: NANOMATERIALES Y DISPOSITIVOS OPTOELECTRÓNICOS | J52: 36 | K52: UDFJC: - Grupo de Instrumentación Cientifica & Didáctica UniANDES: - Grupo de Fisica Teorica de la Materia Condensada - GRUPO DE FISICA DE ALTAS ENERGIAS DE LA UNIVERSIDAD DE LOS ANDES UNAL: - Grupo de Ciencia de Materiales y Superficies - GRUPO DE INVESTIGACIÓN EN CORROSIÓN, TRIBOLOGIA Y ENERGÍA - GRUPO DE INVESTIGACIÓN AFIS (ANÁLISIS DE FALLAS, INTEGRIDAD Y SUPERFICIES) | L52: =+SUM(P52:Z52) -> 2897791859 | M52: 0 | N52: =+P52+Q52+S52+U52+W52+Y52 -> 1378750876 | O52: =+R52+T52+V52+X52+Z52 -> 1519040983 | P52: 1307201650 | Q52: 11924871 | R52: 64000000 | S52: 35774613 | T52: 932402903 | U52: 23849742 | V52: 522638080 | W52: 0 | X52: 0 | Y52: 0 | Z52: 0 | AA52: - Creación de controladores de Software para análisis de parámetros de fabricación (espesor, diámetro, material) de nanodiscos plasmónicos. - Montaje para caracterización espectral de nanodiscos magnetoplasmónicos en función de la temperatura. - Modelo teóricos que incluyan los mecanismos físicos fundamentales que expliquen cualitativa y cuantitativamente las observaciones realizadas en el laboratorio y permitan hacer predicciones correspondientes. - Desarrollo de dispositivo para medición de propiedades ópticas de materiales heteroestructurados en función de la temperatura. | AB52: - Dos Artículos categoría A2 - Dos Artículos categoría A1 - Solicitud patente provisional sobre un dispositivo plasmónico diseñado y fabricado por medio de este programa de investigación. - Un software - Cinco Ponencias a nivel Nacional - Vinculación de tres estudiantes de maestria - Vinculación de un estudiante de doctorado - Vinculación seis jóvenes investigadores | AC52: =+IFERROR(P52/L52,0%) -> 0.45110267 | AD52: =+IFERROR((Q52+R52)/L52,0%) -> 0.02620094 | AE52: =IFERROR(Q52/(Q52+R52),0%) -> 0.15706146 | AF52: =IFERROR(R52/(Q52+R52),0%) -> 0.84293854 | AG52: =+IFERROR((S52+T52)/L52,0%) -> 0.33410872 | AH52: =+IFERROR((U52+V52)/L52,0%) -> 0.18858767 | AI52: =+IFERROR((W52+X52)/L52,0%) -> 0 | AJ52: =+IFERROR((Y52+Z52)/L52,0%) -> 0
A53: 2019 | B53: Propuesta de Investigación Convocatoria | C53: No Avalada | D53: 852 | E53: CONVOCATORIA CONECTANDO CONOCIMIENTO 2019 | F53: MinCiencias | G53: Ejecutor | H53: 1- Universidad de Nariño | I53: Configuración de categorías mediante procesos de innovación para la inclusión y el reconocimiento de la diversidad y diferencia cultural en la educación científica: Estudios de caso en los niveles educativos Básico y Universitario | J53: 36 | K53: UDFJC: - INTERCITEC (Interculturalidad, ciencia y tecnología) | L53: =+SUM(P53:Z53) -> 1520035721 | M53: 0 | N53: =+P53+Q53+S53+U53+W53+Y53 -> 1095641480 | O53: =+R53+T53+V53+X53+Z53 -> 424394241 | P53: 1024092254 | Q53: 47699484 | R53: 304036331 | S53: 23849742 | T53: 120357910 | U53: 0 | V53: 0 | W53: 0 | X53: 0 | Y53: 0 | Z53: 0 | AA53: - Las comunidades de practica interculturales vinculan a sabedores locales al desarrollo de la innovación educativa, este caso los pobladores que acogen a las instituciones educativas - Se plantea como estrategia de comunicación del conocimiento, la generación de contenidos vía radial, por medio de la emisora de las Universidades en Convenio - Se plantea como estrategia de comunicación del conocimiento, la generación de contenidos virtual, por medio de los diferentes portales de las Universidades en Convenio | AB53: - Cinco (5) libros categoría B - Cuatro (4) capítulos de libro categoría B - Dos (2) Artículos categoría A2 - Cuatro (4) artículos categoría B - Cuatro Informes técnicos realizados en el marco del proyecto - Vídeo donde se expone el desarrollo del proceso y la participación de las comunidades - Participación en cuatro (4) Eventos Científicos Internacionales - Participación ciudadana en el evento generado por parte de las Universidades en Convenio - Se realizará un evento con invitados académicos especializados del campo, participantes de las comunidades. Igualmente en dicho evento se realizará una validación de los resultados - Se participará en cuatro (4) Congresos Nacionales especializados en la Enseñanza de las Ciencias EDUCYT con ponencia aprobada. - Se participará en el IX Congreso Internacional de Formación Profesores de Ciencias - Seminario de Investigación a nivel doctoral sobre el desarrollo de la investigación - Vinculación de cuatro (4) estudiantes de doctorado - Vinculación de ocho (8) jóvenes investigadores mediante becas-pasantías a las actividades de CTeI - Tesis de doctorado en desarrollo: Innovaciones educativas, en el nivel de Básica Primaria - Tesis en desarrollo: Innovación educativa en Básica Primaria vinculante con practicas nutricionales. - Culminación de Tesis de Doctorado Claudia Patricia Orjuela - Seminario de Maestría orientado a la formación de profesores de Ciencias - Curso de formación inicial de profesores de ciencias, en la Universidad Distrital y la Universida de Nariño | AC53: =+IFERROR(P53/L53,0%) -> 0.67372907 | AD53: =+IFERROR((Q53+R53)/L53,0%) -> 0.2313997 | AE53: =IFERROR(Q53/(Q53+R53),0%) -> 0.13561168 | AF53: =IFERROR(R53/(Q53+R53),0%) -> 0.86438832 | AG53: =+IFERROR((S53+T53)/L53,0%) -> 0.094871226 | AH53: =+IFERROR((U53+V53)/L53,0%) -> 0 | AI53: =+IFERROR((W53+X53)/L53,0%) -> 0 | AJ53: =+IFERROR((Y53+Z53)/L53,0%) -> 0
A54: 2019 | B54: Propuesta de Investigación Convocatoria | C54: No Avalada | D54: 852 | E54: CONVOCATORIA CONECTANDO CONOCIMIENTO 2019 | F54: MinCiencias | G54: Co-ejecutor | H54: 1- Fundación Universidad Central FUC | I54: N/A | J54: 24 | K54: UDFJC: - Grupo de Instrumentación Cientifica & Didáctica UNAL: - BioMat: Ciencias Biológicas y Nuevos Materiales | L54: =+SUM(P54:Z54) -> 828807869 | M54: 0 | N54: =+P54+Q54+S54+U54+W54+Y54 -> 356405933 | O54: =+R54+T54+V54+X54+Z54 -> 472401936 | P54: 332556191 | Q54: 11924871 | R54: 226780000 | S54: 11924871 | T54: 245621936 | U54: 0 | V54: 0 | W54: 0 | X54: 0 | Y54: 0 | Z54: 0 | AA54: 1- Generación de nuevo conocimiento: * Dos publicación en revista indexada A1 A2 * Dos publicaciones en revistas de menor impacto 2- Apropiación social del conocimiento: * Dos ponencias en eventos nacionales * Dos ponencias en eventos internacionales * Dos ponencias en Encuentro Regional de Semilleros de Investigación 3- Formación de recurso humano: * Dos trabajo de grado de pregrado * Un trabajo de grado de maestría * Vinculaciones de dos jóvenes investigadores | AB54: - Un Artículos categoría A1 - Un Artículos categoría A2 - Dos Artículos categoría D - Dos ponencias en eventos internacionales - Cuatro trabajos de grado de estudiantes de pregrado - Vinculación dos jóvenes investigadores | AC54: =+IFERROR(P54/L54,0%) -> 0.40124642 | AD54: =+IFERROR((Q54+R54)/L54,0%) -> 0.2880099 | AE54: =IFERROR(Q54/(Q54+R54),0%) -> 0.049956547 | AF54: =IFERROR(R54/(Q54+R54),0%) -> 0.95004345 | AG54: =+IFERROR((S54+T54)/L54,0%) -> 0.31074368 | AH54: =+IFERROR((U54+V54)/L54,0%) -> 0 | AI54: =+IFERROR((W54+X54)/L54,0%) -> 0 | AJ54: =+IFERROR((Y54+Z54)/L54,0%) -> 0
A55: 2021 | B55: Propuesta de Investigación Convocatoria | C55: Contrato firmado | D55: N/A | E55: CONVOCATORIA TRAMPOLIN “T-AmSud” | F55: Embajada de Francia en Colombia | G55: Ejecutor | H55: 1- Centre National de la Recherche Scientifique - CNRS 2- Universidad Nacional de la Plata - UNP | I55: N/A | J55: 0.25 | K55: UDFJC: ITI: Innovación en Tecnologías de Información UNP: GEMIS: Grupo de Estudio de Metodologías para Ingeniería en Software y Sistemas de Información | L55: =+SUM(P55:Z55) -> 5675900 | M55: =+P55 -> 5675900 | N55: =+P55+Q55+S55+U55+W55+Y55 -> 5675900 | O55: =+R55+T55+V55+X55+Z55 -> 0 | P55: =1250*4540.72 -> 5675900 | Q55: 0 | R55: 0 | S55: 0 | T55: 0 | U55: 0 | V55: 0 | W55: 0 | X55: 0 | Y55: 0 | Z55: 0 | AA55: Diseñar y desarrollar un proyecto en el contexto de ciencia de datos que permita hacer predicción del comportamiento de la enfermedad, usando la información histórica oficial de la enfermedad ofrecida por la organización mundial de la salud. De esta manera, en este proyecto estudiaremos diferentes técnicas de aprendizaje computacional para usar aquellas que son idóneas para el desarrollo de predicción de información que incluye registros temporales diarios por cada país del mundo. Este proyecto se desarrollará en lenguaje Python con análisis y visualización de datos usando los componentes Pandas, Scikit-learn, Dash y Plotly. | AB55: Diseño de un proyecto de investigación entre los aliados - Preparación a la aplicación de este proyecto a la próxima convocatoria de los programas AMSUD en el 2022. | AC55: =+IFERROR(P55/L55,0%) -> 1 | AD55: =+IFERROR((Q55+R55)/L55,0%) -> 0 | AE55: =IFERROR(Q55/(Q55+R55),0%) -> 0 | AF55: =IFERROR(R55/(Q55+R55),0%) -> 0 | AG55: =+IFERROR((S55+T55)/L55,0%) -> 0 | AH55: =+IFERROR((U55+V55)/L55,0%) -> 0 | AI55: =+IFERROR((W55+X55)/L55,0%) -> 0 | AJ55: =+IFERROR((Y55+Z55)/L55,0%) -> 0
A56: 2019 | B56: Propuesta de Investigación Convocatoria | C56: Contrato firmado | D56: 848 | E56: CONVOCATORIA PROGRAMA DE ESTANCIAS POSTDOCTORALES EN ENTIDADES DEL SNCTeI 2019 | F56: MinCiencias | G56: Ejecutor | H56: N/A | I56: N/A | J56: 12 | K56: UDFJC: - Grupo de Investigación Uso y Conservación de la Diversidad Forestal | L56: =+SUM(P56:Z56) -> 147752000 | M56: 96000000 | N56: =+P56+Q56+S56+U56+W56+Y56 -> 128800000 | O56: =+R56+T56+V56+X56+Z56 -> 18952000 | P56: 96000000 | Q56: 7000000 | R56: 18952000 | S56: 25800000 | T56: 0 | U56: 0 | V56: 0 | W56: 0 | X56: 0 | Y56: 0 | Z56: 0 | AA56: - Línea base con la composición y abundancia de flora y macrofauna del suelo a lo largo del gradiente altitudinal - Modelo basado en datos que relacione las variables hidro-meteorológicas con parámetros de composición de especies y abundancias de flora y macrofauna del suelo, y permita la proyección de efectos de cambio climático en la flora y macrofauna. - Matriz de relación entre la macrofauna del suelo y su aproximación a los servicios ecosistémicos. - Una estrategia de comunicación y apropiación social del conocimiento derivado de esta investigación - Un plan de monitoreo hidro-meteorológico y ecológico a 10 años | AB56: - Un artículo científico sometido a revista indexada - Dirección de una tesis de maestría - Dirección de un trabajo de pregrado - Ponencia en un evento científico - Una charla magistral - Plan de monitoreo hidro-meteorológico y ecológico a 10 años - Dos eventos de comunicación y apropiación social en la zona de estudio - Organizar un simposio sobre ecología e hidrología de bosques andino | AC56: =+IFERROR(P56/L56,0%) -> 0.6497374 | AD56: =+IFERROR((Q56+R56)/L56,0%) -> 0.17564568 | AE56: =IFERROR(Q56/(Q56+R56),0%) -> 0.26972873 | AF56: =IFERROR(R56/(Q56+R56),0%) -> 0.73027127 | AG56: =+IFERROR((S56+T56)/L56,0%) -> 0.17461693 | AH56: =+IFERROR((U56+V56)/L56,0%) -> 0 | AI56: =+IFERROR((W56+X56)/L56,0%) -> 0 | AJ56: =+IFERROR((Y56+Z56)/L56,0%) -> 0
A57: 2019 | B57: Propuesta de Investigación Convocatoria | C57: No Avalada | D57: 863 | E57: CONVOCATORIA PARA EL APOYO DE PROYECTOS DE DESARROLLO Y VALIDACIÓN PRECOMERCIAL Y COMERCIAL DE PROTOTIPOS FUNCIONALES DE TECNOLOGÍAS DE ALTO RIESGO TECNOLÓGICO Y ALTO POTENCIAL COMERCIAL | F57: MinCiencias | G57: Co-ejecutor | H57: 1. Industrias TECSOL LTDA (Ejecutor). 2. Cooperación Verde SAS (Acompañante). | I57: N/A | J57: 20 | K57: UDFJC: - Grupo de investigacion en energias alternativas - GIEAUD - ARMOS - Arquitecturas Modernas para Sistemas de Alimentación TECSOL: - Centro de Desarrollo Industrial Tecsol | L57: =+SUM(P57:Z57) -> 935707049 | M57: 0 | N57: =+P57+Q57+S57+U57+W57+Y57 -> 797780894 | O57: =+R57+T57+V57+X57+Z57 -> 137926155 | P57: 523818458 | Q57: 73962436 | R57: 79900000 | S57: 0 | T57: 38026155 | U57: 200000000 | V57: 20000000 | W57: 0 | X57: 0 | Y57: 0 | Z57: 0 | AA57: - Contar con un producto de desarrollo tecnológico a nivel de prototipo para la cogeneración (electricidad –calor) con biomasa residual de podas. - Hacer pruebas de cogeneración en las instalaciones de la Cooperación Verde - Establecer el potencial de generación eléctrica con la biomasa residual de podas - Establecer el potencial de secar madera con calor residual de la generación eléctrica con biomasa residual de podas. - Establecer los beneficios ambientales y económicos del proceso desarrollado - Desarrollar un informe de panorama tecnológico sobre co-generación energía-calor, hornos y aprovechamiento de biomasa residual - Desarrollar un sistema de control automático de la operación del prototipo - Modelo de negocio o gestión para el aprovechamiento del prototipo | AB57: - Artículos de investigación: Dos (2) categoría B - Acuerdo de licencia para la explotación comercial del prototipo resultado de la investigación - Informe que describan los métodos y procedimientos empleados para la estimación y caracterización de los residuos forestales y su potencial energético. - Informe con la memoria de la ingeniería conceptual y básica de la planta de cogeneración. - Informe con la evaluación técnica, económica y ambiental de la tecnología de cogeneración en procesos de transformación primaria de la madera. - Informe de panorama tecnológico sobre sistemas de co-generación, hornos de secado. - Informe de modelo de negocio o gestión para el aprovechamiento del prototipo. - Planta de cogeneración de energía e integración con los procesos de secado y aserrío - Participación en dos (2) eventos nacionales o internacionales en los que se presenten los avances o resultados del proyecto de investigación - Vinculación un (1) jóven investigador | AC57: =+IFERROR(P57/L57,0%) -> 0.55981032 | AD57: =+IFERROR((Q57+R57)/L57,0%) -> 0.16443441 | AE57: =IFERROR(Q57/(Q57+R57),0%) -> 0.48070496 | AF57: =IFERROR(R57/(Q57+R57),0%) -> 0.51929504 | AG57: =+IFERROR((S57+T57)/L57,0%) -> 0.040638953 | AH57: =+IFERROR((U57+V57)/L57,0%) -> 0.23511632 | AI57: =+IFERROR((W57+X57)/L57,0%) -> 0 | AJ57: =+IFERROR((Y57+Z57)/L57,0%) -> 0
A58: 2019 | B58: Propuesta de Investigación Convocatoria | C58: No Avalada | D58: Convocatoria de Proyectos de Investigación en Paz y Pos-acuerdo SUE 2019 | E58: CONVOCATORIA DE PROYECTOS DE INVESTIGACIÓN EN PAZ Y POS-ACUERDO. SUE 2019 | F58: SUE Distrito Capital | G58: Co-ejecutor | H58: 1. Universidad Militar Nueva Granada - UMNG | I58: N/A | J58: 12 | K58: UDFJC: - GICALYT - Grupo de Investigación en Cadenas de Abastecimiento, logística y Trazabilidad UMNG: - Grupo de estudios contemporáneos en contabilidad, gestión y organizaciones - GECCGO | L58: =+SUM(P58:Z58) -> 49493245 | M58: 0 | N58: =+P58+Q58+S58+U58+W58+Y58 -> 39428000 | O58: =+R58+T58+V58+X58+Z58 -> 10065245 | P58: 39428000 | Q58: 0 | R58: 4125000 | S58: 0 | T58: 5940245 | U58: 0 | V58: 0 | W58: 0 | X58: 0 | Y58: 0 | Z58: 0 | AA58: Los impactos esperados se listan a continuación: i) Transferencia de conocimiento a asociaciones y organizaciones públicas y privadas del sector agroindustrial. ii) Generación de Nuevo Conocimiento en revista de alto impacto que contribuyen a los grupos de investigación de la alianza del SUE. iii) Formación de estudiante de posgrado a nivel de Maestría en investigación y modelado. iv) Difusión de conocimiento en conferencias especializadas en el tema. v) Diseño de alternativas de política para instituciones públicas (Ministerio de Agricultura y Desarrollo entre otros). vi) Diseño de estrategias basada en el modelado y simulación para instituciones privadas. | AB58: - Dos (2) artículos sometidos en revista científica Nacional y/o Internacional (Q3) - Un avance de tesis de maestría relacionadas con el tema de investigación - Una participación en evento internacional y/o nacional para la difusión de resultados - Realizar un (1) evento académico para divulgar los avances alcanzados en el proyecto y/o los resultados del mismo y así como para promover la posible conformación de redes de investigación y alianzas institucionales - Avance de una (1) tesis de pregrado relacionadas con el tema de investigación | AC58: =+IFERROR(P58/L58,0%) -> 0.79663396 | AD58: =+IFERROR((Q58+R58)/L58,0%) -> 0.083344707 | AE58: =IFERROR(Q58/(Q58+R58),0%) -> 0 | AF58: =IFERROR(R58/(Q58+R58),0%) -> 1 | AG58: =+IFERROR((S58+T58)/L58,0%) -> 0.12002133 | AH58: =+IFERROR((U58+V58)/L58,0%) -> 0 | AI58: =+IFERROR((W58+X58)/L58,0%) -> 0 | AJ58: =+IFERROR((Y58+Z58)/L58,0%) -> 0
A59: 2021 | B59: Propuesta de Investigación Convocatoria | C59: Contrato firmado | D59: 897 | E59: CONVOCATORIA PARA LA FINANCIACIÓN DE PROYECTOS DE CTeI EN SALUD QUE PROMUEVAN LA MEDICINA PERSONALIZADA Y LA INVESTIGACIÓN TRASLACIONAL - Modalidad 1: Proyectos de CTeI basados en Investigación traslacional. | F59: MinCiencias | G59: Co-ejecutor | H59: 1- Universidad Pontificia Javeriana - UPJ (Ejecutor) 2- Universidad Nacional de Colombia - UNAL (Co-ejecutor) 3- Hospital Universitario San Ignacio - HUSI (Co-ejecutor) | I59: N/A | J59: 36 | K59: UDFJC: - Grupo de Investigación en Ingeniería Ambiental - GIIAUD UPJ: - INSTITUTO DE GENETICA HUMANA - FACULTAD DE MEDICINA - PONTIF UNAL: - Grupo de Investigación en Bioinformática y Biología de Sistemas HUSI: - Enfermedades Crónicas del Adulto | L59: =+SUM(P59:Z59) -> 1345071944 | M59: 0 | N59: =+P59+Q59+S59+U59+W59+Y59 -> 929956223 | O59: =+R59+T59+V59+X59+Z59 -> 415115721 | P59: 925356223 | Q59: 0 | R59: 57564288 | S59: 4600000 | T59: 287515785 | U59: 0 | V59: 30950880 | W59: 0 | X59: 39084768 | Y59: 0 | Z59: 0 | AA59: -Teniendo como referencia los artículos publicados en relación con esta temática, se esperan encontrar diferencias significativas en los niveles de enriquecimiento de H3K9Ac entre sujetos sanos de las localidades muestreadas; y pacientes con diagnóstico de asma grave. Estas diferencias esperan ser cuantificadas por la metodología de ChIPseq y se espera construir asociaciones entre los patrones epigenéticos detectados en habitantes de las localidades más contaminadas con los patrones exhibidos por pacientes con diagnóstico de asma grave -Se identificarán las regiones promotoras, enhancer, cuerpo del gen con mayor enriquecimiento de H 3K9Ac, en los grupos de investigación seleccionados. Teniendo en cuenta los reportes de la literatura, esperamos reportar que los genes que muestran patrones aberrantes de modificación de histonas están involucrados en estrés oxidativo, inflamación y modulación del sistema inmune. Específicamente esperamos encontrar activación aberrante de genes relacionados con la diferenciación de linfocitos Th2, los cuales han sido descritos en pacientes con asma y alergias. -Se esperan obtener datos precisos de las concentraciones de PM 2.5 en las localidades seleccionadas. Se obtendrá también un análisis espacio-temporal de la variación de las concentraciones de PM2.5. Se obtendrán resultados sobre la percepción ciudadana en relación con la calidad del aire de las áreas en estudio. Por último, se evaluará preliminarmente la posible asociación entre las concentraciones de PM2.5 y las tasas de morbilidad asociadas. -Con los datos obtenidos anteriormente se espera encontrar incrementos en los niveles de H 3K9Ac en sujetos de investigación que habitan localidades con mayor índice de material particulado PM2.5. | AB59: - Un Artículo de investigación categoría A1 - Dos Artículos de investigación categoría B - Participación en dos congresos científicos nacionales y uno internacional - Realización de Seminario de Impacto de la calidad de aire en la salud humana - Elaboración de 1 Cartilla o folleto como medio de divulgación referente a la importancia de la calidad de aire en la salud humana. - Dos estudiantes especialización en medicina interna o neumología - Formación de un estudiante de Doctorado en Ciencias, Facultad de Ciencias, Pontificia Universidad Javeriana - Estudiante de maestría en Bioestadística y maestría en Desarrollo sustentable y ambiental - POLICY BRIEF. Documento técnico que sintetiza la evidencia sobre un tema particular de política., presenta los hallazgos de una investigación o proyecto a los actores políticos o público no especial - Contenidos multimedia y virtuales. Generación de videos de máximo 10 minutos donde se muestre el estado de avance del proyecto y el impacto esperado. | AC59: =+IFERROR(P59/L59,0%) -> 0.68796039 | AD59: =+IFERROR((Q59+R59)/L59,0%) -> 0.042796438 | AE59: =IFERROR(Q59/(Q59+R59),0%) -> 0 | AF59: =IFERROR(R59/(Q59+R59),0%) -> 1 | AG59: =+IFERROR((S59+T59)/L59,0%) -> 0.21717484 | AH59: =+IFERROR((U59+V59)/L59,0%) -> 0.023010576 | AI59: =+IFERROR((W59+X59)/L59,0%) -> 0.029057753 | AJ59: =+IFERROR((Y59+Z59)/L59,0%) -> 0
A60: 2019 | B60: Propuesta de Investigación Convocatoria | C60: No Avalada | D60: 6 | E60: 006-2019 CONVOCATORIA DE PROYECTOS ELEGIBLES DE INVESTIGACIÓN Y DESARROLLO - SGR - FONDO DE CTI | F60: MinCiencias | G60: Ejecutor | H60: 1- CORPORACIÓN UNIVERSITARIA IBEROAMERICANA - CPI 2- UNIVERSIDAD DE ANTOFAGASTA - UATFG 3- ZEMILLAH | I60: N/A | J60: 30 | K60: GIIPLyM | L60: =+SUM(P60:Z60) -> 2052784848 | M60: 0 | N60: =+P60+Q60+S60+U60+W60+Y60 -> 1420935298 | O60: =+R60+T60+V60+X60+Z60 -> 631849550 | P60: 1420935298 | Q60: 0 | R60: 359074286 | S60: 0 | T60: 80330440 | U60: 0 | V60: 139036009 | W60: 0 | X60: 53408815 | Y60: 0 | Z60: 0 | AA60: Formulación de primera versión tipo Artículo que define categorías: experiencias estéticas en lenguaje y comunicación y en artes y criterios para su incorporación en el diseño de AAAA. (Generación de Nuevo conocimiento) - Primera versión de ambientes de aprendizaje para el desarrollo de experiencias estéticas en lenguaje y comunicación y en artes, en la formación de profesores. - Juegos y materiales diseñados para el desarrollo de experiencia estética en lenguaje y comunicación y en artes. (Formación de Recurso Humano) - (Apropiación Social del Conocimiento). - Documentos teóricos resultado grupos focales con propuesta de AAAA para las diversas poblaciones. (Generación de Nuevo Conocimiento Conocimiento) - Repositorio AAAA diseñados y validados tanto en formación de profesores como contextos educativos de distintos niveles y áreas con informe de evolución y de validación. (Apropiación Social del conocimiento). - Artículos postulados a revistas indexadas (Generación de Nuevo Conocimiento) - Cartillas para profesores (Apropiación Social del conocimiento - | AB60: - Cuatro (4) obras y/o productos de investigación, creación en artes, arquitectura y diseño - Doce (12) Libros y/o capítulos de libros resultados de investigación - Tres (3) Artículos publicados en revistas indexadas nacionales e internacionales - Diseño de primeros talleres para los grupos focales incorporando las cuatro categorías. - Preparación y participación en Congresos (mínimo dos en lenguaje y comunicación, dos en artes y uno en tecnología y uno en ingeniería - Dos cartillas para profesores uno en lenguaje y uno en artes | AC60: =+IFERROR(P60/L60,0%) -> 0.69219884 | AD60: =+IFERROR((Q60+R60)/L60,0%) -> 0.17492057 | AE60: =IFERROR(Q60/(Q60+R60),0%) -> 0 | AF60: =IFERROR(R60/(Q60+R60),0%) -> 1 | AG60: =+IFERROR((S60+T60)/L60,0%) -> 0.039132421 | AH60: =+IFERROR((U60+V60)/L60,0%) -> 0.067730434 | AI60: =+IFERROR((W60+X60)/L60,0%) -> 0.026017736 | AJ60: =+IFERROR((Y60+Z60)/L60,0%) -> 0
A61: 2019 | B61: Propuesta de Investigación Alianza Convenio | C61: No Avalada | D61: N/A | E61: N/A | F61: Universidad de América | G61: Aliado | H61: Universidad de América | I61: N/A | J61: 12 | K61: N/A | L61: =+SUM(P61:Z61) -> 178895903 | M61: 0 | N61: =+P61+Q61+S61+U61+W61+Y61 -> 50872223 | O61: =+R61+T61+V61+X61+Z61 -> 128023680 | P61: 0 | Q61: 45872223 | R61: 60125000 | S61: 5000000 | T61: 67898680 | U61: 0 | V61: 0 | W61: 0 | X61: 0 | Y61: 0 | Z61: 0 | AA61: * Formación de dos (2) estudiantes de pregrado en investigación formativa de la Universidad America. * Dos (2) estudiantes de la Tecnología en Saneamiento Ambiental y/o Ingeniería Sanitaria de la Universidad Distrital. * Formación de un (1) estudiante de maestría. * Asistencia a tres (3) ponencias en Congresos y/o Seminarios especializados | AB61: * Tres (3) artículos científicos resultados de la investigación en revistas indexadas por Colciencias * Un (1) Libro de resultado de investigación | AC61: =+IFERROR(P61/L61,0%) -> 0 | AD61: =+IFERROR((Q61+R61)/L61,0%) -> 0.59250783 | AE61: =IFERROR(Q61/(Q61+R61),0%) -> 0.43276816 | AF61: =IFERROR(R61/(Q61+R61),0%) -> 0.56723184 | AG61: =+IFERROR((S61+T61)/L61,0%) -> 0.40749217 | AH61: =+IFERROR((U61+V61)/L61,0%) -> 0 | AI61: =+IFERROR((W61+X61)/L61,0%) -> 0 | AJ61: =+IFERROR((Y61+Z61)/L61,0%) -> 0
A62: 2020 | B62: Propuesta de Investigación Convocatoria | C62: No Avalada | D62: Solución COVID-19 | E62: INVITACIÓN A PRESENTAR PROYECTOS QUE CONTRIBUYAN A LA SOLUCIÓN DE PROBLEMÁTICAS ACTUALES DE SALUD RELACIONADAS CON LA PANDEMIA DE COVID-19 | F62: MinCiencias | G62: Ejecutor | H62: N/A | I62: N/A | J62: 8 | K62: - GIIRA - AQUAFORMAT | L62: =+SUM(P62:Z62) -> 1452705021 | M62: 0 | N62: =+P62+Q62+S62+U62+W62+Y62 -> 932705021 | O62: =+R62+T62+V62+X62+Z62 -> 520000000 | P62: 932705021 | Q62: 0 | R62: 520000000 | S62: 0 | T62: 0 | U62: 0 | V62: 0 | W62: 0 | X62: 0 | Y62: 0 | Z62: 0 | AA62: - Formación de cinco (5) estudiantes de pregrado en investigación formativa (Tecnología en Saneamiento Ambiental, Ingeniería Sanitaria, Ingeniería de Sistemas e Ingeniería Electrónica de la Universidad Distrital Francisco José de Caldas) - Dos (2) ponencias en Congresos y/o Seminarios especializados, uno nacional y otro internacional. - Socialización de resultados ante el Gobierno Nacional, Autoridad Sanitaria y Autoridad Ambiental Jurisdicción. | AB62: - Dos (2) artículos científicos resultados de la investigación en revistas indexadas por Colciencias - Un (1) libro de los resultados de la investigación que reúna cada una de las líneas del proyecto. - Un (1) software especializado. | AC62: =+IFERROR(P62/L62,0%) -> 0.64204708 | AD62: =+IFERROR((Q62+R62)/L62,0%) -> 0.35795292 | AE62: =IFERROR(Q62/(Q62+R62),0%) -> 0 | AF62: =IFERROR(R62/(Q62+R62),0%) -> 1 | AG62: =+IFERROR((S62+T62)/L62,0%) -> 0 | AH62: =+IFERROR((U62+V62)/L62,0%) -> 0 | AI62: =+IFERROR((W62+X62)/L62,0%) -> 0 | AJ62: =+IFERROR((Y62+Z62)/L62,0%) -> 0
A63: 2020 | B63: Propuesta de Investigación Convocatoria | C63: No Avalada | D63: Solución COVID-19 | E63: INVITACIÓN A PRESENTAR PROYECTOS QUE CONTRIBUYAN A LA SOLUCIÓN DE PROBLEMÁTICAS ACTUALES DE SALUD RELACIONADAS CON LA PANDEMIA DE COVID-19 | F63: MinCiencias | G63: Ejecutor | H63: N/A | I63: N/A | J63: 8 | K63: - LIFAE | L63: =+SUM(P63:Z63) -> 833158200 | M63: 0 | N63: =+P63+Q63+S63+U63+W63+Y63 -> 538108200 | O63: =+R63+T63+V63+X63+Z63 -> 295050000 | P63: 538108200 | Q63: 0 | R63: 295050000 | S63: 0 | T63: 0 | U63: 0 | V63: 0 | W63: 0 | X63: 0 | Y63: 0 | Z63: 0 | AA63: El trabajo desarrollado por el grupo de investigación se ha focalizado en tres (03) aspectos: Pronóstico de información disponible en las bases de datos, pronóstico de la segmentación de las imágenes de rayos x y automatización de la clasificación asistencial a partir de soluciones disponibles en la nube. En la actualidad, se dispone de una gran cantidad de información que hace posible el desarrollo de modelos de pronóstico bastante precisos. Sin embargo, el reto consiste en definir flujos de trabajo para el análisis de datos que permitan convertir toda la información de baja calidad en información procesable. En el documento se define un flujo de trabajo que tiene en cuenta cuatro pasos: 1. Importar datos de diferentes fuentes, tales como, archivos, bases de datos y hojas de datos. 2. Limpiar la información por medio de la eliminación de valores atípicos y ruido, y combinar los conjuntos de datos. 3. Desarrollar un modelo predictivo preciso con base en la combinación de datos utilizando técnicas adecuadas de aprendizaje profundo. 4. Desplegar el modelo como una aplicación en un ambiente de producción. Para el desarrollo de la investigación se está utilizando las siguientes herramientas: Matlab [8], Simulink [9], Opal-RT [10], DSPACE [11] y Amazon AWS [12]. Matlab y Simulink se utilizan para modelar el sistema de clasificación asistencial y expandirlo a la segmentación de imágenes de rayos x. La definición del modelo incluye el flujo de trabajo que permita el análisis de datos para el pronóstico del nexo epidemiológico y de los antecedentes clínicos. Adicionalmente, se proyecta definir una aplicación que permita seleccionar cualquier entidad que reporte información dentro del país para desplegar la clasificación asistencial actual y pronosticar una futura. La plataforma de simulación de elementos eléctricos complejos (Opal-RT ó DSPACE) se utiliza para emular en tiempo real el desempeño del modelo en términos de generación de datos y seguimiento al modelo. La incorporación de los datos en la caracterización del comportamiento del nexo epidemiológico y de los antecedentes clínicos permite obtener un pronóstico más preciso, de tal manera, que el sistema de clasificación asistencial pueda mostrar escenarios para tomar decisiones más acertadas con respecto a situaciones particulares. Finalmente, se utiliza el servicio de almacenamiento simple de Amazon (Amazon S3 ) para garantizar el acceso y registro de los archivos que se utilizan por los modelos y los algoritmos de pronóstico bajo condiciones adecuadas de escalabilidad, disponibilidad de datos, seguridad y rendimiento. | AB63: La producción de esta solución permitirá tener disponible la información centralizada de los pacientes de manera permanente y la presentación amigable de escenarios futuros adecuados para la toma de decisiones de corto y mediano plazo. | AC63: =+IFERROR(P63/L63,0%) -> 0.64586558 | AD63: =+IFERROR((Q63+R63)/L63,0%) -> 0.35413442 | AE63: =IFERROR(Q63/(Q63+R63),0%) -> 0 | AF63: =IFERROR(R63/(Q63+R63),0%) -> 1 | AG63: =+IFERROR((S63+T63)/L63,0%) -> 0 | AH63: =+IFERROR((U63+V63)/L63,0%) -> 0 | AI63: =+IFERROR((W63+X63)/L63,0%) -> 0 | AJ63: =+IFERROR((Y63+Z63)/L63,0%) -> 0
A64: 2020 | B64: Propuesta de Investigación Convocatoria | C64: No Avalada | D64: Solución COVID-19 | E64: INVITACIÓN A PRESENTAR PROYECTOS QUE CONTRIBUYAN A LA SOLUCIÓN DE PROBLEMÁTICAS ACTUALES DE SALUD RELACIONADAS CON LA PANDEMIA DE COVID-19 | F64: MinCiencias | G64: Ejecutor | H64: - PONTIFICIA UNIVERSIDAD JAVERIANA - COLOMBIANA DE TRASPLANTES SAS - HOSPITAL MILITAR CENTRAL - SOCIEDAD COLOMBIANA DE INGENIERIA FISICA - UNIVERSIDAD EL BOSQUE | I64: N/A | J64: 6 | K64: UDFJC: Grupo de Instrumentación Cientifica & Didáctica PUJ: Enfermedades Infecciosas CDTSAS: Grupo de investigación Colombiana de Trasplantes HMC: Grupo de Inmunología Clínica Aplicada SCDIF: INGENIERIA FISICA UDB: Grupo de Inmunología celular y molecular Universidad El Bosque | L64: =+SUM(P64:Z64) -> 1590798299 | M64: 0 | N64: =+P64+Q64+S64+U64+W64+Y64 -> 824297436 | O64: =+R64+T64+V64+X64+Z64 -> 766500863 | P64: 824297436 | Q64: 0 | R64: 739600000 | S64: 0 | T64: 2047391 | U64: 0 | V64: 5399040 | W64: 0 | X64: 5454432 | Y64: 0 | Z64: 14000000 | AA64: 0 | AB64: Actualmente se han identificado cuatro genes que pertenecen a la familia del coronavirus, conocidos como alfa, beta, gamma y delta. Dentro de este grupo de genes, el virus corona alfa y beta, puede ocasionar patologías, tanto en seres humanos como en animales. Mientras que coronavirus del grupo gamma y delta, sólo generan procesos infecciosos en animales. El virus coronavirus (COVID-19) pertenece a la familia beta, y es el patógeno responsable de los mecanismos infecciosos que se desencadenaron en seres humanos y que generaron una neumonía masiva en Wuhan, Hubei (China) en diciembre del 2019. Aquí radica la importancia de diagnosticar esta infección de manera rápida y ágil por medio de técnicas moleculares como RT-PCR. Esto también es de relevancia en la actualidad, debido a que no existen vacunas o antivirales que se encuentren aprobados para procedimientos clínicos. La Organización Mundial de la Salud (OMS) ha puesto a disposición protocolos de laboratorio para la detección de este virus. En estos documentos, este organismo menciona la importancia de detectar los genes RdyRp y E que se han utilizado masivamente en países como Corea, desde febrero de 2020 y los genes N, que se han utilizado en los Centros para el Control y Prevención de Enfermedades (CDC) de los Estados Unidos; dándole una mayor fiabilidad al diagnóstico. En este procedimiento sólo se añade ARN de plantilla para que pueda ser utilizado por cualquier investigador que decida realizar el procedimiento. Esto es posible a través de la utilización de un kit de RT-PCR en tiempo real, que detecte los genes anteriormente mencionados e identifique a los pacientes positivos para la enfermedad y descarte a los que no han sido infectados con el COVID-19. A partir de este punto, se procede a la correlación de los resultados a través de la técnica de RAMAN. Bibliografía: Directrices de Laboratorio para la Detección y Diagnóstico de la Infección con el Nuevo Coronavirus 2019 (2019-nCoV) - 1 Febrero de 2020 - Organización mundial de la salud. | AC64: =+IFERROR(P64/L64,0%) -> 0.5181659 | AD64: =+IFERROR((Q64+R64)/L64,0%) -> 0.46492381 | AE64: =IFERROR(Q64/(Q64+R64),0%) -> 0 | AF64: =IFERROR(R64/(Q64+R64),0%) -> 1 | AG64: =+IFERROR((S64+T64)/L64,0%) -> 0.0012870211 | AH64: =+IFERROR((U64+V64)/L64,0%) -> 0.0033939186 | AI64: =+IFERROR((W64+X64)/L64,0%) -> 0.0034287389 | AJ64: =+IFERROR((Y64+Z64)/L64,0%) -> 0.0088006129
A65: 2020 | B65: Propuesta de Investigación Convocatoria | C65: No Avalada | D65: Solución COVID-19 | E65: INVITACIÓN A PRESENTAR PROYECTOS QUE CONTRIBUYAN A LA SOLUCIÓN DE PROBLEMÁTICAS ACTUALES DE SALUD RELACIONADAS CON LA PANDEMIA DE COVID-19 | F65: MinCiencias | G65: Ejecutor | H65: N/A | I65: N/A | J65: 6 | K65: LIDER | L65: =+SUM(P65:Z65) -> 712600000 | M65: 0 | N65: =+P65+Q65+S65+U65+W65+Y65 -> 553400000 | O65: =+R65+T65+V65+X65+Z65 -> 159200000 | P65: 553400000 | Q65: 0 | R65: 159200000 | S65: 0 | T65: 0 | U65: 0 | V65: 0 | W65: 0 | X65: 0 | Y65: 0 | Z65: 0 | AA65: 0 | AB65: Contar con un sistema de geolocalización en tiempo real permite conocer las ubicaciones de los pacientes afectados por el Covid-19, esto con el fin de implementar planes de contingencia que ayuden a reducir dichos focos de propagación. Se sabe que actualmente una de las ciudades en Colombia más afectadas es la capital Bogotá, inicialmente el virus ingresó en días anteriores al 6 de Marzo cuando se diagnosticó el paciente cero en el país, asumiendo que este virus se importó por vía aérea, este sistema logrará caracterizar dichos escenarios de propagación permitiendo tomar decisiones radicales que ayuden a minimizar la razón del número de contagiados en función del tiempo, esta es una de las grandes preocupaciones en vista de que la red hospitalaria [11] no cuenta con UCIS suficientes para la demanda que se avecina. Cuando el sistema se encuentre en funcionamiento se retroalimentan las bases de datos en tiempo real que permitan conocer estadísticas actualizadas para analizar si los protocolos implementados por el Ministerio de Salud han generado resultados. Actualmente el número de contagios en Colombia supera los 490 individuos y se estima por medio de una regresión con losdatos actuales que para finales de abril esta cifra se encuentre muy por encima de las 5.000 personas afectadas y que haya en total entre 80 y 100 muertes. El diseño de un algoritmo estocástico y/o metaheurístico retroalimentado con machine learning permitirá generar un modelo de estimación que pronostique un número probable de contagios por día, según la ubicación y factores estudiados previamente, esto con el fin de mitigar dichos focos de propagación por medio de medidas radicales que no impacten colateralmente la economía del país. Con el total de los datos obtenidos durante el proceso, se convierte en un insumo de toma de decisión para el gobierno. | AC65: =+IFERROR(P65/L65,0%) -> 0.77659276 | AD65: =+IFERROR((Q65+R65)/L65,0%) -> 0.22340724 | AE65: =IFERROR(Q65/(Q65+R65),0%) -> 0 | AF65: =IFERROR(R65/(Q65+R65),0%) -> 1 | AG65: =+IFERROR((S65+T65)/L65,0%) -> 0 | AH65: =+IFERROR((U65+V65)/L65,0%) -> 0 | AI65: =+IFERROR((W65+X65)/L65,0%) -> 0 | AJ65: =+IFERROR((Y65+Z65)/L65,0%) -> 0
A66: 2020 | B66: Propuesta de Investigación Convocatoria | C66: No Avalada | D66: Solución COVID-19 | E66: INVITACIÓN A PRESENTAR PROYECTOS QUE CONTRIBUYAN A LA SOLUCIÓN DE PROBLEMÁTICAS ACTUALES DE SALUD RELACIONADAS CON LA PANDEMIA DE COVID-19 | F66: MinCiencias | G66: Ejecutor | H66: - CORPORACIÓN TECNOLÓGICA INDUSTRIAL COLOMBIANA - FUNDACIÓN UNIVERSITARIA PANAMERICANA - UNIVERSIDAD SANTO TOMAS | I66: N/A | J66: 8 | K66: - INNOVATEC - GRUPO DE INVESTIGACIÓN EN INGENIERÍAS - GIIS | L66: =+SUM(P66:Z66) -> 622920055 | M66: 0 | N66: =+P66+Q66+S66+U66+W66+Y66 -> 561614647 | O66: =+R66+T66+V66+X66+Z66 -> 61305408 | P66: 561614647 | Q66: 0 | R66: 16200000 | S66: 0 | T66: 28800000 | U66: 0 | V66: 9000000 | W66: 0 | X66: 7305408 | Y66: 0 | Z66: 0 | AA66: 0 | AB66: La relación simbiótica entre las redes sociales y la información, no ha sido ajena al manejo que ha tenido esta en relación con el surgimiento y desarrollo de esta pandemia denominada COVID 19. En la historia de la humanidad ninguna pandemia tuvo tanta cobertura, tanto flujo de datos, tantos elementos audiovisuales y textuales que permiten a cada individuo realizar sus propios análisis y por qué no sacar conclusiones. Solo en los siglos XX y XXI varias epidemias han asolado a la humanidad desde la gripe española, el ébola, el cólera y el SIDA hasta las más recientes como lo son la gripe A (H1N1) y el COVID 19. Pero sin duda es esta ultima la que mayor difusión ha tenido, gracias obviamente a las redes sociales. Es vital el flujo de la información, hoy tenemos acceso directo a los datos de la epidemia en tiempo real, conocemos las políticas de los diferentes Estados, observamos el sentir de los diferentes países, culturas e individuos, tratamos de entender los pronósticos de la ciencia y de las paraciencias, nos reímos con memes, nos preocupamos por audios y videos apocalípticos, podemos escuchar de primera mano la voz de los afectados, de los creyentes y contradictores. Al mismo tiempo las redes han permitido continuar con cierta normalidad tenemos conciertos virtuales, noticias minuto a minuto, eventos culturales y hasta la vida académica se está desarrollando por estas redes. Son muchas las ventajas que hoy se tienen para el desarrollo y conocimiento de este tipo de situaciones, hoy la información esta tan solo a un clip, lo que hace más importante el manejo responsable de la información y las redes y hace a su vez necesarias profundas investigaciones que hagan de esta relación un factor de desarrollo y mejoramiento de las condiciones de existencia de la humanidad. | AC66: =+IFERROR(P66/L66,0%) -> 0.90158383 | AD66: =+IFERROR((Q66+R66)/L66,0%) -> 0.026006548 | AE66: =IFERROR(Q66/(Q66+R66),0%) -> 0 | AF66: =IFERROR(R66/(Q66+R66),0%) -> 1 | AG66: =+IFERROR((S66+T66)/L66,0%) -> 0.046233862 | AH66: =+IFERROR((U66+V66)/L66,0%) -> 0.014448082 | AI66: =+IFERROR((W66+X66)/L66,0%) -> 0.011727681 | AJ66: =+IFERROR((Y66+Z66)/L66,0%) -> 0
A67: 2020 | B67: Propuesta de Investigación Convocatoria | C67: No Avalada | D67: Solución COVID-19 | E67: INVITACIÓN A PRESENTAR PROYECTOS QUE CONTRIBUYAN A LA SOLUCIÓN DE PROBLEMÁTICAS ACTUALES DE SALUD RELACIONADAS CON LA PANDEMIA DE COVID-19 | F67: MinCiencias | G67: Co-ejecutor | H67: - FUNDACIÓN UNIVERSITARIA LOS LIBERTADORES - UNIVERSIDAD TECNOLOGICA DEL CHOCO DIEGO LUIS CORDOBA - UNIVERSIDAD TECNOLOGICA DEL CHOCO DIEGO LUIS CORDOBA | I67: N/A | J67: 9 | K67: - Representaciones y Conceptos Científicos. IREC. - Electronica, Telecomunicaciones e Informatica con Oportunidad y Servicio "ETICOS" - Investigaciones Pedagógicas en el área de Matemáticas "INPEMA" | L67: =+SUM(P67:Z67) -> 720007707 | M67: 0 | N67: =+P67+Q67+S67+U67+W67+Y67 -> 539355252 | O67: =+R67+T67+V67+X67+Z67 -> 180652455 | P67: 539355252 | Q67: 0 | R67: 43680000 | S67: 0 | T67: 42000000 | U67: 0 | V67: 94972455 | W67: 0 | X67: 0 | Y67: 0 | Z67: 0 | AA67: 0 | AB67: 0 | AC67: =+IFERROR(P67/L67,0%) -> 0.7490965 | AD67: =+IFERROR((Q67+R67)/L67,0%) -> 0.060666017 | AE67: =IFERROR(Q67/(Q67+R67),0%) -> 0 | AF67: =IFERROR(R67/(Q67+R67),0%) -> 1 | AG67: =+IFERROR((S67+T67)/L67,0%) -> 0.058332709 | AH67: =+IFERROR((U67+V67)/L67,0%) -> 0.13190478 | AI67: =+IFERROR((W67+X67)/L67,0%) -> 0 | AJ67: =+IFERROR((Y67+Z67)/L67,0%) -> 0
A68: 2020 | B68: Propuesta de Investigación Convocatoria | C68: No Avalada | D68: Solución COVID-19 | E68: INVITACIÓN A PRESENTAR PROYECTOS QUE CONTRIBUYAN A LA SOLUCIÓN DE PROBLEMÁTICAS ACTUALES DE SALUD RELACIONADAS CON LA PANDEMIA DE COVID-19 | F68: MinCiencias | G68: Ejecutor | H68: N/A | I68: N/A | J68: 6 | K68: Comercio Electronico en Colombia - GICOECOL | L68: =+SUM(P68:Z68) -> 2032670000 | M68: 0 | N68: =+P68+Q68+S68+U68+W68+Y68 -> 1952670000 | O68: =+R68+T68+V68+X68+Z68 -> 80000000 | P68: 1952670000 | Q68: 0 | R68: 80000000 | S68: 0 | T68: 0 | U68: 0 | V68: 0 | W68: 0 | X68: 0 | Y68: 0 | Z68: 0 | AA68: 0 | AB68: Análisis y detección de posibles infectados en tiempo real. Seguimiento oportuno a personas con alto riesgo de contagio de COVID-19. Alertamientos oportunos para mitigación de contagio de COVID-19 | AC68: =+IFERROR(P68/L68,0%) -> 0.9606429 | AD68: =+IFERROR((Q68+R68)/L68,0%) -> 0.039357102 | AE68: =IFERROR(Q68/(Q68+R68),0%) -> 0 | AF68: =IFERROR(R68/(Q68+R68),0%) -> 1 | AG68: =+IFERROR((S68+T68)/L68,0%) -> 0 | AH68: =+IFERROR((U68+V68)/L68,0%) -> 0 | AI68: =+IFERROR((W68+X68)/L68,0%) -> 0 | AJ68: =+IFERROR((Y68+Z68)/L68,0%) -> 0
A69: 2020 | B69: Propuesta de Investigación Convocatoria | C69: No Avalada | D69: Solución COVID-19 | E69: INVITACIÓN A PRESENTAR PROYECTOS QUE CONTRIBUYAN A LA SOLUCIÓN DE PROBLEMÁTICAS ACTUALES DE SALUD RELACIONADAS CON LA PANDEMIA DE COVID-19 | F69: MinCiencias | G69: Ejecutor | H69: N/A | I69: N/A | J69: 6 | K69: GIIRA | L69: =+SUM(P69:Z69) -> 565630929 | M69: 0 | N69: =+P69+Q69+S69+U69+W69+Y69 -> 533893587 | O69: =+R69+T69+V69+X69+Z69 -> 31737342 | P69: 519493587 | Q69: 0 | R69: 31737342 | S69: 14400000 | T69: 0 | U69: 0 | V69: 0 | W69: 0 | X69: 0 | Y69: 0 | Z69: 0 | AA69: 0 | AB69: El principal beneficio de la UNIDAD DE ATENCION DE EMERGENCIA POR INSUFICIENCIA RESPIRATORIA es la rápida implementación y el bajo costo, esto permitirá aumentar la cobertura de la atención de pacientes con infecciones respiratorias agudas (SARS-Cov-2 entre ellas) en zonas de difícil acceso o con limitada disponibilidad de recursos hospitalarios, principalmente respiradores mecánicos. Al usar usar la electricidad como fuente de energía, el equipo puede ser operado en hospitales temporales o incluso en espacios con adecuación mínima para atender enfermos. Tiene el potencial de ser fabricado masivamente con un bajo costo, lo que amplía las posibilidades de adquisición. La mayoría de los componentes son usados comercialmente en la actualidad, facilitando la construcción, mantenimiento y entrenamiento del personal médico. | AC69: =+IFERROR(P69/L69,0%) -> 0.91843207 | AD69: =+IFERROR((Q69+R69)/L69,0%) -> 0.05610963 | AE69: =IFERROR(Q69/(Q69+R69),0%) -> 0 | AF69: =IFERROR(R69/(Q69+R69),0%) -> 1 | AG69: =+IFERROR((S69+T69)/L69,0%) -> 0.025458297 | AH69: =+IFERROR((U69+V69)/L69,0%) -> 0 | AI69: =+IFERROR((W69+X69)/L69,0%) -> 0 | AJ69: =+IFERROR((Y69+Z69)/L69,0%) -> 0
A70: 2022 | B70: Propuesta de Investigación Alianza Convenio | C70: Contrato firmado | D70: N/A | E70: CONVOCATORIA PARA LA CONFORMACIÓN DEL BANCO DE PROYECTOS Y PROGRAMAS DE INVESTIGACIÓN E INNOVACIÓN DE LA CORPORACIÓN UNIVERSITARIA IBEROAMERICANA | F70: Corporación Universitaria Iberoamericana | G70: Aliado | H70: 1- Corporación Universitaria Iberoamericana 2- Empresa Vértice SAS 3- Corporación Inclusive Movimiento | I70: N/A | J70: 10 | K70: UDFJC: - -Grupo de Investigación Interdisciplinaria en Pedagogía del Lenguaje y las Matemáticas-GIIPLyM, -Grupo de Investigación - Literatura, Educación y Comunicación (LEC) IBERO: - Grupo en Investigación y Escenarios de Educación Pedagógica - GIEEP - | L70: =+SUM(P70:Z70) -> 92497760 | M70: 0 | N70: =+P70+Q70+S70+U70+W70+Y70 -> 5000000 | O70: =+R70+T70+V70+X70+Z70 -> 87497760 | P70: 0 | Q70: 0 | R70: 40700000 | S70: 5000000 | T70: 34797760 | U70: 0 | V70: 6000000 | W70: 0 | X70: 6000000 | Y70: 0 | Z70: 0 | AA70: - Sistema de validación con categorías, unidades de análisis e instrumentos - Documento con Ajuste de los referentes didácticos formulados en la fase I - Identificación entre las relaciones de las hipótesis propuestas y el desarrollo de la evolución. - Identificación de los aspectos de refinación en el diseño - Diseño didáctico refinado y sistema de actividades e instrumentos para realizar la evolución del diseño - Registro y sistematización de la evolución del diseño - Reformulación definitiva de requerimientos didácticos a partir del proceso de validación | AB70: - Un Artículo postulado a revista indexada Q1. - Tres Prototipos de talleres para formación de estudiantes para profesor validados. - Sistema de validación de requerimientos de acuerdo con la revisión, identificación entre las relaciones de las hipótesis propuestas y el desarrollo de la evolución, así como los aspectos de refinación en el diseño. Diseños refinados - Un Informe de análisis de potencialidades de recursos tecnológicos ampliado por efecto de la validación. - Un Diseño didáctico validado de un sistema de talleres para formar profesores en el diseño y validación de AAAA para desarrollar experiencias estéticas en lenguaje y en artes. - Dos Trabajos de grado en el tema de validación didáctica de ambientes de aprendizaje para el desarrollo de experiencias estéticas en lenguaje y en artes. | AC70: =+IFERROR(P70/L70,0%) -> 0 | AD70: =+IFERROR((Q70+R70)/L70,0%) -> 0.44001066 | AE70: =IFERROR(Q70/(Q70+R70),0%) -> 0 | AF70: =IFERROR(R70/(Q70+R70),0%) -> 1 | AG70: =+IFERROR((S70+T70)/L70,0%) -> 0.43025647 | AH70: =+IFERROR((U70+V70)/L70,0%) -> 0.064866436 | AI70: =+IFERROR((W70+X70)/L70,0%) -> 0.064866436 | AJ70: =+IFERROR((Y70+Z70)/L70,0%) -> 0
A71: 2020 | B71: Propuesta de Investigación Convocatoria | C71: No Avalada | D71: 874 | E71: CONVOCATORIA PARA EL FORTALECIMIENTO DE PROYECTOS EN EJECUCIÓN DE CTeI EN CIENCIAS DE LA SALUD CON TALENTO JOVEN E IMPACTO REGIONAL | F71: MinCiencias | G71: Ejecutor | H71: N/A | I71: N/A | J71: 13 | K71: Interoperabilidad Tecnológica y Semántica | L71: =+SUM(P71:Z71) -> 173040000 | M71: 0 | N71: =+P71+Q71+S71+U71+W71+Y71 -> 168000000 | O71: =+R71+T71+V71+X71+Z71 -> 5040000 | P71: 168000000 | Q71: 0 | R71: 5040000 | S71: 0 | T71: 0 | U71: 0 | V71: 0 | W71: 0 | X71: 0 | Y71: 0 | Z71: 0 | AA71: - Diagnóstico participativo para la definición y/fortalecimiento de la problemática a abordar: entendido como una actividad para el encuentro entre investigadores y actores involucrados en la investigación. El diagnóstico permite evidenciar las expectativas del grupo de jóvenes y las de la comunidad, ampliar la identificación de temas de interés y la negociación sobre los mismos frente a las distintas problemáticas. Así, el proceso de investigación de investigación es resultado del diálogo de saberes entre investigadores y comunidad – actores locales, en pleno reconocimiento del contexto social, y con una clara intención de impacto. Como parte de este diagnóstico se debe realizar la identificación y caracterización de los actores, así: actores vinculados activamente al desarrollo del proceso de investigación, aliados, población afectada, población beneficiada, otros grupos de interés. - Lectura del entorno para medición y seguimiento: esta actividad consiste en la realización de una lectura que incluya información sobre prácticas ciudadanas, estado actual de las problemáticas que se estudian, contexto social, económico, normativo y geográfico. Esta información se obtiene de fuentes primarias y secundarias, teniendo en cuenta que las voces de los actores locales y de las comunidades son fundamentales para el desarrollo de la investigación. A partir de esta línea, se definen los indicadores de seguimiento y resultado, tanto de la investigación como de su impacto en la comunidad(es) participantes. De esta manera, los jóvenes talento, podrán dar cuenta al finalizar su investigación, de los resultados obtenidos. - Diseño e implementación metodológico desde un enfoque participativo: describe las etapas y actividades dirigidas a la vinculación de la comunidad y a la co-elaboración de cada uno de los insumos y productos del proceso investigativo, así como la generación o vinculación a redes o alianzas. Es importante que el grupo de investigación parta de reconocer a las personas de la comunidad como integrantes activos de la investigación. Como actividades de investigación, la observación, indagación, recolección de datos, análisis de información, entre otras, deben realizarse de manera conjunta entre investigadores y comunidad, y otros actores identificados. | AB71: - Artículo en autoría o co - autoría en formato de revista indexada con parámetros para ser publicado en una revista categorizada (categorías A1, A2, B y C) o Capítulo en libro resultado de investigación - Capítulo de libro o borrador para ser sometido a evaluación. Este producto será entregado por proyecto, en el cual se mencionen los jóvenes talento que participaron. - Informe Técnico Final de las actividades de CTeI desarrolladas y los resultados de investigación obtenidos por el joven en el marco del proyecto. Para los jóvenes que realizan su pasantía en el exterior, se debe entregar un informe de las actividades de CTeI y resultados de la estancia de investigación en el exterior. | AC71: =+IFERROR(P71/L71,0%) -> 0.97087379 | AD71: =+IFERROR((Q71+R71)/L71,0%) -> 0.029126214 | AE71: =IFERROR(Q71/(Q71+R71),0%) -> 0 | AF71: =IFERROR(R71/(Q71+R71),0%) -> 1 | AG71: =+IFERROR((S71+T71)/L71,0%) -> 0 | AH71: =+IFERROR((U71+V71)/L71,0%) -> 0 | AI71: =+IFERROR((W71+X71)/L71,0%) -> 0 | AJ71: =+IFERROR((Y71+Z71)/L71,0%) -> 0
A72: 2020 | B72: Propuesta de Investigación Convocatoria | C72: Contrato firmado | D72: 869 | E72: CONVOCATORIA PARA EL REGISTRO DE PROYECTOS QUE ASPÍRAN A OBTENER BENEFICIOS TRIBUTARIOS POR INVERSIÓN EN CTeI A PARTIR DEL AÑO 2020. | F72: MinCiencias | G72: Supervisor Técnico | H72: Banco Agrario de Colombia | I72: N/A | J72: 12 | K72: “Laboratorio de Automatización, Sistemas Embebidos y Robótica - LASER” | L72: =+SUM(P72:Z72) -> 1116098162 | M72: 0 | N72: =+P72+Q72+S72+U72+W72+Y72 -> 1116098162 | O72: =+R72+T72+V72+X72+Z72 -> 0 | P72: 0 | Q72: 19057103 | R72: 0 | S72: 1097041059 | T72: 0 | U72: 0 | V72: 0 | W72: 0 | X72: 0 | Y72: 0 | Z72: 0 | AA72: OE1.P1. Diseño de prototipo tecnológico que facilite la comercialización de productos agropecuarios. OE1.P2. Requerimiento del desarrollo de software que permita la implementación del mínimo producto viable del prototipo diseñado OE1.P3. Manuales técnicos y de usuario de la plataforma OE1.P1. Desarrollo tecnológico que permita la comunicación efectiva entre productor agropecuario y comercializador para facilitar la logística de trasporte OE2.P2. Manual técnico y de Usuario de uso de plataforma OE3.P1. Campaña de capacitación para clientes internos y externos del Banco. OE3.P2. Tutorial de uso de la plataforma por medios audiovisuales y documentales. OE3.P3. Piloto implementado en campo para probar las funcionalidades del Mínimo Producto Viable, y la experiencia de usuario. OE3.P4. Informe de hallazgos y resultados de la implementación de prototipo en Banco. OE3.P5. Artículo de investigación sobre resultados. | AB72: Dos Campañas de capacitación para clientes internos y externos del Banco sobre el uso de la plataforma - Un Tutorial publicado y socializado sobre el uso de la plataforma por medios audiovisuales y documentales - Dos Manuales técnico y manual de usuario. Comunicación efectiva entre productor agropecuario y comercializador para facilitar la logística de trasporte. - Un prototipo: El desarrollo a la medida contemplará un mínimo producto viable con las siguientes características: Publicar productos agropecuarios a vender. Inscripción cuenta de ahorro o corriente del Banco para recibir pagos o giros. Inscripción de persona o mayorista para la compra de productos. Compra de productos a través del botón de pago del Banco. Concertar logística de transporte entre productor agropecuario y comercializador. - Un artículo publicado y socializado sobre hallazgos de los resultados de la implementación de prototipo en Banco. | AC72: =+IFERROR(P72/L72,0%) -> 0 | AD72: =+IFERROR((Q72+R72)/L72,0%) -> 0.017074755 | AE72: =IFERROR(Q72/(Q72+R72),0%) -> 1 | AF72: =IFERROR(R72/(Q72+R72),0%) -> 0 | AG72: =+IFERROR((S72+T72)/L72,0%) -> 0.98292524 | AH72: =+IFERROR((U72+V72)/L72,0%) -> 0 | AI72: =+IFERROR((W72+X72)/L72,0%) -> 0 | AJ72: =+IFERROR((Y72+Z72)/L72,0%) -> 0
A73: 2020 | B73: Propuesta de Investigación Convocatoria | C73: No Avalada | D73: 879 | E73: CONVOCATORIA ENERGÍA SOSTENIBLE Y SU APORTE A LA PLANEACIÓN MINERO ENERGÉTICA – 2020 | F73: MinCiencias | G73: Ejecutor | H73: 1- Universidad de Cundinamarca UdeC | I73: N/A | J73: 14 | K73: UDFJC: - GIEAUD - DISING UdeC: - GITEINCO | L73: =+SUM(P73:Z73) -> 694161800 | M73: 0 | N73: =+P73+Q73+S73+U73+W73+Y73 -> 448060000 | O73: =+R73+T73+V73+X73+Z73 -> 246101800 | P73: 448060000 | Q73: 0 | R73: 236391800 | S73: 0 | T73: 9710000 | U73: 0 | V73: 0 | W73: 0 | X73: 0 | Y73: 0 | Z73: 0 | AA73: Plan de divulgación técnica: - Organización de 1 evento de divulgación de resultados de investigación en el mes 7 de la investigación. - Organización de 1 evento de divulgación de resultados de investigación en el mes 14 de la investigación. - Construcción de 1 página web donde se podrá acceder a todo el historial de los productos así como guías para la instalación de los proyectos. - Creación de una red de conocimiento especializado con la Universidad de Louisiana. - 1 curso de capacitación, en generación de archivos climáticos - 1 curso de capacitación, en el manejo de la herramienta Trnsys V18 - 1 curso de capacitación, en tecnologías de generación eléctrica solar, eólica y mediante turbina de río. | AB73: - Vinculación de 2 estudiantes de maestría en el marco del proyecto. - Vinculación de 6 estudiantes de pregrado, para fortalecer los procesos de investigación formativa de la Universidad Distrital F.J.C. - 1 Artículo de investigación publicado o con carta de aceptación, en revista indexada en categoría A1. - 1 Artículo de investigación publicado o con carta de aceptación, en revista indexada en categoría A2. - 1 Libro resultado de investigación categoría B. - 1 planta piloto para probar las capacidades de generación de cada una de las tecnologías. - Nuevo registro científico de mapas vectoriales generados a partir de la investigación - Consultoría e informes técnicos parciales - Consultoría e informes técnicos finales | AC73: =+IFERROR(P73/L73,0%) -> 0.64546911 | AD73: =+IFERROR((Q73+R73)/L73,0%) -> 0.3405428 | AE73: =IFERROR(Q73/(Q73+R73),0%) -> 0 | AF73: =IFERROR(R73/(Q73+R73),0%) -> 1 | AG73: =+IFERROR((S73+T73)/L73,0%) -> 0.013988093 | AH73: =+IFERROR((U73+V73)/L73,0%) -> 0 | AI73: =+IFERROR((W73+X73)/L73,0%) -> 0 | AJ73: =+IFERROR((Y73+Z73)/L73,0%) -> 0
A74: 2020 | B74: Propuesta de Investigación Convocatoria | C74: No Avalada | D74: 879 | E74: CONVOCATORIA ENERGÍA SOSTENIBLE Y SU APORTE A LA PLANEACIÓN MINERO ENERGÉTICA – 2020 | F74: MinCiencias | G74: Ejecutor | H74: N/A | I74: N/A | J74: 14 | K74: LIDER (Laboratorio de Investigación y Desarrollo en Electrónica y Redes) | L74: =+SUM(P74:Z74) -> 688180615 | M74: 0 | N74: =+P74+Q74+S74+U74+W74+Y74 -> 411180615 | O74: =+R74+T74+V74+X74+Z74 -> 277000000 | P74: 379180615 | Q74: 32000000 | R74: 277000000 | S74: 0 | T74: 0 | U74: 0 | V74: 0 | W74: 0 | X74: 0 | Y74: 0 | Z74: 0 | AA74: - Diseño e implementación de un proceso para el mejoramiento de la formulación, gestión, seguimiento y evaluación de los planes misionales y los proyectos derivados de éstos, por parte de la UPME: Medios de verificación: • Documento de diagnóstico que contenga los escenarios: As- Is, To- Be y Análisis de brecha. • Documento de recomendaciones y buenas prácticas de gestión de proyectos. • Propuesta metodológica para la gestión de los proyectos de la UPME. • Proceso para la formulación, gestión, seguimiento y cierre de proyectos. • Definición y diseño de la PMO • Flujo de procesos. • Batería de Indicadores y metas para la medición de la gestión de los proyectos y fichas de indicadores. • Diseño del Tablero de seguimiento, monitoreo y control • Diseño y especificación de requerimientos generales para la herramienta de software para gestión de proyectos de la UPME. • Plan de acción y Cronograma para la implementación del proceso y la propuesta metodológica de gestión de proyectos. • Documento con la descripción de los Resultados de la implementación. • Documento de lecciones aprendidas. • Medición inicial de Indicadores de desempeño. • Tablero de monitoreo, seguimiento y control | AB74: - Participación en un evento especializados, presentando los resultados del proyecto - Dos artículos de investigación C. - Dos presentaciones de los resultados ante las autoridades competentes - Diseño e implementación de un proceso para el mejoramiento de la formulación, gestión, seguimiento y evaluación de los planes misionales y los proyectos derivados de éstos, por parte de la UPME | AC74: =+IFERROR(P74/L74,0%) -> 0.55098997 | AD74: =+IFERROR((Q74+R74)/L74,0%) -> 0.44901003 | AE74: =IFERROR(Q74/(Q74+R74),0%) -> 0.10355987 | AF74: =IFERROR(R74/(Q74+R74),0%) -> 0.89644013 | AG74: =+IFERROR((S74+T74)/L74,0%) -> 0 | AH74: =+IFERROR((U74+V74)/L74,0%) -> 0 | AI74: =+IFERROR((W74+X74)/L74,0%) -> 0 | AJ74: =+IFERROR((Y74+Z74)/L74,0%) -> 0
A75: 2020 | B75: Propuesta de Investigación Convocatoria | C75: No Avalada | D75: 879 | E75: CONVOCATORIA ENERGÍA SOSTENIBLE Y SU APORTE A LA PLANEACIÓN MINERO ENERGÉTICA – 2020 | F75: MinCiencias | G75: Ejecutor | H75: 1- Fundación Universitaria Panamericana 2- Corporación Tecnológica Industrial Colombiana 3- Instituto Tecnológico de Ciudad Juárez | I75: N/A | J75: 12 | K75: UDFJC: GRUPO ADQUISICIÓN Y REPRESENTACIÓN DEL CONOCIMIENTO - SISTEMAS EXPERTOS Y SIMULACIÓN (ARCO SES) FUP: GRUPO DE INVESTIGACIÓN EN INGENIERÍAS - GIIS TEINCO: INNOVATEC | L75: =+SUM(P75:Z75) -> 840660000 | M75: 0 | N75: =+P75+Q75+S75+U75+W75+Y75 -> 644200000 | O75: =+R75+T75+V75+X75+Z75 -> 196460000 | P75: 640000000 | Q75: 0 | R75: 63500000 | S75: 0 | T75: 36984000 | U75: 0 | V75: 36984000 | W75: 4200000 | X75: 58992000 | Y75: 0 | Z75: 0 | AA75: - Una red de investigación Colombo - Mexicana - Participación de cienco (5) Congresos Internacionales de Investigación - Curso de eficiencia energética - energías renovables - Curso de gestión Tecnológica - Formación de nueve (9) estudiantes de pregrado | AB75: - Dos capítulos de libro de investigación categoría B - Dos artículos de investigación categoría B - Dos consultorías de los procesos - Un informe técnico final - Un software de Gestión Tecnológica | AC75: =+IFERROR(P75/L75,0%) -> 0.76130659 | AD75: =+IFERROR((Q75+R75)/L75,0%) -> 0.075535888 | AE75: =IFERROR(Q75/(Q75+R75),0%) -> 0 | AF75: =IFERROR(R75/(Q75+R75),0%) -> 1 | AG75: =+IFERROR((S75+T75)/L75,0%) -> 0.043994005 | AH75: =+IFERROR((U75+V75)/L75,0%) -> 0.043994005 | AI75: =+IFERROR((W75+X75)/L75,0%) -> 0.07516951 | AJ75: =+IFERROR((Y75+Z75)/L75,0%) -> 0
A76: 2020 | B76: Propuesta de Investigación Convocatoria | C76: No Avalada | D76: 10 | E76: CONVOCATORIA DEL FONDO CTEI DEL SGR PARA EL FORTALECIMIENTO DE CAPACIDADES DE INVESTIGACIÓN Y DESARROLLO REGIONALES E INICIATIVAS DE CTeI Y TRANSFERENCIA DE TECNOLOGÍA Y CONOCIMIENTO ORIENTADAS A ATENDER PROBLEMÁTICAS DERIVADAS DEL COVID-19 | F76: MinCiencias | G76: Co-ejecutor | H76: 1- Corporación Universitaria Remington 2- Secretaria de Educación Municipal de Montería - Cordoba | I76: N/A | J76: 24 | K76: LIDER (Laboratorio de Investigación y Desarrollo en Electrónica y Redes) | L76: =+SUM(P76:Z76) -> 2892715428 | M76: 0 | N76: =+P76+Q76+S76+U76+W76+Y76 -> 2598715428 | O76: =+R76+T76+V76+X76+Z76 -> 294000000 | P76: 2528510580 | Q76: 30204848 | R76: 150000000 | S76: 40000000 | T76: 144000000 | U76: 0 | V76: 0 | W76: 0 | X76: 0 | Y76: 0 | Z76: 0 | AA76: - Perfil sociodemográfico y psicográfico de los estudiantes de educación virtual, identificando su perfil tecnológico, su historia de interacción con entornos virtuales y sus competencias de autorregulación. - Evidencia, a partir de las actividades de investigación y la metodología descrita, de los componentes pedagógicos necesarios para la implementación del programa. | AB76: - Ocho Informes técnicos y financieros de ejecución presentados trismestralmente durante la ejecución del proyecto - Tesis de pregrado, dos tesis de maestria y dos tesis de doctorado, un libro de investigación, dos documentos de investigación. - Publicación de seis artículos de investigación en revistas indexadas de cuartil Q1 y Q3 - Trámite de una patente resultado del proyecto - Para la producción de un libro de investigación - Cuatro cursos como servicio de apoyo para entrenamiento especializado para científicos investigadores - Una estrategía como servicios de comunicación con enfoque en Ciencia, Tecnología y Sociedad - Un servicio de apoyo para el desarrollo tecnológico y la innovación | AC76: =+IFERROR(P76/L76,0%) -> 0.87409586 | AD76: =+IFERROR((Q76+R76)/L76,0%) -> 0.062296086 | AE76: =IFERROR(Q76/(Q76+R76),0%) -> 0.16761396 | AF76: =IFERROR(R76/(Q76+R76),0%) -> 0.83238604 | AG76: =+IFERROR((S76+T76)/L76,0%) -> 0.063608054 | AH76: =+IFERROR((U76+V76)/L76,0%) -> 0 | AI76: =+IFERROR((W76+X76)/L76,0%) -> 0 | AJ76: =+IFERROR((Y76+Z76)/L76,0%) -> 0
A77: 2020 | B77: Propuesta de Investigación Convocatoria | C77: No Avalada | D77: ANE | E77: CONVOCATORIA DE INVESTIGACIONES 2021 PARA PRESENTAR PROYECTOS DE CT+I EN TEMÁTICAS RELACIONADAS CON LA GESTIÓN, PLANEACIÓN, ATRIBUCIÓN, VIGILANCIA Y CONTROL DEL ESPECTRO RADIOELÉCTRICO EN COLOMBIA. | F77: Agencia Nacional del Espectro - ANE | G77: Ejecutor | H77: N/A | I77: N/A | J77: 12 | K77: 1- Grupo de investigación Gestión e Investigación en Informática, Redes y Afines (GIIRA) 2- Grupo de Investigación de Telecomunicaciones de la universidad Distrital Francisco José de Caldas (GITUD) | L77: =+SUM(P77:Z77) -> 354827930 | M77: 0 | N77: =+P77+Q77+S77+U77+W77+Y77 -> 224768147 | O77: =+R77+T77+V77+X77+Z77 -> 130059783 | P77: 223872647 | Q77: 895500 | R77: 130059783 | S77: 0 | T77: 0 | U77: 0 | V77: 0 | W77: 0 | X77: 0 | Y77: 0 | Z77: 0 | AA77: Fase 1: revisión del estado del arte El resultado esperado de esta fase es una caracterización completa del uso, manipulación y tratamiento de la señal usada por un operador que opere en la banda VHF con presencia en la zona urbana del departamento de Cundinamarca. Entre ellos se pretende establecer cuales tienen mayor ocupación del espectro y por ende mayor influencia sobre las zonas que hacen parte del proyecto. Fase 2: adquisición de datos en campo En esta etapa se pretende desarrollar toda la adquisición, validación, almacenamiento, y verificación de datos confinados en un informe que unifique, demuestre y justifique con validez la integridad de los datos, que relacione las justificaciones en la medición y relacione las características usadas para las mismas. En esta sección de pruebas de campo se deben realizar mediciones de prueba, donde se valide el funcionamiento del método de medición seleccionado mediante la captura de señales con el dispositivo de vuelo no tripulado, asegurando la integridad y validez de los datos siguiendo las recomendaciones internacionales, además, debe evidenciarse la captura de datos usados para el estudio relacionando con firmeza el factor de los parámetros a evaluar dentro de la identificación de la señal interferente. Fase 3: análisis de datos Esta fase debe entregar un informe de toda la información extraída de los datos obtenidos, en el cual se establezcan los patrones más relevantes de la señal, los niveles obtenidos, las correlaciones y correspondencia con simulaciones, cálculos esperados y demostrar de forma adecuada que cumple con los requisitos establecidos por las entidades estatales. Se debe hacer una verificación de la exposición a CEM logrando identificar, si existen, las zonas donde la medición sea relevante para el usuario. En este análisis se pretende descubrir y establecer que fuentes de transmisión presentan los niveles más altos, los niveles con mejor recepción y cuales se ven más afectadas por las señales en la misma banda. A partir del análisis establecer los parámetros de la señal interferente identificada y lograr extraer de ella la base científica que permita diseñar la metodología de la señal interferente. Fase 4: Desarrollo de base científica para metodología Esta fase debe ser la última del proyecto, donde se aprovechen todos los análisis hechos anteriormente, y se relacione la información con las metodologías desarrolladas bajo otras mediciones y entornos. Con lo cual se espera establecer la base científica para los modelos que se deben lograr a futuro respecto a la identificación de la señal interferente, una metodología de medición de la señal interferente y los patrones que ella presente. Además de vincular a partir de la medición hecha la base científica para el modelamiento de una metodología de diseño basada en parámetros de calidad de servicio vinculados al modelo de propagación escogido basado en la medición de la señal en el entorno urbano del proyecto. | AB77: 1- Un (1) Artículo aceptado para publicación en Revista Indexada como A1, A2 o B en la clasificación Publindex, y/o incluida en ISI, Scopus o SciELO 2- Informe final de Investigación 3- Formación de dos (2) estudiantes de programas de maestría de la Universidad Distrital 4- Resultados parciales de Tesis Doctoral 5- Desarrollo de un curso – taller dirigido a estudiantes de pregrado o posgrado sobre señales interferentes en RF 6- Presentación de una ponencia en eventos científicos basada en los resultados de investigación. 7- Documento Final de Investigación de los proyectos de pregrado vinculados en el Proyecto | AC77: =+IFERROR(P77/L77,0%) -> 0.63093299 | AD77: =+IFERROR((Q77+R77)/L77,0%) -> 0.36906701 | AE77: =IFERROR(Q77/(Q77+R77),0%) -> 0.0068382121 | AF77: =IFERROR(R77/(Q77+R77),0%) -> 0.99316179 | AG77: =+IFERROR((S77+T77)/L77,0%) -> 0 | AH77: =+IFERROR((U77+V77)/L77,0%) -> 0 | AI77: =+IFERROR((W77+X77)/L77,0%) -> 0 | AJ77: =+IFERROR((Y77+Z77)/L77,0%) -> 0
A78: 2020 | B78: Propuesta de Investigación Convocatoria | C78: No Avalada | D78: 891 | E78: Vocaciones y Formación en CTeI para la reactivación económica en el marco de la Postpandemia 2020 | F78: MinCiencias | G78: Ejecutor | H78: N/A | I78: N/A | J78: 12 | K78: Laboratorio de Investigación en Fuentes Alternativas de Energía - LIFAE | L78: =+SUM(P78:Z78) -> 96000000 | M78: 0 | N78: =+P78+Q78+S78+U78+W78+Y78 -> 96000000 | O78: =+R78+T78+V78+X78+Z78 -> 0 | P78: 96000000 | Q78: 0 | R78: 0 | S78: 0 | T78: 0 | U78: 0 | V78: 0 | W78: 0 | X78: 0 | Y78: 0 | Z78: 0 | AA78: - Estrategia de control basada en aprendizaje de máquina aplicada a convertidores eléctricos en microrredes aisladas, capaz de adaptarse a perfiles de generación variables y perturbaciones. - Productos y resultados de actividades de Apropiación Social del Conocimiento: participación en ponencia nacional-internacional. - Productos y resultados de actividades de Generación de Nuevo Conocimiento: 1 artículo original enviado para evaluación a revista indexada categoría A1-A2-B Publindex. | AB78: 0 | AC78: =+IFERROR(P78/L78,0%) -> 1 | AD78: =+IFERROR((Q78+R78)/L78,0%) -> 0 | AE78: =IFERROR(Q78/(Q78+R78),0%) -> 0 | AF78: =IFERROR(R78/(Q78+R78),0%) -> 0 | AG78: =+IFERROR((S78+T78)/L78,0%) -> 0 | AH78: =+IFERROR((U78+V78)/L78,0%) -> 0 | AI78: =+IFERROR((W78+X78)/L78,0%) -> 0 | AJ78: =+IFERROR((Y78+Z78)/L78,0%) -> 0
A79: 2020 | B79: Propuesta de Investigación Convocatoria | C79: No Avalada | D79: 890 | E79: Convocatoria para el Fortalecimiento de CTeI en Instituciones de Educación Superior (IES) Públicas 2020 Mecanismo 1 | F79: MinCiencias | G79: Ejecutor | H79: 1- Universidad de Cundinamarca UdeC (Aliado) 2- Universidad Central UC (Cooperante) 3- Unidades Tecnológicas de Santander UTS (Aliado) | I79: N/A | J79: 36 | K79: UDFJC: Grupo de Instrumentación Cientifica & Didáctica UdeC: Nanoingeniería UC: Grupo de investigación en Bioingeniería, Nanotecnología y Telecomunicaciones (SPIN) UTS: Grupo de Investigación en Diseño y Materiales DIMAT | L79: =+SUM(P79:Z79) -> 809754417 | M79: 0 | N79: =+P79+Q79+S79+U79+W79+Y79 -> 575194673 | O79: =+R79+T79+V79+X79+Z79 -> 234559744 | P79: 549913947 | Q79: 25280726 | R79: 140200000 | S79: 0 | T79: 44399808 | U79: 0 | V79: 36730944 | W79: 0 | X79: 13228992 | Y79: 0 | Z79: 0 | AA79: - Síntesis y caracterización fisicoquímica de tres familias de nanomateriales: óxidos de grafeno multicapa, nanoestructuras de óxidos de hierro (magnetita y hematita) y semiconductores calcogénidos fotocatalíticos (SnS y ZnS). - Aplicación de estas tres familias de nanomateriales en la remediación y tratamiento de muestras de aguas rurales y urbanas de la ciudad de Bogotá - 2 artículos publicado en revista internacional - 1 tesis de pregrado y de maestría defendida - Participación en Congresos/Ponencias/Conferencias/Workshops/Conversatorios Internacionales - Participación de dos jóvenes investigadores en la elaboración de la investigación | AB79: - Dos artículos de categoría A2 y B - Tres participaciones en congresos nacionales e internacionales sobre nuevos materiales y medio ambiente - Tres Artículos y videos divulgativos del proyecto para público especializado - Dos Artículo divulgativo sobre la aplicación de nanomateriales en remedicación de aguas - Cuatro Participaciones en simposios, congresos, meetings del área de nanomateriales - Realización de un trabajo de fin de grado (pregrado) relacionado con el proyecto - Realización de dos tesis de maestría relacionada con el proyecto | AC79: =+IFERROR(P79/L79,0%) -> 0.67911201 | AD79: =+IFERROR((Q79+R79)/L79,0%) -> 0.20435915 | AE79: =IFERROR(Q79/(Q79+R79),0%) -> 0.15277142 | AF79: =IFERROR(R79/(Q79+R79),0%) -> 0.84722858 | AG79: =+IFERROR((S79+T79)/L79,0%) -> 0.054831202 | AH79: =+IFERROR((U79+V79)/L79,0%) -> 0.045360597 | AI79: =+IFERROR((W79+X79)/L79,0%) -> 0.016337042 | AJ79: =+IFERROR((Y79+Z79)/L79,0%) -> 0
A80: 2020 | B80: Propuesta de Investigación Convocatoria | C80: No Avalada | D80: 890 | E80: Convocatoria para el Fortalecimiento de CTeI en Instituciones de Educación Superior (IES) Públicas 2020 Mecanismo 1 | F80: MinCiencias | G80: Ejecutor | H80: 1- Universidad de Cundinanmarca UdeC (Aliado) 2- Escuela Tecnológica Instituto Técnico Central ETITC (Aliado) | I80: N/A | J80: 24 | K80: UDFJC: GIIRA UdeC: ETITC: | L80: =+SUM(P80:Z80) -> 722133857 | M80: 0 | N80: =+P80+Q80+S80+U80+W80+Y80 -> 595733857 | O80: =+R80+T80+V80+X80+Z80 -> 126400000 | P80: 549385859 | Q80: 46347998 | R80: 62300000 | S80: 0 | T80: 16000000 | U80: 0 | V80: 48100000 | W80: 0 | X80: 0 | Y80: 0 | Z80: 0 | AA80: - Con el modelo de predicción a desarrollar se mejorará la predicción de ruido ambiental en un entorno urbano de Bogotá al considerar variables propias del ambiente. Esta herramienta permitirá a las entidades gubernamentales generar procesos de gestión de ruido en acústica ambiental para mejorar el bienestar de la sociedad. - Herramienta informática para el registro y análisis datos objetivos y subjetivos del entorno acústico | AB80: - Dos artículos de investigación categoría A1 y A2 - Un libro categoría A, donde se evidencien los resultados detallados de la implementación del modelo, capítulos por cada institución participante. - Dos ponencias en Congresos Internacionales - Proyecto que vincula a estudiante de pregrado de la Universidad de Cundinamarca - Proyecto que vincula a estudiante de maestría de la Universidad Distrital Francisco José de Caldas - Proyecto que vincula a estudiante del doctorado de la Universidad Distrital Francisco José de Caldas | AC80: =+IFERROR(P80/L80,0%) -> 0.7607812 | AD80: =+IFERROR((Q80+R80)/L80,0%) -> 0.1504541 | AE80: =IFERROR(Q80/(Q80+R80),0%) -> 0.42658861 | AF80: =IFERROR(R80/(Q80+R80),0%) -> 0.57341139 | AG80: =+IFERROR((S80+T80)/L80,0%) -> 0.022156557 | AH80: =+IFERROR((U80+V80)/L80,0%) -> 0.06660815 | AI80: =+IFERROR((W80+X80)/L80,0%) -> 0 | AJ80: =+IFERROR((Y80+Z80)/L80,0%) -> 0
A81: 2020 | B81: Propuesta de Investigación Convocatoria | C81: Contrato firmado | D81: 890 | E81: Convocatoria para el Fortalecimiento de CTeI en Instituciones de Educación Superior (IES) Públicas 2020 Mecanismo 2 | F81: MinCiencias | G81: Ejecutor | H81: 1- Unidad Administrativa Especial de Rehabilitación y Mantenimiento Vial -UMV | I81: N/A | J81: 20 | K81: UDFJC: Grupo de Estudios en Pavimentos y materiales Sostenibles - COL0154879 UMV: Grupo de Adopción y adaptación de nuevas Tecnologías COL0217094 | L81: =+SUM(P81:Z81) -> 780809454 | M81: 449981010 | N81: =+P81+Q81+S81+U81+W81+Y81 -> 606145810 | O81: =+R81+T81+V81+X81+Z81 -> 174663644 | P81: 449981010 | Q81: 59561452 | R81: 83985194 | S81: 96603348 | T81: 90678450 | U81: 0 | V81: 0 | W81: 0 | X81: 0 | Y81: 0 | Z81: 0 | AA81: Los resultados esperados del presente proyecto se pueden clasificar en cuatro productos diferentes, en primer lugar, en el desarrollo tecnológico en el que se pondrá al servicio de la Unidad de Mantenimiento Vial para contribuir con el cumplimiento de su misión. En segundo lugar, con la formación de investigadores, en donde se vincularán 4 estudiantes de maestría y se espera que cada uno produzca un resultado de investigación y en tercer lugar con la apropiación social del conocimiento, en donde se divulgarán los resultados en eventos internos de la Unidad de Mantenimiento Vial con la participación de las entidades distritales que pueden ser beneficiadas de la tecnología desarrollada. Finalmente, se esperan resultados desde el punto de vista comercial en donde se dará impulso a la marca y la comercialización del producto o de los servicios derivados. | AB81: Cuatro artículos de investigación categoria C - Un Producto Tecnológico, Sistema de mapeo móvil de entornos viales. - Dos Trabajos de grado de pregrado - Vinculación de Cuatro estudiantes de maestría - Consolidación de una red de investigación, Virginia Tech Estados Unidos - Divulgación de los resultados en dos eventos académicos nacionales como el Simposio Nacional sobre Ingeniería de Pavimentos, y el Congreso Iberoamericano del asfalto - Foro de presentación de los resultados de la tecnología | AC81: =+IFERROR(P81/L81,0%) -> 0.57630067 | AD81: =+IFERROR((Q81+R81)/L81,0%) -> 0.18384338 | AE81: =IFERROR(Q81/(Q81+R81),0%) -> 0.41492751 | AF81: =IFERROR(R81/(Q81+R81),0%) -> 0.58507249 | AG81: =+IFERROR((S81+T81)/L81,0%) -> 0.23985596 | AH81: =+IFERROR((U81+V81)/L81,0%) -> 0 | AI81: =+IFERROR((W81+X81)/L81,0%) -> 0 | AJ81: =+IFERROR((Y81+Z81)/L81,0%) -> 0
